Workbook

Sheet Dashboard
B1: AEC Strategy Implementation
B2: 2025/2026 Dashboard
B3: 1ST JAN 2026 TO 30TH SEPT 2026
B5: Focus Area | C5: Total Outcomes | D5: Total Milestones | E5: % Complete
B6: ='Data (Master Table)'!W3 -> Financial Stability | C6: =COUNTIF('Data (Master Table)'!C3:C17, "YES") -> 4 | D6: =SUM('Financial Stability'!L:L) -> 6 | E6: =AVERAGE('Financial Stability'!R:R) -> 0.65
B7: ='Data (Master Table)'!W4 -> Youth Succession Planning | C7: =COUNTIF('Data (Master Table)'!C18:C32, "YES") -> 6 | D7: =SUM('Youth Succession Planning'!L:L) -> 34 | E7: =AVERAGE('Youth Succession Planning'!R:R) -> 0.53333333
B8: ='Data (Master Table)'!W5 -> Wider Community Engagement | C8: =COUNTIF('Data (Master Table)'!C33:C47, "YES") -> 7 | D8: =SUM('Wider Community Engagement'!L:L) -> 24 | E8: =AVERAGE('Wider Community Engagement'!R:R) -> 0.55714286
B9: ='Data (Master Table)'!W6 -> Building Teams & Leadership | C9: =COUNTIF('Data (Master Table)'!C48:C62, "YES") -> 4 | D9: =SUM('Building Teams & Leadership'!L:L) -> 12 | E9: =AVERAGE('Building Teams & Leadership'!R:R) -> 0.55
B10: ='Data (Master Table)'!W7 -> Community Activities | C10: =COUNTIF('Data (Master Table)'!C63:C77, "YES") -> 3 | D10: =SUM('Community Activities'!L:L) -> 12 | E10: =AVERAGE('Community Activities'!R:R) -> 0.7
B11: ='Data (Master Table)'!W8 -> Spiritual Focus | C11: =COUNTIF('Data (Master Table)'!C78:C91, "YES") -> 6 | D11: =SUM('Spiritual Focus'!L:L) -> 13 | E11: =AVERAGE('Spiritual Focus'!R:R) -> 0.64
B12: TOTAL | C12: =SUM(C6:C11) -> 30 | D12: =SUM(D6:D11) -> 101 | E12: =AVERAGE(E6:E11) -> 0.60507937

Sheet Instructions
A1: Tracker Instructions
A3: Purpose
A4: This workbook tracks delivery of AEC’s 2025–2026 strategy across six focus areas. All stakeholders can see the whole spreadsheet; please edit your own tab only
A6: How to update
A7: 1) Click on your focus-area tab, adjust % bottom left to enable seeing all sections
A8: 2) Scroll down to see all streams. Add notes and modify sections as required; milestones, dates, owners etc.
A9: Grey cells and risk levels are not to be changed, white cells can be amended by you. Some cells (status, % and risk cells) have drop down boxes for you to select options
A10: 3) Set Status and % Complete using drop down boxes
A11: 4) If actions are delayed, choose a Reason for Delay and add a brief note
A12: 5) When finished just close the spreadsheet, it is automatically saved. Cancel changes you made by using the Und button in the home tab of the spreadsheet. The Dashboard will update your completion % automatically
A13: 6) The Dashboard will update your completion % automatically
A15: This video shows how to use the spreadsheet: | G15: Watch Video
A17: Please note: this document and the video are Confidential – Al‑Emaan Centre Internal Use Only. Not to be shared

Sheet Financial Stability
A1: ULTIMATE AIM : ESTABLISH DIVERSIFIED, SUSTAINABLE INCOME STREAMS SLT Lead Behzat | K1: ='Data (Master Table)'!W3 -> Financial Stability
A2: ='Data (Master Table)'!C2 -> IS VALID | B2: ='Data (Master Table)'!D2 -> SMART Outcome | C2: ='Data (Master Table)'!E2 -> Benefit | D2: ='Data (Master Table)'!F2 -> Starting Point / Baseline | E2: ='Data (Master Table)'!G2 -> Department | F2: ='Data (Master Table)'!H2 -> Reported to OPEX | G2: ='Data (Master Table)'!I2 -> Responsible Person | H2: ='Data (Master Table)'!J2 -> Risk Level | ... S2: ='Data (Master Table)'!U2 -> Notes
A3: =IF('Data (Master Table)'!$B3 = $K$1, 'Data (Master Table)'!C3, "") -> YES | B3: =IF('Data (Master Table)'!$B3 = $K$1, 'Data (Master Table)'!D3, "") -> Establish diversified, sustainable income streams | C3: =IF('Data (Master Table)'!$B3 = $K$1, 'Data (Master Table)'!E3, "") -> Service provision, significant income stream to be invested in Waqf | D3: =IF('Data (Master Table)'!$B3 = $K$1, 'Data (Master Table)'!F3, "") -> Donation-dependent operations; limited reserves; no diversified income operational yet. Soft launch of TFS complete | E3: =IF('Data (Master Table)'!$B3 = $K$1, 'Data (Master Table)'!G3, "") -> Safa Holdings / Finance | F3: =IF('Data (Master Table)'!$B3 = $K$1, 'Data (Master Table)'!H3, "") -> End of March End of June End of Sept | G3: =IF('Data (Master Table)'!$B3 = $K$1, 'Data (Master Table)'!I3, "") -> Shaffiq | H3: =IF('Data (Master Table)'!$B3 = $K$1, 'Data (Master Table)'!J3, "") -> Medium | ... J3: =IF('Data (Master Table)'!$B3 = $K$1, 'Data (Master Table)'!L3, "") -> 46081 | K3: Deliver a live Funeral Service: Tahreem Funeral Service (operational & marketed) | L3: 3 | M3: 1. Cement policies & procedures 2. Hard Launch 3. Full service provision + £ | N3: 1. Jan - March 2. March 3. Mar - Sept | O3: Continuous service improvement, additional fridge set up. Imam and Funeral Director to run roadshow prior to hard launch. Thorough marketing and relationship building- cemeteries, hospitals etc. Add our website link to other masajid and Eternal Gardens website | P3: Complete | R3: 1 | S3: The launch included delivering 21 full funerals, tightening policies and procedures, adding fridges, creating leaflets, livening the website, sending emails and WhatsApp messages, building relationships with Shirley, Penge, Purley, MCWAS, Tunbridge Wells and Maidstone (including use of facilities at Maidstone and TW). Send messages to our community, making a popup for the AEC website, setting up Tahreem@group email, adding our details to the Eternal Gardens website, announcing at jumu'ah. Before hard laucnh we have made a net profit of £20k
A4: =IF('Data (Master Table)'!$B4 = $K$1, 'Data (Master Table)'!C4, "") -> YES | B4: =IF('Data (Master Table)'!$B4 = $K$1, 'Data (Master Table)'!D4, "") -> Establish diversified, sustainable income streams | C4: =IF('Data (Master Table)'!$B4 = $K$1, 'Data (Master Table)'!E4, "") -> Service provision, recurring advertising revenue + partnerships | D4: =IF('Data (Master Table)'!$B4 = $K$1, 'Data (Master Table)'!F4, "") -> Donation-dependent operations; limited reserves; no diversified income operational yet. Idea and website ready for Business Directory | E4: =IF('Data (Master Table)'!$B4 = $K$1, 'Data (Master Table)'!G4, "") -> Safa Holdings / Finance | F4: =IF('Data (Master Table)'!$B4 = $K$1, 'Data (Master Table)'!H4, "") -> End of March End of June End of Sept | G4: Shaffiq | H4: =IF('Data (Master Table)'!$B4 = $K$1, 'Data (Master Table)'!J4, "") -> Medium | I4: =IF('Data (Master Table)'!$B4 = $K$1, 'Data (Master Table)'!K4, "") -> Medium | J4: =IF('Data (Master Table)'!$B4 = $K$1, 'Data (Master Table)'!L4, "") -> 46112 | K4: Launch Green Pages Business Directory (100+ listings.) Launch through MosqueApp | L4: 1 | M4: Created website offering, Raja to launch and do intital pre registration checks | N4: 46142 | O4: Intro offer; outreach to local businesses; simple sign-up | P4: In Progress | R4: 0.9 | S4: Raja is on this iA
A5: =IF('Data (Master Table)'!$B5 = $K$1, 'Data (Master Table)'!C5, "") -> NO | B5: =IF('Data (Master Table)'!$B5 = $K$1, 'Data (Master Table)'!D5, "") -> Grow current Waqf capital by £60,000 by Sept 2026 | C5: =IF('Data (Master Table)'!$B5 = $K$1, 'Data (Master Table)'!E5, "") -> Perpetual income for AEC | D5: =IF('Data (Master Table)'!$B5 = $K$1, 'Data (Master Table)'!F5, "") -> Donation-dependent operations; limited reserves; no diversified income operational yet. Curently contains £75k | E5: =IF('Data (Master Table)'!$B5 = $K$1, 'Data (Master Table)'!G5, "") -> Finance | F5: =IF('Data (Master Table)'!$B5 = $K$1, 'Data (Master Table)'!H5, "") -> End of March End of June End of Sept | G5: =IF('Data (Master Table)'!$B5 = $K$1, 'Data (Master Table)'!I5, "") -> Raja / Kamraan | H5: =IF('Data (Master Table)'!$B5 = $K$1, 'Data (Master Table)'!J5, "") -> Low | ... J5: =IF('Data (Master Table)'!$B5 = $K$1, 'Data (Master Table)'!L5, "") -> 46203 | K5: Raise £60k additional funds for waqf investment | L5: 0 | M5: Ramadhan Waqf fundraising round 2 | N5: Last 10 days of Ramadhan | O5: Friday talks, create deck for last 10 days of Ramadhan | P5: In Progress | Q5: The amount we wanted to raise in the last 10 days of Ramadhan was not realised | S5: Will look to HNW network to achieve this
A6: =IF('Data (Master Table)'!$B6 = $K$1, 'Data (Master Table)'!C6, "") -> YES | B6: =IF('Data (Master Table)'!$B6 = $K$1, 'Data (Master Table)'!D6, "") -> Grow Waqf capital to £200,000 by Sept 2026 | C6: =IF('Data (Master Table)'!$B6 = $K$1, 'Data (Master Table)'!E6, "") -> Step-change in waqf investment amount | D6: =IF('Data (Master Table)'!$B6 = $K$1, 'Data (Master Table)'!F6, "") -> Donation-dependent operations; limited reserves; no diversified income operational yet. Curently contains £75k (+£60k Ramadhan iA) | E6: =IF('Data (Master Table)'!$B6 = $K$1, 'Data (Master Table)'!G6, "") -> Exec | F6: =IF('Data (Master Table)'!$B6 = $K$1, 'Data (Master Table)'!H6, "") -> End of March End of June End of Sept | G6: =IF('Data (Master Table)'!$B6 = $K$1, 'Data (Master Table)'!I6, "") -> Shaffiq | H6: =IF('Data (Master Table)'!$B6 = $K$1, 'Data (Master Table)'!J6, "") -> Medium | ... J6: =IF('Data (Master Table)'!$B6 = $K$1, 'Data (Master Table)'!L6, "") -> 46295 | K6: Increase waqf investment by further £65k | L6: 1 | M6: HNW and individual investor approach pack + roadshows | N6: 46266 | O6: Curated deck; Brunei / Malaysian network, donor lunches; targeted HNW outreach | P6: In Progress | R6: 0.7
A7: =IF('Data (Master Table)'!$B7 = $K$1, 'Data (Master Table)'!C7, "") -> YES | B7: =IF('Data (Master Table)'!$B7 = $K$1, 'Data (Master Table)'!D7, "") -> Achieve net-positive operating balance by Sept 2026 | C7: =IF('Data (Master Table)'!$B7 = $K$1, 'Data (Master Table)'!E7, "") -> Operational transparency + sustainability | D7: =IF('Data (Master Table)'!$B7 = $K$1, 'Data (Master Table)'!F7, "") -> Donation-dependent operations; limited reserves; no diversified income operational yet | E7: =IF('Data (Master Table)'!$B7 = $K$1, 'Data (Master Table)'!G7, "") -> Finance | F7: =IF('Data (Master Table)'!$B7 = $K$1, 'Data (Master Table)'!H7, "") -> End of March End of June End of Sept | G7: =IF('Data (Master Table)'!$B7 = $K$1, 'Data (Master Table)'!I7, "") -> Behzat / Raja / Kamraan | H7: =IF('Data (Master Table)'!$B7 = $K$1, 'Data (Master Table)'!J7, "") -> Low | ... J7: =IF('Data (Master Table)'!$B7 = $K$1, 'Data (Master Table)'!L7, "") -> 46295 | K7: Monthly finance dashboard & cost controls | L7: 1 | M7: Ramadhan BAU fundraising Dashboard creation | N7: 46266 | O7: Budget discipline; procurement policy | P7: In Progress | R7: 0
A8: =IF('Data (Master Table)'!$B8 = $K$1, 'Data (Master Table)'!C8, "") | B8: =IF('Data (Master Table)'!$B8 = $K$1, 'Data (Master Table)'!D8, "") | C8: =IF('Data (Master Table)'!$B8 = $K$1, 'Data (Master Table)'!E8, "") | D8: =IF('Data (Master Table)'!$B8 = $K$1, 'Data (Master Table)'!F8, "") | E8: =IF('Data (Master Table)'!$B8 = $K$1, 'Data (Master Table)'!G8, "") | F8: =IF('Data (Master Table)'!$B8 = $K$1, 'Data (Master Table)'!H8, "") | G8: =IF('Data (Master Table)'!$B8 = $K$1, 'Data (Master Table)'!I8, "") | H8: =IF('Data (Master Table)'!$B8 = $K$1, 'Data (Master Table)'!J8, "") | ... J8: =IF('Data (Master Table)'!$B8 = $K$1, 'Data (Master Table)'!L8, "")
A9: =IF('Data (Master Table)'!$B9 = $K$1, 'Data (Master Table)'!C9, "") | B9: =IF('Data (Master Table)'!$B9 = $K$1, 'Data (Master Table)'!D9, "") | C9: =IF('Data (Master Table)'!$B9 = $K$1, 'Data (Master Table)'!E9, "") | D9: =IF('Data (Master Table)'!$B9 = $K$1, 'Data (Master Table)'!F9, "") | E9: =IF('Data (Master Table)'!$B9 = $K$1, 'Data (Master Table)'!G9, "") | F9: =IF('Data (Master Table)'!$B9 = $K$1, 'Data (Master Table)'!H9, "") | G9: =IF('Data (Master Table)'!$B9 = $K$1, 'Data (Master Table)'!I9, "") | H9: =IF('Data (Master Table)'!$B9 = $K$1, 'Data (Master Table)'!J9, "") | ... J9: =IF('Data (Master Table)'!$B9 = $K$1, 'Data (Master Table)'!L9, "")
A10: =IF('Data (Master Table)'!$B10 = $K$1, 'Data (Master Table)'!C10, "") | B10: =IF('Data (Master Table)'!$B10 = $K$1, 'Data (Master Table)'!D10, "") | C10: =IF('Data (Master Table)'!$B10 = $K$1, 'Data (Master Table)'!E10, "") | D10: =IF('Data (Master Table)'!$B10 = $K$1, 'Data (Master Table)'!F10, "") | E10: =IF('Data (Master Table)'!$B10 = $K$1, 'Data (Master Table)'!G10, "") | F10: =IF('Data (Master Table)'!$B10 = $K$1, 'Data (Master Table)'!H10, "") | G10: =IF('Data (Master Table)'!$B10 = $K$1, 'Data (Master Table)'!I10, "") | H10: =IF('Data (Master Table)'!$B10 = $K$1, 'Data (Master Table)'!J10, "") | ... J10: =IF('Data (Master Table)'!$B10 = $K$1, 'Data (Master Table)'!L10, "")
A11: =IF('Data (Master Table)'!$B11 = $K$1, 'Data (Master Table)'!C11, "") | B11: =IF('Data (Master Table)'!$B11 = $K$1, 'Data (Master Table)'!D11, "") | C11: =IF('Data (Master Table)'!$B11 = $K$1, 'Data (Master Table)'!E11, "") | D11: =IF('Data (Master Table)'!$B11 = $K$1, 'Data (Master Table)'!F11, "") | E11: =IF('Data (Master Table)'!$B11 = $K$1, 'Data (Master Table)'!G11, "") | F11: =IF('Data (Master Table)'!$B11 = $K$1, 'Data (Master Table)'!H11, "") | G11: =IF('Data (Master Table)'!$B11 = $K$1, 'Data (Master Table)'!I11, "") | H11: =IF('Data (Master Table)'!$B11 = $K$1, 'Data (Master Table)'!J11, "") | ... J11: =IF('Data (Master Table)'!$B11 = $K$1, 'Data (Master Table)'!L11, "")
A12: =IF('Data (Master Table)'!$B12 = $K$1, 'Data (Master Table)'!C12, "") | B12: =IF('Data (Master Table)'!$B12 = $K$1, 'Data (Master Table)'!D12, "") | C12: =IF('Data (Master Table)'!$B12 = $K$1, 'Data (Master Table)'!E12, "") | D12: =IF('Data (Master Table)'!$B12 = $K$1, 'Data (Master Table)'!F12, "") | E12: =IF('Data (Master Table)'!$B12 = $K$1, 'Data (Master Table)'!G12, "") | F12: =IF('Data (Master Table)'!$B12 = $K$1, 'Data (Master Table)'!H12, "") | G12: =IF('Data (Master Table)'!$B12 = $K$1, 'Data (Master Table)'!I12, "") | H12: =IF('Data (Master Table)'!$B12 = $K$1, 'Data (Master Table)'!J12, "") | ... J12: =IF('Data (Master Table)'!$B12 = $K$1, 'Data (Master Table)'!L12, "")
A13: =IF('Data (Master Table)'!$B13 = $K$1, 'Data (Master Table)'!C13, "") | B13: =IF('Data (Master Table)'!$B13 = $K$1, 'Data (Master Table)'!D13, "") | C13: =IF('Data (Master Table)'!$B13 = $K$1, 'Data (Master Table)'!E13, "") | D13: =IF('Data (Master Table)'!$B13 = $K$1, 'Data (Master Table)'!F13, "") | E13: =IF('Data (Master Table)'!$B13 = $K$1, 'Data (Master Table)'!G13, "") | F13: =IF('Data (Master Table)'!$B13 = $K$1, 'Data (Master Table)'!H13, "") | G13: =IF('Data (Master Table)'!$B13 = $K$1, 'Data (Master Table)'!I13, "") | H13: =IF('Data (Master Table)'!$B13 = $K$1, 'Data (Master Table)'!J13, "") | ... J13: =IF('Data (Master Table)'!$B13 = $K$1, 'Data (Master Table)'!L13, "")
A14: =IF('Data (Master Table)'!$B14 = $K$1, 'Data (Master Table)'!C14, "") | B14: =IF('Data (Master Table)'!$B14 = $K$1, 'Data (Master Table)'!D14, "") | C14: =IF('Data (Master Table)'!$B14 = $K$1, 'Data (Master Table)'!E14, "") | D14: =IF('Data (Master Table)'!$B14 = $K$1, 'Data (Master Table)'!F14, "") | E14: =IF('Data (Master Table)'!$B14 = $K$1, 'Data (Master Table)'!G14, "") | F14: =IF('Data (Master Table)'!$B14 = $K$1, 'Data (Master Table)'!H14, "") | G14: =IF('Data (Master Table)'!$B14 = $K$1, 'Data (Master Table)'!I14, "") | H14: =IF('Data (Master Table)'!$B14 = $K$1, 'Data (Master Table)'!J14, "") | ... J14: =IF('Data (Master Table)'!$B14 = $K$1, 'Data (Master Table)'!L14, "")
A15: =IF('Data (Master Table)'!$B15 = $K$1, 'Data (Master Table)'!C15, "") | B15: =IF('Data (Master Table)'!$B15 = $K$1, 'Data (Master Table)'!D15, "") | C15: =IF('Data (Master Table)'!$B15 = $K$1, 'Data (Master Table)'!E15, "") | D15: =IF('Data (Master Table)'!$B15 = $K$1, 'Data (Master Table)'!F15, "") | E15: =IF('Data (Master Table)'!$B15 = $K$1, 'Data (Master Table)'!G15, "") | F15: =IF('Data (Master Table)'!$B15 = $K$1, 'Data (Master Table)'!H15, "") | G15: =IF('Data (Master Table)'!$B15 = $K$1, 'Data (Master Table)'!I15, "") | H15: =IF('Data (Master Table)'!$B15 = $K$1, 'Data (Master Table)'!J15, "") | ... J15: =IF('Data (Master Table)'!$B15 = $K$1, 'Data (Master Table)'!L15, "")
A16: =IF('Data (Master Table)'!$B16 = $K$1, 'Data (Master Table)'!C16, "") | B16: =IF('Data (Master Table)'!$B16 = $K$1, 'Data (Master Table)'!D16, "") | C16: =IF('Data (Master Table)'!$B16 = $K$1, 'Data (Master Table)'!E16, "") | D16: =IF('Data (Master Table)'!$B16 = $K$1, 'Data (Master Table)'!F16, "") | E16: =IF('Data (Master Table)'!$B16 = $K$1, 'Data (Master Table)'!G16, "") | F16: =IF('Data (Master Table)'!$B16 = $K$1, 'Data (Master Table)'!H16, "") | G16: =IF('Data (Master Table)'!$B16 = $K$1, 'Data (Master Table)'!I16, "") | H16: =IF('Data (Master Table)'!$B16 = $K$1, 'Data (Master Table)'!J16, "") | ... J16: =IF('Data (Master Table)'!$B16 = $K$1, 'Data (Master Table)'!L16, "")

Sheet Youth Succession Planning
A1: ULTIMATE AIM : DEVELOP YOUTH LEADERSHIP + SUCCESSION PLANNING SLT Lead Avais | K1: ='Data (Master Table)'!W4 -> Youth Succession Planning
A2: ='Data (Master Table)'!C2 -> IS VALID | B2: ='Data (Master Table)'!D2 -> SMART Outcome | C2: ='Data (Master Table)'!E2 -> Benefit | D2: ='Data (Master Table)'!F2 -> Starting Point / Baseline | E2: ='Data (Master Table)'!G2 -> Department | F2: ='Data (Master Table)'!H2 -> Reported to OPEX | G2: ='Data (Master Table)'!I2 -> Responsible Person | H2: ='Data (Master Table)'!J2 -> Risk Level | ... S2: ='Data (Master Table)'!U2 -> Notes
A3: =IF('Data (Master Table)'!$B18 = $K$1, 'Data (Master Table)'!C18, "") -> YES | B3: =IF('Data (Master Table)'!$B18 = $K$1, 'Data (Master Table)'!D18, "") -> Develop youth leadership | C3: =IF('Data (Master Table)'!$B18 = $K$1, 'Data (Master Table)'!E18, "") -> Pipeline of young leaders, succession planning | D3: =IF('Data (Master Table)'!$B18 = $K$1, 'Data (Master Table)'!F18, "") -> No formal youth leadership structure; involvement is ad‑hoc and reactive | E3: =IF('Data (Master Table)'!$B18 = $K$1, 'Data (Master Table)'!G18, "") -> Youth | F3: =IF('Data (Master Table)'!$B18 = $K$1, 'Data (Master Table)'!H18, "") -> End of March End of June End of Sept | G3: =IF('Data (Master Table)'!$B18 = $K$1, 'Data (Master Table)'!I18, "") -> Afsor | H3: =IF('Data (Master Table)'!$B18 = $K$1, 'Data (Master Table)'!J18, "") -> Medium | ... J3: =IF('Data (Master Table)'!$B18 = $K$1, 'Data (Master Table)'!L18, "") -> 46068 | K3: Establish Youth Council (10 members) + Shadow Trustees + Key staff positions proteges allocated | L3: 1 | M3: Clear roles; mentor pairing; monthly meetings, Liaise with Madrassa, Scouts, Boxing and Taekwondo functions | N3: Target end Ramadan for first results | O3: Ramadan: Volunteer Request, Omar Youth talks > key to identify youth. Youth Experience event plan for post Ramadan. | P3: In Progress | R3: 0.8 | S3: Results Ramadan> Youth activiites - building responsibility for the youth across the mosque. Demonstrated across youth events, running the coffee cart (i.e not just running, but also increasing product range to generate more "revenue" for the mosque), youth volunteers. How does this line with pipelne of young leaders: We have identified young leaders who we would recommend as part of a youth leadership strucutre that can support our growth. So based on we have identnfied caditates and now its about setting the strucutre, we have completed 40%, next 20% is setting structure, next 20% is executing it, and final 20% is ensuring its operating as part of the wider management teams. Q2: setting up youth board in progress.
A4: =IF('Data (Master Table)'!$B19 = $K$1, 'Data (Master Table)'!C19, "") -> YES | B4: =IF('Data (Master Table)'!$B19 = $K$1, 'Data (Master Table)'!D19, "") -> Increase youth volunteering team by 40% | C4: =IF('Data (Master Table)'!$B19 = $K$1, 'Data (Master Table)'!E19, "") -> Higher engagement & continuity | D4: =IF('Data (Master Table)'!$B19 = $K$1, 'Data (Master Table)'!F19, "") -> Current team number: X | E4: =IF('Data (Master Table)'!$B19 = $K$1, 'Data (Master Table)'!G19, "") -> Youth | F4: =IF('Data (Master Table)'!$B19 = $K$1, 'Data (Master Table)'!H19, "") -> End of March End of June End of Sept | G4: =IF('Data (Master Table)'!$B19 = $K$1, 'Data (Master Table)'!I19, "") -> Afsor | H4: =IF('Data (Master Table)'!$B19 = $K$1, 'Data (Master Table)'!J19, "") -> Low | ... J4: =IF('Data (Master Table)'!$B19 = $K$1, 'Data (Master Table)'!L19, "") -> 46203 | K4: Quarterly youth volunteer drives | L4: 1 | M4: School/college outreach; buddy system | N4: Target end Ramadan for first results | O4: Ramadan - youth voltuneering kicked off. | P4: In Progress | R4: 0.6 | S4: Q1:Results Ramadan: Youth volunteering from our advertising was not as successful but we had youth volunteering more by supporting the young adults i.e. Davids kids were helping coffee stand. We just need a bit more forward planning around youth volunteer requirements leading up to events, lead with young adults .. this will yield better results in future. Q2: We are building a core set of youth who are very engaged. Summer will be an important time to build events which bring our youth together.
A5: =IF('Data (Master Table)'!$B20 = $K$1, 'Data (Master Table)'!C20, "") -> YES | B5: =IF('Data (Master Table)'!$B20 = $K$1, 'Data (Master Table)'!D20, "") -> Targeted talks to attract youth | C5: =IF('Data (Master Table)'!$B20 = $K$1, 'Data (Master Table)'!E20, "") -> Higher engagement & building youth connection to masjid | D5: =IF('Data (Master Table)'!$B20 = $K$1, 'Data (Master Table)'!F20, "") -> Ad-hoc talks currently | E5: =IF('Data (Master Table)'!$B20 = $K$1, 'Data (Master Table)'!G20, "") -> Youth | F5: =IF('Data (Master Table)'!$B20 = $K$1, 'Data (Master Table)'!H20, "") -> End of March End of June End of Sept | G5: =IF('Data (Master Table)'!$B20 = $K$1, 'Data (Master Table)'!I20, "") -> Afsor | H5: =IF('Data (Master Table)'!$B20 = $K$1, 'Data (Master Table)'!J20, "") -> Medium | ... J5: =IF('Data (Master Table)'!$B20 = $K$1, 'Data (Master Table)'!L20, "") -> 46112 | K5: Plan and deliver targeted talks for all youth demographics | L5: 6 | M5: 1 every 2 months | N5: Target end Ramadan for first results | O5: Working with Omar to create a better set of talks for youth. Focus is not purley on topic, but more on connecting them to mentors + people they can respect/look up too (people who are not to old). First test of this will be in Ramadan. | P5: In Progress | R5: 0.6 | S5: Ramadan Resulst > Continue youth. Omar and Eni doing a great job. Think we need a sisters lead one switch at some point. 60% completion rate once we get consisten cy, have new people joining, 80% once we see engagement from youth outsend youth talks and final 100% swhen we have sister led sessions as well
A6: =IF('Data (Master Table)'!$B21 = $K$1, 'Data (Master Table)'!C21, "") -> YES | B6: =IF('Data (Master Table)'!$B21 = $K$1, 'Data (Master Table)'!D21, "") -> Bi-monthly events to attract youth | C6: =IF('Data (Master Table)'!$B21 = $K$1, 'Data (Master Table)'!E21, "") -> Higher engagement & building youth connection to masjid | D6: =IF('Data (Master Table)'!$B21 = $K$1, 'Data (Master Table)'!F21, "") -> Ad-hoc events running currently | E6: =IF('Data (Master Table)'!$B21 = $K$1, 'Data (Master Table)'!G21, "") -> Youth | F6: =IF('Data (Master Table)'!$B21 = $K$1, 'Data (Master Table)'!H21, "") -> End of March End of June End of Sept | G6: =IF('Data (Master Table)'!$B21 = $K$1, 'Data (Master Table)'!I21, "") -> Afsor | H6: =IF('Data (Master Table)'!$B21 = $K$1, 'Data (Master Table)'!J21, "") -> High | ... J6: =IF('Data (Master Table)'!$B21 = $K$1, 'Data (Master Table)'!L21, "") -> 46112 | K6: Plan and deliver fortnightly events, social, Islamic, food etc for specific youth demographics | L6: 24 | M6: 2 every month | N6: on-going | O6: While this is aspiration. For youth, possible. We will continue with consistency on boys and girls circles. For the YA, we want to build more on providing experiences e.g. hike at seven sisters etc. Build stronger bonds + friendships. This helps them feel more connected to the mosque and the community. | P6: In Progress | R6: 0.5 | S6: Q1: Ideas being progress: Experienced based events. Volunteering. DoE - our first volunteer. Building plans. Q2: Summer will be key. Where we want to get more volunteers and more experiences for youth.
A7: =IF('Data (Master Table)'!$B22 = $K$1, 'Data (Master Table)'!C22, "") -> YES | B7: =IF('Data (Master Table)'!$B22 = $K$1, 'Data (Master Table)'!D22, "") -> Leadership development | C7: =IF('Data (Master Table)'!$B22 = $K$1, 'Data (Master Table)'!E22, "") -> Safer, more competent teams | D7: =IF('Data (Master Table)'!$B22 = $K$1, 'Data (Master Table)'!F22, "") -> No formal youth leadership structure; involvement is ad‑hoc and reactive | E7: =IF('Data (Master Table)'!$B22 = $K$1, 'Data (Master Table)'!G22, "") -> OPEX | F7: =IF('Data (Master Table)'!$B22 = $K$1, 'Data (Master Table)'!H22, "") -> End of March End of June End of Sept | G7: =IF('Data (Master Table)'!$B22 = $K$1, 'Data (Master Table)'!I22, "") -> Amer | H7: =IF('Data (Master Table)'!$B22 = $K$1, 'Data (Master Table)'!J22, "") -> Low | ... J7: =IF('Data (Master Table)'!$B22 = $K$1, 'Data (Master Table)'!L22, "") -> 46112 | K7: Training calendar (safeguarding, first aid, comms) | L7: 1 | M7: Book trainers; certificates; track completion | N7: 18.01.26 | O7: Begin leadership development programme with Yusra training | P7: In Progress | Q7: Completion of pre-training 1-2-1 sessions with OPEX | R7: 0.7 | S7: Youth Lead Afsor Miah is captured within this training programme. Following MOSCARS awards ceremony several youth volunteers were identified for consideration for a youth council or shadow trustee/directors board. Shaffiq has put document tyogether detailing proposed structure. Some of the youth m,embers have also attended Yusar training sessions.
A8: =IF('Data (Master Table)'!$B23 = $K$1, 'Data (Master Table)'!C23, "") -> YES | B8: =IF('Data (Master Table)'!$B23 = $K$1, 'Data (Master Table)'!D23, "") -> Leadership development | C8: =IF('Data (Master Table)'!$B23 = $K$1, 'Data (Master Table)'!E23, "") -> Pipeline of young leaders, succession planning | D8: =IF('Data (Master Table)'!$B23 = $K$1, 'Data (Master Table)'!F23, "") -> Scouts provision low | E8: =IF('Data (Master Table)'!$B23 = $K$1, 'Data (Master Table)'!G23, "") -> Scouts | F8: =IF('Data (Master Table)'!$B23 = $K$1, 'Data (Master Table)'!H23, "") -> End of March End of June End of Sept | G8: =IF('Data (Master Table)'!$B23 = $K$1, 'Data (Master Table)'!I23, "") -> Khaleeq | H8: =IF('Data (Master Table)'!$B23 = $K$1, 'Data (Master Table)'!J23, "") -> Medium | ... J8: =IF('Data (Master Table)'!$B23 = $K$1, 'Data (Master Table)'!L23, "") -> 46112 | K8: Increase number of Scouts places- key issue; staffing | L8: 1 | M8: Increase staff numbers | N8: 31.01.26 | O8: Advertising targeted for Q1. Story around impact and outcomes. We will keep on top of this. We will review impact. | P8: Not Started | R8: 0 | S8: Risk: Scout leader is leaving. Need to first onboard a new lead Lack of volunteers are we progressing this?
A9: =IF('Data (Master Table)'!$B24 = $K$1, 'Data (Master Table)'!C24, "") | B9: =IF('Data (Master Table)'!$B24 = $K$1, 'Data (Master Table)'!D24, "") | C9: =IF('Data (Master Table)'!$B24 = $K$1, 'Data (Master Table)'!E24, "") | D9: =IF('Data (Master Table)'!$B24 = $K$1, 'Data (Master Table)'!F24, "") | E9: =IF('Data (Master Table)'!$B24 = $K$1, 'Data (Master Table)'!G24, "") | F9: =IF('Data (Master Table)'!$B24 = $K$1, 'Data (Master Table)'!H24, "") | G9: =IF('Data (Master Table)'!$B24 = $K$1, 'Data (Master Table)'!I24, "") | H9: =IF('Data (Master Table)'!$B24 = $K$1, 'Data (Master Table)'!J24, "") | ... J9: =IF('Data (Master Table)'!$B24 = $K$1, 'Data (Master Table)'!L24, "")
A10: =IF('Data (Master Table)'!$B25 = $K$1, 'Data (Master Table)'!C25, "") | B10: =IF('Data (Master Table)'!$B25 = $K$1, 'Data (Master Table)'!D25, "") | C10: =IF('Data (Master Table)'!$B25 = $K$1, 'Data (Master Table)'!E25, "") | D10: =IF('Data (Master Table)'!$B25 = $K$1, 'Data (Master Table)'!F25, "") | E10: =IF('Data (Master Table)'!$B25 = $K$1, 'Data (Master Table)'!G25, "") | F10: =IF('Data (Master Table)'!$B25 = $K$1, 'Data (Master Table)'!H25, "") | G10: =IF('Data (Master Table)'!$B25 = $K$1, 'Data (Master Table)'!I25, "") | H10: =IF('Data (Master Table)'!$B25 = $K$1, 'Data (Master Table)'!J25, "") | ... J10: =IF('Data (Master Table)'!$B25 = $K$1, 'Data (Master Table)'!L25, "")
A11: =IF('Data (Master Table)'!$B26 = $K$1, 'Data (Master Table)'!C26, "") | B11: =IF('Data (Master Table)'!$B26 = $K$1, 'Data (Master Table)'!D26, "") | C11: =IF('Data (Master Table)'!$B26 = $K$1, 'Data (Master Table)'!E26, "") | D11: =IF('Data (Master Table)'!$B26 = $K$1, 'Data (Master Table)'!F26, "") | E11: =IF('Data (Master Table)'!$B26 = $K$1, 'Data (Master Table)'!G26, "") | F11: =IF('Data (Master Table)'!$B26 = $K$1, 'Data (Master Table)'!H26, "") | G11: =IF('Data (Master Table)'!$B26 = $K$1, 'Data (Master Table)'!I26, "") | H11: =IF('Data (Master Table)'!$B26 = $K$1, 'Data (Master Table)'!J26, "") | ... J11: =IF('Data (Master Table)'!$B26 = $K$1, 'Data (Master Table)'!L26, "")
A12: =IF('Data (Master Table)'!$B27 = $K$1, 'Data (Master Table)'!C27, "") | B12: =IF('Data (Master Table)'!$B27 = $K$1, 'Data (Master Table)'!D27, "") | C12: =IF('Data (Master Table)'!$B27 = $K$1, 'Data (Master Table)'!E27, "") | D12: =IF('Data (Master Table)'!$B27 = $K$1, 'Data (Master Table)'!F27, "") | E12: =IF('Data (Master Table)'!$B27 = $K$1, 'Data (Master Table)'!G27, "") | F12: =IF('Data (Master Table)'!$B27 = $K$1, 'Data (Master Table)'!H27, "") | G12: =IF('Data (Master Table)'!$B27 = $K$1, 'Data (Master Table)'!I27, "") | H12: =IF('Data (Master Table)'!$B27 = $K$1, 'Data (Master Table)'!J27, "") | ... J12: =IF('Data (Master Table)'!$B27 = $K$1, 'Data (Master Table)'!L27, "")
A13: =IF('Data (Master Table)'!$B28 = $K$1, 'Data (Master Table)'!C28, "") | B13: =IF('Data (Master Table)'!$B28 = $K$1, 'Data (Master Table)'!D28, "") | C13: =IF('Data (Master Table)'!$B28 = $K$1, 'Data (Master Table)'!E28, "") | D13: =IF('Data (Master Table)'!$B28 = $K$1, 'Data (Master Table)'!F28, "") | E13: =IF('Data (Master Table)'!$B28 = $K$1, 'Data (Master Table)'!G28, "") | F13: =IF('Data (Master Table)'!$B28 = $K$1, 'Data (Master Table)'!H28, "") | G13: =IF('Data (Master Table)'!$B28 = $K$1, 'Data (Master Table)'!I28, "") | H13: =IF('Data (Master Table)'!$B28 = $K$1, 'Data (Master Table)'!J28, "") | ... J13: =IF('Data (Master Table)'!$B28 = $K$1, 'Data (Master Table)'!L28, "")
A14: =IF('Data (Master Table)'!$B29 = $K$1, 'Data (Master Table)'!C29, "") | B14: =IF('Data (Master Table)'!$B29 = $K$1, 'Data (Master Table)'!D29, "") | C14: =IF('Data (Master Table)'!$B29 = $K$1, 'Data (Master Table)'!E29, "") | D14: =IF('Data (Master Table)'!$B29 = $K$1, 'Data (Master Table)'!F29, "") | E14: =IF('Data (Master Table)'!$B29 = $K$1, 'Data (Master Table)'!G29, "") | F14: =IF('Data (Master Table)'!$B29 = $K$1, 'Data (Master Table)'!H29, "") | G14: =IF('Data (Master Table)'!$B29 = $K$1, 'Data (Master Table)'!I29, "") | H14: =IF('Data (Master Table)'!$B29 = $K$1, 'Data (Master Table)'!J29, "") | ... J14: =IF('Data (Master Table)'!$B29 = $K$1, 'Data (Master Table)'!L29, "")
A15: =IF('Data (Master Table)'!$B30 = $K$1, 'Data (Master Table)'!C30, "") | B15: =IF('Data (Master Table)'!$B30 = $K$1, 'Data (Master Table)'!D30, "") | C15: =IF('Data (Master Table)'!$B30 = $K$1, 'Data (Master Table)'!E30, "") | D15: =IF('Data (Master Table)'!$B30 = $K$1, 'Data (Master Table)'!F30, "") | E15: =IF('Data (Master Table)'!$B30 = $K$1, 'Data (Master Table)'!G30, "") | F15: =IF('Data (Master Table)'!$B30 = $K$1, 'Data (Master Table)'!H30, "") | G15: =IF('Data (Master Table)'!$B30 = $K$1, 'Data (Master Table)'!I30, "") | H15: =IF('Data (Master Table)'!$B30 = $K$1, 'Data (Master Table)'!J30, "") | ... J15: =IF('Data (Master Table)'!$B30 = $K$1, 'Data (Master Table)'!L30, "")
A16: =IF('Data (Master Table)'!$B31 = $K$1, 'Data (Master Table)'!C31, "") | B16: =IF('Data (Master Table)'!$B31 = $K$1, 'Data (Master Table)'!D31, "") | C16: =IF('Data (Master Table)'!$B31 = $K$1, 'Data (Master Table)'!E31, "") | D16: =IF('Data (Master Table)'!$B31 = $K$1, 'Data (Master Table)'!F31, "") | E16: =IF('Data (Master Table)'!$B31 = $K$1, 'Data (Master Table)'!G31, "") | F16: =IF('Data (Master Table)'!$B31 = $K$1, 'Data (Master Table)'!H31, "") | G16: =IF('Data (Master Table)'!$B31 = $K$1, 'Data (Master Table)'!I31, "") | H16: =IF('Data (Master Table)'!$B31 = $K$1, 'Data (Master Table)'!J31, "") | ... J16: =IF('Data (Master Table)'!$B31 = $K$1, 'Data (Master Table)'!L31, "")

Sheet Wider Community Engagement
A1: ULTIMATE AIM : BUILD BENEFICIAL PARTNERSHIPS SLT - Lead Matiur | K1: ='Data (Master Table)'!W5 -> Wider Community Engagement
A2: ='Data (Master Table)'!C2 -> IS VALID | B2: ='Data (Master Table)'!D2 -> SMART Outcome | C2: ='Data (Master Table)'!E2 -> Benefit | D2: ='Data (Master Table)'!F2 -> Starting Point / Baseline | E2: ='Data (Master Table)'!G2 -> Department | F2: ='Data (Master Table)'!H2 -> Reported to OPEX | G2: ='Data (Master Table)'!I2 -> Responsible Person | H2: ='Data (Master Table)'!J2 -> Risk Level | ... S2: ='Data (Master Table)'!U2 -> Notes
A3: =IF('Data (Master Table)'!$B33 = $K$1, 'Data (Master Table)'!C33, "") -> YES | B3: =IF('Data (Master Table)'!$B33 = $K$1, 'Data (Master Table)'!D33, "") -> Build partnerships | C3: =IF('Data (Master Table)'!$B33 = $K$1, 'Data (Master Table)'!E33, "") -> Shared impact & credibility, improved societal integration | D3: =IF('Data (Master Table)'!$B33 = $K$1, 'Data (Master Table)'!F33, "") -> 3–4 informal partnerships; sporadic open days; no structured annual calendar | E3: =IF('Data (Master Table)'!$B33 = $K$1, 'Data (Master Table)'!G33, "") -> Community / Politics | F3: =IF('Data (Master Table)'!$B33 = $K$1, 'Data (Master Table)'!H33, "") -> End of March End of June End of Sept | G3: =IF('Data (Master Table)'!$B33 = $K$1, 'Data (Master Table)'!I33, "") -> Matiur | H3: =IF('Data (Master Table)'!$B33 = $K$1, 'Data (Master Table)'!J33, "") -> Medium | ... J3: =IF('Data (Master Table)'!$B33 = $K$1, 'Data (Master Table)'!L33, "") -> 46173 | K3: Sign 5 MOUs with local orgs | L3: 3 | M3: 1. Target list (schools, council, charities); template MOU 2. Set up Bromley Citizens UK 3. Recruit more volunteers for Citizens UK | N3: 1. Apr 2. Sept 3. Feb | O3: Further Citizen's UK meeting attended by other community members | P3: In Progress | R3: 0.4 | S3: Founding Assembly of Bromley Citizens to be held on 30th April
A4: =IF('Data (Master Table)'!$B34 = $K$1, 'Data (Master Table)'!C34, "") -> YES | B4: =IF('Data (Master Table)'!$B34 = $K$1, 'Data (Master Table)'!D34, "") -> Community events | C4: =IF('Data (Master Table)'!$B34 = $K$1, 'Data (Master Table)'!E34, "") -> Improved public perception and relationships, increased local impact | D4: =IF('Data (Master Table)'!$B34 = $K$1, 'Data (Master Table)'!F34, "") -> 3–4 informal partnerships; sporadic open days; no structured annual calendar | E4: =IF('Data (Master Table)'!$B34 = $K$1, 'Data (Master Table)'!G34, "") -> Community / Politics | F4: =IF('Data (Master Table)'!$B34 = $K$1, 'Data (Master Table)'!H34, "") -> End of March End of June End of Sept | G4: =IF('Data (Master Table)'!$B34 = $K$1, 'Data (Master Table)'!I34, "") -> Avais | H4: =IF('Data (Master Table)'!$B34 = $K$1, 'Data (Master Table)'!J34, "") -> Medium | ... J4: =IF('Data (Master Table)'!$B34 = $K$1, 'Data (Master Table)'!L34, "") -> 46295 | K4: Deliver 4 open community events | L4: 5 | M4: Plan calendar; steward training; inclusive themes. Include neighbourhood consultation (first build relationships, then ask what are your needs?)and Interfaith iftar | N4: Feb - Calendar May - Eid Jun - World Cup Sep - Dec - Christmas | O4: Online community Calendar is ready for Ramadan! Build an informal way of engaging with the mosque space to make it more accessiable for non muslims. Event invitations to consider non-muslim community. Partnerships - tbc | P4: In Progress | R4: 0.5 | S4: Calendar up and running. Testing during Ramdan. Avais and Meryem to own, keep up to date. Need to make this calendar more avalaible to non muslim community. Coffee Cart super successful, we need to get someone to own this and also this need sto beome a more regular daily service. Q2: Progressing well. Eid event we invited wider community. I am keen to do an Art event, farmers market in August etc
A5: =IF('Data (Master Table)'!$B35 = $K$1, 'Data (Master Table)'!C35, "") -> YES | B5: =IF('Data (Master Table)'!$B35 = $K$1, 'Data (Master Table)'!D35, "") -> Transparency | C5: =IF('Data (Master Table)'!$B35 = $K$1, 'Data (Master Table)'!E35, "") -> Evidence for funders & partners | D5: =IF('Data (Master Table)'!$B35 = $K$1, 'Data (Master Table)'!F35, "") -> 3–4 informal partnerships; sporadic open days; no structured annual calendar | E5: =IF('Data (Master Table)'!$B35 = $K$1, 'Data (Master Table)'!G35, "") -> Community / Politics | F5: =IF('Data (Master Table)'!$B35 = $K$1, 'Data (Master Table)'!H35, "") -> End of March End of June End of Sept | G5: =IF('Data (Master Table)'!$B35 = $K$1, 'Data (Master Table)'!I35, "") -> Avais | H5: =IF('Data (Master Table)'!$B35 = $K$1, 'Data (Master Table)'!J35, "") -> Low | ... J5: =IF('Data (Master Table)'!$B35 = $K$1, 'Data (Master Table)'!L35, "") -> 46295 | K5: Publish annual Community Impact Report | L5: 3 | M5: Collect metrics; case studies; design & print | N5: On-going | O5: Ensuring data capturing of events is requested before events. Looking to get more youth to take videos/photos during evets | P5: Complete | R5: 1 | S5: We are getting data for events every time which is good, succewss is shared throguh leads utd, and we are keeping each other updated. Good progress on this and its linked well to marketing
A6: =IF('Data (Master Table)'!$B36 = $K$1, 'Data (Master Table)'!C36, "") -> YES | B6: =IF('Data (Master Table)'!$B36 = $K$1, 'Data (Master Table)'!D36, "") -> Non-Muslims understand Islam | C6: =IF('Data (Master Table)'!$B36 = $K$1, 'Data (Master Table)'!E36, "") -> Spreading the Deen and benefitting local community. Islamic stereotypes broken | D6: =IF('Data (Master Table)'!$B36 = $K$1, 'Data (Master Table)'!F36, "") -> Recruited da'ee group; completing training. Dawah stall equipment and clothing being sourced, branding complete. Awaiting stall permission from Bromley Council | E6: =IF('Data (Master Table)'!$B36 = $K$1, 'Data (Master Table)'!G36, "") -> Religious Affairs | F6: =IF('Data (Master Table)'!$B36 = $K$1, 'Data (Master Table)'!H36, "") -> End of March End of June End of Sept | G6: =IF('Data (Master Table)'!$B36 = $K$1, 'Data (Master Table)'!I36, "") -> Ahmed | H6: =IF('Data (Master Table)'!$B36 = $K$1, 'Data (Master Table)'!J36, "") -> Low | ... J6: =IF('Data (Master Table)'!$B36 = $K$1, 'Data (Master Table)'!L36, "") -> 46053 | K6: Live, active Da'wah project | L6: 3 | M6: 1. Complete purchases of equipment 2. Stall permission granted 3. Volunteer training complete | N6: 1. Jan end 2. Jan end 3. Jan end | P6: In Progress | R6: 0.9
A7: =IF('Data (Master Table)'!$B37 = $K$1, 'Data (Master Table)'!C37, "") -> YES | B7: =IF('Data (Master Table)'!$B37 = $K$1, 'Data (Master Table)'!D37, "") -> Engage and connect with local schools and scouts groups | C7: =IF('Data (Master Table)'!$B37 = $K$1, 'Data (Master Table)'!E37, "") -> Active daw'ah and increasing Islamic knowledge (including breaking stereotypes) of young local people through immersive experiences | D7: =IF('Data (Master Table)'!$B37 = $K$1, 'Data (Master Table)'!F37, "") -> School and scouts visits service already active, through school/scout group contact | E7: =IF('Data (Master Table)'!$B37 = $K$1, 'Data (Master Table)'!G37, "") -> Education | F7: =IF('Data (Master Table)'!$B37 = $K$1, 'Data (Master Table)'!H37, "") -> End of March End of June End of Sept | G7: =IF('Data (Master Table)'!$B37 = $K$1, 'Data (Master Table)'!I37, "") -> Sobia | H7: =IF('Data (Master Table)'!$B37 = $K$1, 'Data (Master Table)'!J37, "") -> Low | ... J7: =IF('Data (Master Table)'!$B37 = $K$1, 'Data (Master Table)'!L37, "") -> 46173 | K7: Service to become proactive, reaching out to schools /scout groups | L7: 6 | M7: 1. Attract and retain further volunteers 2. Begin actively reaching out to schools/scout groups 3. Engage Bromley College 4. Invite them to our wider events 5. Get them to partake in our Ramadhan Challenge and iftars | N7: 1. Jan Mid 2. May End 3. Feb End 4. Feb Begin 5. Feb end | O7: Successfully attracted and retained additional volunteers to support the mosque visits programme. | P7: In Progress | R7: 0.5
A8: =IF('Data (Master Table)'!$B38 = $K$1, 'Data (Master Table)'!C38, "") -> YES | B8: =IF('Data (Master Table)'!$B38 = $K$1, 'Data (Master Table)'!D38, "") -> Deepen relationships and benefit from connections to other faiths | C8: =IF('Data (Master Table)'!$B38 = $K$1, 'Data (Master Table)'!E38, "") -> Learn from them, teach them about Islam, break stereotypes, aid geo/political dialogues/situations | D8: =IF('Data (Master Table)'!$B38 = $K$1, 'Data (Master Table)'!F38, "") -> Already esablished long term Interfaith relationships | E8: =IF('Data (Master Table)'!$B38 = $K$1, 'Data (Master Table)'!G38, "") -> Education | F8: =IF('Data (Master Table)'!$B38 = $K$1, 'Data (Master Table)'!H38, "") -> End of March End of June End of Sept | G8: =IF('Data (Master Table)'!$B38 = $K$1, 'Data (Master Table)'!I38, "") -> Sofi | H8: =IF('Data (Master Table)'!$B38 = $K$1, 'Data (Master Table)'!J38, "") -> Medium | ... J8: =IF('Data (Master Table)'!$B38 = $K$1, 'Data (Master Table)'!L38, "") -> 46280 | K8: Participate in regular Interfaith meetings and continue to educate about Islam, lessons learned from our shared prophets and highlight the advantages of being a people of peace who pray, fast and are ready to help others | L8: 3 | M8: 1. Get more of our community involved 2. Strengthen relationships with focus on Justice 3. Benefit from learning about how other faiths function,e.g. financial set up of Christians, power dynamics from Jews. 4.Plan Islamophobia and anti-semitism workshops | N8: 1. Feb end 2. Apr end 3. Sep end | O8: 1. Work in progress re drawing more of our community . Issues are due to advertising events late, this is partly due to the sensitive nature of the topics and have been hesitant to advertise. 2 | P8: In Progress | R8: 0.5
A9: =IF('Data (Master Table)'!$B39 = $K$1, 'Data (Master Table)'!C39, "") -> YES | B9: =IF('Data (Master Table)'!$B39 = $K$1, 'Data (Master Table)'!D39, "") -> Connect with, market, and advertise well with wider community | C9: =IF('Data (Master Table)'!$B39 = $K$1, 'Data (Master Table)'!E39, "") -> Improved community cohesion | D9: =IF('Data (Master Table)'!$B39 = $K$1, 'Data (Master Table)'!F39, "") -> Have an existing but out of date and non searchable database. A sharepoint version now exists in SharePoint | E9: =IF('Data (Master Table)'!$B39 = $K$1, 'Data (Master Table)'!G39, "") -> Community / Politics | F9: =IF('Data (Master Table)'!$B39 = $K$1, 'Data (Master Table)'!H39, "") -> End of March End of June End of Sept | G9: =IF('Data (Master Table)'!$B39 = $K$1, 'Data (Master Table)'!I39, "") -> Matiur | H9: =IF('Data (Master Table)'!$B39 = $K$1, 'Data (Master Table)'!J39, "") -> Medium | ... J9: =IF('Data (Master Table)'!$B39 = $K$1, 'Data (Master Table)'!L39, "") -> 46234 | K9: Build useful, searchable, regularly updated database of community contacts | L9: 1 | P9: In Progress | R9: 0.1 | S9: To be reviewed after Eid. Interfaith iftar invitations was not well executed with many key stakeholders missed
A10: =IF('Data (Master Table)'!$B40 = $K$1, 'Data (Master Table)'!C40, "") | B10: =IF('Data (Master Table)'!$B40 = $K$1, 'Data (Master Table)'!D40, "") | C10: =IF('Data (Master Table)'!$B40 = $K$1, 'Data (Master Table)'!E40, "") | D10: =IF('Data (Master Table)'!$B40 = $K$1, 'Data (Master Table)'!F40, "") | E10: =IF('Data (Master Table)'!$B40 = $K$1, 'Data (Master Table)'!G40, "") | F10: =IF('Data (Master Table)'!$B40 = $K$1, 'Data (Master Table)'!H40, "") | G10: =IF('Data (Master Table)'!$B40 = $K$1, 'Data (Master Table)'!I40, "") | H10: =IF('Data (Master Table)'!$B40 = $K$1, 'Data (Master Table)'!J40, "") | ... J10: =IF('Data (Master Table)'!$B40 = $K$1, 'Data (Master Table)'!L40, "") | O10: Work in progress:
A11: =IF('Data (Master Table)'!$B41 = $K$1, 'Data (Master Table)'!C41, "") | B11: =IF('Data (Master Table)'!$B41 = $K$1, 'Data (Master Table)'!D41, "") | C11: =IF('Data (Master Table)'!$B41 = $K$1, 'Data (Master Table)'!E41, "") | D11: =IF('Data (Master Table)'!$B41 = $K$1, 'Data (Master Table)'!F41, "") | E11: =IF('Data (Master Table)'!$B41 = $K$1, 'Data (Master Table)'!G41, "") | F11: =IF('Data (Master Table)'!$B41 = $K$1, 'Data (Master Table)'!H41, "") | G11: =IF('Data (Master Table)'!$B41 = $K$1, 'Data (Master Table)'!I41, "") | H11: =IF('Data (Master Table)'!$B41 = $K$1, 'Data (Master Table)'!J41, "") | ... J11: =IF('Data (Master Table)'!$B41 = $K$1, 'Data (Master Table)'!L41, "")
A12: =IF('Data (Master Table)'!$B42 = $K$1, 'Data (Master Table)'!C42, "") | B12: =IF('Data (Master Table)'!$B42 = $K$1, 'Data (Master Table)'!D42, "") | C12: =IF('Data (Master Table)'!$B42 = $K$1, 'Data (Master Table)'!E42, "") | D12: =IF('Data (Master Table)'!$B42 = $K$1, 'Data (Master Table)'!F42, "") | E12: =IF('Data (Master Table)'!$B42 = $K$1, 'Data (Master Table)'!G42, "") | F12: =IF('Data (Master Table)'!$B42 = $K$1, 'Data (Master Table)'!H42, "") | G12: =IF('Data (Master Table)'!$B42 = $K$1, 'Data (Master Table)'!I42, "") | H12: =IF('Data (Master Table)'!$B42 = $K$1, 'Data (Master Table)'!J42, "") | ... J12: =IF('Data (Master Table)'!$B42 = $K$1, 'Data (Master Table)'!L42, "")
A13: =IF('Data (Master Table)'!$B43 = $K$1, 'Data (Master Table)'!C43, "") | B13: =IF('Data (Master Table)'!$B43 = $K$1, 'Data (Master Table)'!D43, "") | C13: =IF('Data (Master Table)'!$B43 = $K$1, 'Data (Master Table)'!E43, "") | D13: =IF('Data (Master Table)'!$B43 = $K$1, 'Data (Master Table)'!F43, "") | E13: =IF('Data (Master Table)'!$B43 = $K$1, 'Data (Master Table)'!G43, "") | F13: =IF('Data (Master Table)'!$B43 = $K$1, 'Data (Master Table)'!H43, "") | G13: =IF('Data (Master Table)'!$B43 = $K$1, 'Data (Master Table)'!I43, "") | H13: =IF('Data (Master Table)'!$B43 = $K$1, 'Data (Master Table)'!J43, "") | ... J13: =IF('Data (Master Table)'!$B43 = $K$1, 'Data (Master Table)'!L43, "")
A14: =IF('Data (Master Table)'!$B44 = $K$1, 'Data (Master Table)'!C44, "") | B14: =IF('Data (Master Table)'!$B44 = $K$1, 'Data (Master Table)'!D44, "") | C14: =IF('Data (Master Table)'!$B44 = $K$1, 'Data (Master Table)'!E44, "") | D14: =IF('Data (Master Table)'!$B44 = $K$1, 'Data (Master Table)'!F44, "") | E14: =IF('Data (Master Table)'!$B44 = $K$1, 'Data (Master Table)'!G44, "") | F14: =IF('Data (Master Table)'!$B44 = $K$1, 'Data (Master Table)'!H44, "") | G14: =IF('Data (Master Table)'!$B44 = $K$1, 'Data (Master Table)'!I44, "") | H14: =IF('Data (Master Table)'!$B44 = $K$1, 'Data (Master Table)'!J44, "") | ... J14: =IF('Data (Master Table)'!$B44 = $K$1, 'Data (Master Table)'!L44, "")
A15: =IF('Data (Master Table)'!$B45 = $K$1, 'Data (Master Table)'!C45, "") | B15: =IF('Data (Master Table)'!$B45 = $K$1, 'Data (Master Table)'!D45, "") | C15: =IF('Data (Master Table)'!$B45 = $K$1, 'Data (Master Table)'!E45, "") | D15: =IF('Data (Master Table)'!$B45 = $K$1, 'Data (Master Table)'!F45, "") | E15: =IF('Data (Master Table)'!$B45 = $K$1, 'Data (Master Table)'!G45, "") | F15: =IF('Data (Master Table)'!$B45 = $K$1, 'Data (Master Table)'!H45, "") | G15: =IF('Data (Master Table)'!$B45 = $K$1, 'Data (Master Table)'!I45, "") | H15: =IF('Data (Master Table)'!$B45 = $K$1, 'Data (Master Table)'!J45, "") | ... J15: =IF('Data (Master Table)'!$B45 = $K$1, 'Data (Master Table)'!L45, "")
A16: =IF('Data (Master Table)'!$B46 = $K$1, 'Data (Master Table)'!C46, "") | B16: =IF('Data (Master Table)'!$B46 = $K$1, 'Data (Master Table)'!D46, "") | C16: =IF('Data (Master Table)'!$B46 = $K$1, 'Data (Master Table)'!E46, "") | D16: =IF('Data (Master Table)'!$B46 = $K$1, 'Data (Master Table)'!F46, "") | E16: =IF('Data (Master Table)'!$B46 = $K$1, 'Data (Master Table)'!G46, "") | F16: =IF('Data (Master Table)'!$B46 = $K$1, 'Data (Master Table)'!H46, "") | G16: =IF('Data (Master Table)'!$B46 = $K$1, 'Data (Master Table)'!I46, "") | H16: =IF('Data (Master Table)'!$B46 = $K$1, 'Data (Master Table)'!J46, "") | ... J16: =IF('Data (Master Table)'!$B46 = $K$1, 'Data (Master Table)'!L46, "")
O19: 5) Ramadan challenge & iftar
P20: •

Sheet Building Teams & Leadership
A1: ULTIMATE AIM : DEVELOP LEADERSHIP TEAMS, ESPECIALLY VOLUNTEERS SLT Lead Amer | K1: ='Data (Master Table)'!W6 -> Building Teams & Leadership
A2: ='Data (Master Table)'!C2 -> IS VALID | B2: ='Data (Master Table)'!D2 -> SMART Outcome | C2: ='Data (Master Table)'!E2 -> Benefit | D2: ='Data (Master Table)'!F2 -> Starting Point / Baseline | E2: ='Data (Master Table)'!G2 -> Department | F2: ='Data (Master Table)'!H2 -> Reported to OPEX | G2: ='Data (Master Table)'!I2 -> Responsible Person | H2: ='Data (Master Table)'!J2 -> Risk Level | ... S2: ='Data (Master Table)'!U2 -> Notes
A3: =IF('Data (Master Table)'!$B48 = $K$1, 'Data (Master Table)'!C48, "") -> YES | B3: =IF('Data (Master Table)'!$B48 = $K$1, 'Data (Master Table)'!D48, "") -> Competence & compliance | C3: =IF('Data (Master Table)'!$B48 = $K$1, 'Data (Master Table)'!E48, "") -> Risk reduction; improved leadership | D3: =IF('Data (Master Table)'!$B48 = $K$1, 'Data (Master Table)'!F48, "") -> Partial ad-hoc training coverage | E3: =IF('Data (Master Table)'!$B48 = $K$1, 'Data (Master Table)'!G48, "") -> OPEX | F3: =IF('Data (Master Table)'!$B48 = $K$1, 'Data (Master Table)'!H48, "") -> End of March End of June End of Sept | G3: =IF('Data (Master Table)'!$B48 = $K$1, 'Data (Master Table)'!I48, "") -> Amer | H3: =IF('Data (Master Table)'!$B48 = $K$1, 'Data (Master Table)'!J48, "") -> Medium | ... J3: =IF('Data (Master Table)'!$B48 = $K$1, 'Data (Master Table)'!L48, "") -> 46203 | K3: Train all leads in leadership, governance & safeguarding | L3: 1 | M3: Book courses; track completion | N3: Yusra training starting 18/01/26 | O3: Leasdership development programme 8 half day sessions over 6-12 months | P3: In Progress | R3: 0.6 | S3: To reconvene after Ramadan. Traing resumed Fri 1st May. However poor attendance (6 delegetes) Agreed with trainer Shahid to consider hybrid delivery of next session to encourage more attendees. Online Zoom training delivered Sat 20th June successfully with 2 attendees including most Leads and some team members. Good feedback and training well received. Will speak to Shahid at Yusra training to see how this can be delivered for the remaining sessions. Recent online scheduled session July 18th postponed as trainer's wife unwell. To re-organise.
A4: =IF('Data (Master Table)'!$B49 = $K$1, 'Data (Master Table)'!C49, "") -> YES | B4: =IF('Data (Master Table)'!$B49 = $K$1, 'Data (Master Table)'!D49, "") -> Onboarding excellence | C4: =IF('Data (Master Table)'!$B49 = $K$1, 'Data (Master Table)'!E49, "") -> Faster integration; safety | D4: =IF('Data (Master Table)'!$B49 = $K$1, 'Data (Master Table)'!F49, "") -> Onboarding is informal | E4: =IF('Data (Master Table)'!$B49 = $K$1, 'Data (Master Table)'!G49, "") -> OPEX | F4: =IF('Data (Master Table)'!$B49 = $K$1, 'Data (Master Table)'!H49, "") -> End of March End of June End of Sept | G4: =IF('Data (Master Table)'!$B49 = $K$1, 'Data (Master Table)'!I49, "") -> Amer | H4: =IF('Data (Master Table)'!$B49 = $K$1, 'Data (Master Table)'!J49, "") -> Low | ... J4: =IF('Data (Master Table)'!$B49 = $K$1, 'Data (Master Table)'!L49, "") -> 46142 | K4: Structured induction pack and build a process to align volunteers to roles | L4: 5 | M4: Checklist; DBS; H&S; first aid; handbook | N4: Will need to liase with Ali to organise DBS, 1st Aid and staff handbook | O4: No communication from Ali regarding staff handbook | P4: In Progress | Q4: Ali has already DBS several leads. | R4: 0.3 | S4: Faridah has notified me of her stepping down from AEC duties including OPEX and Leads Utd from 30th March. Conversation with Shaffiq regarding Perkbox. Have messaged Br Behzat with proposal and is being considered. After further discussion, Perkbox has been parked as not enough interest generated for this platform. Flick still to be considered for recording of volunteer training and documentation. Spoken to Ali rearding taking over the helm of Leads Utd. Ali has now led a couple of meetings asking for monthly updates from the leads. Amer will coninue leading OPEX onboarding volunteers and organising training.
A5: =IF('Data (Master Table)'!$B50 = $K$1, 'Data (Master Table)'!C50, "") -> YES | B5: =IF('Data (Master Table)'!$B50 = $K$1, 'Data (Master Table)'!D50, "") -> Volunteer attraction and retention | C5: =IF('Data (Master Table)'!$B50 = $K$1, 'Data (Master Table)'!E50, "") -> Staff retention & morale | D5: =IF('Data (Master Table)'!$B50 = $K$1, 'Data (Master Table)'!F50, "") -> Volunteers praised by Leaders, Volunteer yearly event | E5: =IF('Data (Master Table)'!$B50 = $K$1, 'Data (Master Table)'!G50, "") -> OPEX | F5: =IF('Data (Master Table)'!$B50 = $K$1, 'Data (Master Table)'!H50, "") -> End of March End of June End of Sept | G5: =IF('Data (Master Table)'!$B50 = $K$1, 'Data (Master Table)'!I50, "") -> Amer | H5: =IF('Data (Master Table)'!$B50 = $K$1, 'Data (Master Table)'!J50, "") -> Medium | ... J5: =IF('Data (Master Table)'!$B50 = $K$1, 'Data (Master Table)'!L50, "") -> 46053 | K5: Volunteer recognition & retention programme. considering Perkbox and other reward schemes. | L5: 3 | M5: Badges/PerkBox Dinner/awards; Yusra training | N5: 1.Training starting 18.01.26 2. volunteer dinner to be arranged post ramadan 01.04.26 3. Badges/lanyards 30.03.26 | O5: Amer to arrange sponsors and speakers for post Ramadan volunteer dinner as per last year. Following a thank you dinner at AEC arranged by Shaffiq and Shazli, I have separated the Leads award ceremony into the 'MOscars' to be held in the first week in April or first week of June. Families of leads to also be invited to acknowledge their support in the process. | P5: In Progress | Q5: We did see some new voliunteers sign up at Ramadan but these were drated in the 'Ramadan group' headed by Br Tauffique and Br Shazli who are notably not part of Leads Utd and contunues to be a bone of contention. | R5: 0.8 | S5: sponsors to include Abrahams, Cuppa Chai, Langthorne Pharmacy, Garden Square Denta, Kayi Crossfit. MOSCARS Lead Volunteer awards ceremony delivered successfully. Some excellent feedback from this especially with encoragement for youth memebers. Consideration for these youth members to form a youth council or shadow directors committee. Afsor has stepped back from youth activitie for now due to personal reasons. Will need to organise youth board meeting.
A6: =IF('Data (Master Table)'!$B51 = $K$1, 'Data (Master Table)'!C51, "") -> YES | B6: =IF('Data (Master Table)'!$B51 = $K$1, 'Data (Master Table)'!D51, "") -> Improved performance in key areas | C6: =IF('Data (Master Table)'!$B51 = $K$1, 'Data (Master Table)'!E51, "") -> Make important functions work better, prevent burnout | D6: =IF('Data (Master Table)'!$B51 = $K$1, 'Data (Master Table)'!F51, "") -> Digital, Marketing and Outreach teams limited human resources | E6: =IF('Data (Master Table)'!$B51 = $K$1, 'Data (Master Table)'!G51, "") -> OPEX | F6: =IF('Data (Master Table)'!$B51 = $K$1, 'Data (Master Table)'!H51, "") -> End of March End of June End of Sept | G6: =IF('Data (Master Table)'!$B51 = $K$1, 'Data (Master Table)'!I51, "") -> Amer | H6: =IF('Data (Master Table)'!$B51 = $K$1, 'Data (Master Table)'!J51, "") -> High | ... J6: =IF('Data (Master Table)'!$B51 = $K$1, 'Data (Master Table)'!L51, "") -> 46203 | K6: Increase volunteers in Digital, Marketing and Outreach Teams | L6: 3 | M6: Role profiles; mentoring; appraisal process | N6: Volunteer drive during Ramadan | O6: Request Imam to advertise volunteer rercuitment during Ramadan | P6: In Progress | Q6: Imam has his own ideasabout volunteer training. He has run some Zoom online training session pre-Ramadan. | R6: 0.5 | S6: Imam Ossama had mentioned volunteers for Ramadan at Jummah Khutbah . After the departure of Imam Ossama we have not as yet led a volunteer drive but individiual gropups are reaching out to theoir own networks to recruit eg dawah project Ahmed Rawi. Still need top recruit further for SEND Tech team, and Scouts following imminent departure of Saira who is currently Lead.
A7: =IF('Data (Master Table)'!$B52 = $K$1, 'Data (Master Table)'!C52, "") | B7: =IF('Data (Master Table)'!$B52 = $K$1, 'Data (Master Table)'!D52, "") | C7: =IF('Data (Master Table)'!$B52 = $K$1, 'Data (Master Table)'!E52, "") | D7: =IF('Data (Master Table)'!$B52 = $K$1, 'Data (Master Table)'!F52, "") | E7: =IF('Data (Master Table)'!$B52 = $K$1, 'Data (Master Table)'!G52, "") | F7: =IF('Data (Master Table)'!$B52 = $K$1, 'Data (Master Table)'!H52, "") | G7: =IF('Data (Master Table)'!$B52 = $K$1, 'Data (Master Table)'!I52, "") | H7: =IF('Data (Master Table)'!$B52 = $K$1, 'Data (Master Table)'!J52, "") | ... J7: =IF('Data (Master Table)'!$B52 = $K$1, 'Data (Master Table)'!L52, "")
A8: =IF('Data (Master Table)'!$B53 = $K$1, 'Data (Master Table)'!C53, "") | B8: =IF('Data (Master Table)'!$B53 = $K$1, 'Data (Master Table)'!D53, "") | C8: =IF('Data (Master Table)'!$B53 = $K$1, 'Data (Master Table)'!E53, "") | D8: =IF('Data (Master Table)'!$B53 = $K$1, 'Data (Master Table)'!F53, "") | E8: =IF('Data (Master Table)'!$B53 = $K$1, 'Data (Master Table)'!G53, "") | F8: =IF('Data (Master Table)'!$B53 = $K$1, 'Data (Master Table)'!H53, "") | G8: =IF('Data (Master Table)'!$B53 = $K$1, 'Data (Master Table)'!I53, "") | H8: =IF('Data (Master Table)'!$B53 = $K$1, 'Data (Master Table)'!J53, "") | ... J8: =IF('Data (Master Table)'!$B53 = $K$1, 'Data (Master Table)'!L53, "")
A9: =IF('Data (Master Table)'!$B54 = $K$1, 'Data (Master Table)'!C54, "") | B9: =IF('Data (Master Table)'!$B54 = $K$1, 'Data (Master Table)'!D54, "") | C9: =IF('Data (Master Table)'!$B54 = $K$1, 'Data (Master Table)'!E54, "") | D9: =IF('Data (Master Table)'!$B54 = $K$1, 'Data (Master Table)'!F54, "") | E9: =IF('Data (Master Table)'!$B54 = $K$1, 'Data (Master Table)'!G54, "") | F9: =IF('Data (Master Table)'!$B54 = $K$1, 'Data (Master Table)'!H54, "") | G9: =IF('Data (Master Table)'!$B54 = $K$1, 'Data (Master Table)'!I54, "") | H9: =IF('Data (Master Table)'!$B54 = $K$1, 'Data (Master Table)'!J54, "") | ... J9: =IF('Data (Master Table)'!$B54 = $K$1, 'Data (Master Table)'!L54, "")
A10: =IF('Data (Master Table)'!$B55 = $K$1, 'Data (Master Table)'!C55, "") | B10: =IF('Data (Master Table)'!$B55 = $K$1, 'Data (Master Table)'!D55, "") | C10: =IF('Data (Master Table)'!$B55 = $K$1, 'Data (Master Table)'!E55, "") | D10: =IF('Data (Master Table)'!$B55 = $K$1, 'Data (Master Table)'!F55, "") | E10: =IF('Data (Master Table)'!$B55 = $K$1, 'Data (Master Table)'!G55, "") | F10: =IF('Data (Master Table)'!$B55 = $K$1, 'Data (Master Table)'!H55, "") | G10: =IF('Data (Master Table)'!$B55 = $K$1, 'Data (Master Table)'!I55, "") | H10: =IF('Data (Master Table)'!$B55 = $K$1, 'Data (Master Table)'!J55, "") | ... J10: =IF('Data (Master Table)'!$B55 = $K$1, 'Data (Master Table)'!L55, "")
A11: =IF('Data (Master Table)'!$B56 = $K$1, 'Data (Master Table)'!C56, "") | B11: =IF('Data (Master Table)'!$B56 = $K$1, 'Data (Master Table)'!D56, "") | C11: =IF('Data (Master Table)'!$B56 = $K$1, 'Data (Master Table)'!E56, "") | D11: =IF('Data (Master Table)'!$B56 = $K$1, 'Data (Master Table)'!F56, "") | E11: =IF('Data (Master Table)'!$B56 = $K$1, 'Data (Master Table)'!G56, "") | F11: =IF('Data (Master Table)'!$B56 = $K$1, 'Data (Master Table)'!H56, "") | G11: =IF('Data (Master Table)'!$B56 = $K$1, 'Data (Master Table)'!I56, "") | H11: =IF('Data (Master Table)'!$B56 = $K$1, 'Data (Master Table)'!J56, "") | ... J11: =IF('Data (Master Table)'!$B56 = $K$1, 'Data (Master Table)'!L56, "")
A12: =IF('Data (Master Table)'!$B57 = $K$1, 'Data (Master Table)'!C57, "") | B12: =IF('Data (Master Table)'!$B57 = $K$1, 'Data (Master Table)'!D57, "") | C12: =IF('Data (Master Table)'!$B57 = $K$1, 'Data (Master Table)'!E57, "") | D12: =IF('Data (Master Table)'!$B57 = $K$1, 'Data (Master Table)'!F57, "") | E12: =IF('Data (Master Table)'!$B57 = $K$1, 'Data (Master Table)'!G57, "") | F12: =IF('Data (Master Table)'!$B57 = $K$1, 'Data (Master Table)'!H57, "") | G12: =IF('Data (Master Table)'!$B57 = $K$1, 'Data (Master Table)'!I57, "") | H12: =IF('Data (Master Table)'!$B57 = $K$1, 'Data (Master Table)'!J57, "") | ... J12: =IF('Data (Master Table)'!$B57 = $K$1, 'Data (Master Table)'!L57, "")
A13: =IF('Data (Master Table)'!$B58 = $K$1, 'Data (Master Table)'!C58, "") | B13: =IF('Data (Master Table)'!$B58 = $K$1, 'Data (Master Table)'!D58, "") | C13: =IF('Data (Master Table)'!$B58 = $K$1, 'Data (Master Table)'!E58, "") | D13: =IF('Data (Master Table)'!$B58 = $K$1, 'Data (Master Table)'!F58, "") | E13: =IF('Data (Master Table)'!$B58 = $K$1, 'Data (Master Table)'!G58, "") | F13: =IF('Data (Master Table)'!$B58 = $K$1, 'Data (Master Table)'!H58, "") | G13: =IF('Data (Master Table)'!$B58 = $K$1, 'Data (Master Table)'!I58, "") | H13: =IF('Data (Master Table)'!$B58 = $K$1, 'Data (Master Table)'!J58, "") | ... J13: =IF('Data (Master Table)'!$B58 = $K$1, 'Data (Master Table)'!L58, "")
A14: =IF('Data (Master Table)'!$B59 = $K$1, 'Data (Master Table)'!C59, "") | B14: =IF('Data (Master Table)'!$B59 = $K$1, 'Data (Master Table)'!D59, "") | C14: =IF('Data (Master Table)'!$B59 = $K$1, 'Data (Master Table)'!E59, "") | D14: =IF('Data (Master Table)'!$B59 = $K$1, 'Data (Master Table)'!F59, "") | E14: =IF('Data (Master Table)'!$B59 = $K$1, 'Data (Master Table)'!G59, "") | F14: =IF('Data (Master Table)'!$B59 = $K$1, 'Data (Master Table)'!H59, "") | G14: =IF('Data (Master Table)'!$B59 = $K$1, 'Data (Master Table)'!I59, "") | H14: =IF('Data (Master Table)'!$B59 = $K$1, 'Data (Master Table)'!J59, "") | ... J14: =IF('Data (Master Table)'!$B59 = $K$1, 'Data (Master Table)'!L59, "")
A15: =IF('Data (Master Table)'!$B60 = $K$1, 'Data (Master Table)'!C60, "") | B15: =IF('Data (Master Table)'!$B60 = $K$1, 'Data (Master Table)'!D60, "") | C15: =IF('Data (Master Table)'!$B60 = $K$1, 'Data (Master Table)'!E60, "") | D15: =IF('Data (Master Table)'!$B60 = $K$1, 'Data (Master Table)'!F60, "") | E15: =IF('Data (Master Table)'!$B60 = $K$1, 'Data (Master Table)'!G60, "") | F15: =IF('Data (Master Table)'!$B60 = $K$1, 'Data (Master Table)'!H60, "") | G15: =IF('Data (Master Table)'!$B60 = $K$1, 'Data (Master Table)'!I60, "") | H15: =IF('Data (Master Table)'!$B60 = $K$1, 'Data (Master Table)'!J60, "") | ... J15: =IF('Data (Master Table)'!$B60 = $K$1, 'Data (Master Table)'!L60, "")
A16: =IF('Data (Master Table)'!$B61 = $K$1, 'Data (Master Table)'!C61, "") | B16: =IF('Data (Master Table)'!$B61 = $K$1, 'Data (Master Table)'!D61, "") | C16: =IF('Data (Master Table)'!$B61 = $K$1, 'Data (Master Table)'!E61, "") | D16: =IF('Data (Master Table)'!$B61 = $K$1, 'Data (Master Table)'!F61, "") | E16: =IF('Data (Master Table)'!$B61 = $K$1, 'Data (Master Table)'!G61, "") | F16: =IF('Data (Master Table)'!$B61 = $K$1, 'Data (Master Table)'!H61, "") | G16: =IF('Data (Master Table)'!$B61 = $K$1, 'Data (Master Table)'!I61, "") | H16: =IF('Data (Master Table)'!$B61 = $K$1, 'Data (Master Table)'!J61, "") | ... J16: =IF('Data (Master Table)'!$B61 = $K$1, 'Data (Master Table)'!L61, "")

Sheet Community Activities
A1: ULTIMATE AIM : DEVELOP A VIBRANT CALENDAR OF ENGAGING EVENTS, GROW ATTENDANCE + VOLUNTEER APPRECIATION SLT Lead Avais | K1: ='Data (Master Table)'!W7 -> Community Activities
A2: ='Data (Master Table)'!C2 -> IS VALID | B2: ='Data (Master Table)'!D2 -> SMART Outcome | C2: ='Data (Master Table)'!E2 -> Benefit | D2: ='Data (Master Table)'!F2 -> Starting Point / Baseline | E2: ='Data (Master Table)'!G2 -> Department | F2: ='Data (Master Table)'!H2 -> Reported to OPEX | G2: ='Data (Master Table)'!I2 -> Responsible Person | H2: ='Data (Master Table)'!J2 -> Risk Level | ... S2: ='Data (Master Table)'!U2 -> Notes
A3: =IF('Data (Master Table)'!$B63 = $K$1, 'Data (Master Table)'!C63, "") -> YES | B3: =IF('Data (Master Table)'!$B63 = $K$1, 'Data (Master Table)'!D63, "") -> Vibrant Events Calendar | C3: =IF('Data (Master Table)'!$B63 = $K$1, 'Data (Master Table)'!E63, "") -> Cohesion & visibility | D3: =IF('Data (Master Table)'!$B63 = $K$1, 'Data (Master Table)'!F63, "") -> Approx. 6 activities per year; decentralised planning; limited follow-up/feedback loops | E3: =IF('Data (Master Table)'!$B63 = $K$1, 'Data (Master Table)'!G63, "") -> Events | F3: =IF('Data (Master Table)'!$B63 = $K$1, 'Data (Master Table)'!H63, "") -> End of March End of June End of Sept | G3: =IF('Data (Master Table)'!$B63 = $K$1, 'Data (Master Table)'!I63, "") -> Avais | H3: =IF('Data (Master Table)'!$B63 = $K$1, 'Data (Master Table)'!J63, "") -> Medium | ... J3: =IF('Data (Master Table)'!$B63 = $K$1, 'Data (Master Table)'!L63, "") -> 46295 | K3: Deliver 10 high-impact events. Quarterly themes; partnerships; family focus | L3: 6 | M3: Big ticket events: Community and Neighbour Consultations, Eids,Volunteer thank you, Mosque Fayre, family BBQ, talks. Communicate these through calendar, newsletters and Annual Report | P3: In Progress | R3: 0.7 | S3: Events wise, structure, lot of good things. Big community events we need to now plan post ramadan.
A4: =IF('Data (Master Table)'!$B64 = $K$1, 'Data (Master Table)'!C64, "") -> YES | B4: =IF('Data (Master Table)'!$B64 = $K$1, 'Data (Master Table)'!D64, "") -> Attendance growth | C4: =IF('Data (Master Table)'!$B64 = $K$1, 'Data (Master Table)'!E64, "") -> Broader engagement | D4: =IF('Data (Master Table)'!$B64 = $K$1, 'Data (Master Table)'!F64, "") -> Approx. 6 activities per year; decentralised planning; limited follow-up/feedback loops | E4: =IF('Data (Master Table)'!$B64 = $K$1, 'Data (Master Table)'!G64, "") -> Marketing | F4: =IF('Data (Master Table)'!$B64 = $K$1, 'Data (Master Table)'!H64, "") -> End of March End of June End of Sept | G4: =IF('Data (Master Table)'!$B64 = $K$1, 'Data (Master Table)'!I64, "") -> Ameera | H4: =IF('Data (Master Table)'!$B64 = $K$1, 'Data (Master Table)'!J64, "") -> Medium | ... J4: =IF('Data (Master Table)'!$B64 = $K$1, 'Data (Master Table)'!L64, "") -> 46295 | K4: Strengthen visibility and engagement of community activities via social media and WhatsApp, contributing to at least a 25% increase in event attendance vs 2025 baseline | L4: 3 | M4: 1. Coordinated social media & WhatsApp promotion for all major community events. 2. Published and regularly updated community events calendar (online and/or on-site). 3. Systematic post-event feedback and attendance tracking after major events. | N4: Jan 2026: Initial coordinated promotion in place + draft calendar created. Feb 2026: Online calendar live and used for Ramadan communications. Jun 2026: Regular promotion embedded + feedback piloted. Sept 2026: Approach fully embedded with systematic feedback and attendance tracking. | O4: Work with the Events Team to coordinate promotion of major community activities via social media and WhatsApp; work with the Digital Team to maintain an up-to-date online events calendar; and support the rollout of simple post-event feedback and attendance tracking. | P4: In Progress | R4: 0.7 | S4: Ramadan programme successfully delivered with very strong attendance and engagement; mosque consistently full across key events. Coordinated promotion via WhatsApp and social media, supported by live events calendar. Positive feedback and compliments received from the community
A5: =IF('Data (Master Table)'!$B65 = $K$1, 'Data (Master Table)'!C65, "") -> YES | B5: =IF('Data (Master Table)'!$B65 = $K$1, 'Data (Master Table)'!D65, "") -> Events well advertised and attended | C5: =IF('Data (Master Table)'!$B65 = $K$1, 'Data (Master Table)'!E65, "") -> Increased event attendance,staff booking system | D5: =IF('Data (Master Table)'!$B65 = $K$1, 'Data (Master Table)'!F65, "") -> No calendar currently available | E5: =IF('Data (Master Table)'!$B65 = $K$1, 'Data (Master Table)'!G65, "") -> Tech | F5: =IF('Data (Master Table)'!$B65 = $K$1, 'Data (Master Table)'!H65, "") -> End of March End of June End of Sept | G5: =IF('Data (Master Table)'!$B65 = $K$1, 'Data (Master Table)'!I65, "") -> Khaleeq | H5: =IF('Data (Master Table)'!$B65 = $K$1, 'Data (Master Table)'!J65, "") -> High | ... J5: =IF('Data (Master Table)'!$B65 = $K$1, 'Data (Master Table)'!L65, "") -> 46173 | K5: Clear electronic calendar of events for staff and community to see/access | L5: 3 | M5: 1. Set up calendars 2. Integrate 3. Share | N5: 1. Jan 2.Jan 3. Feb | P5: In Progress | R5: 0.7
A6: =IF('Data (Master Table)'!$B66 = $K$1, 'Data (Master Table)'!C66, "") | B6: =IF('Data (Master Table)'!$B66 = $K$1, 'Data (Master Table)'!D66, "") | C6: =IF('Data (Master Table)'!$B66 = $K$1, 'Data (Master Table)'!E66, "") | D6: =IF('Data (Master Table)'!$B66 = $K$1, 'Data (Master Table)'!F66, "") | E6: =IF('Data (Master Table)'!$B66 = $K$1, 'Data (Master Table)'!G66, "") | F6: =IF('Data (Master Table)'!$B66 = $K$1, 'Data (Master Table)'!H66, "") | G6: =IF('Data (Master Table)'!$B66 = $K$1, 'Data (Master Table)'!I66, "") | H6: =IF('Data (Master Table)'!$B66 = $K$1, 'Data (Master Table)'!J66, "") | ... J6: =IF('Data (Master Table)'!$B66 = $K$1, 'Data (Master Table)'!L66, "")
A7: =IF('Data (Master Table)'!$B67 = $K$1, 'Data (Master Table)'!C67, "") | B7: =IF('Data (Master Table)'!$B67 = $K$1, 'Data (Master Table)'!D67, "") | C7: =IF('Data (Master Table)'!$B67 = $K$1, 'Data (Master Table)'!E67, "") | D7: =IF('Data (Master Table)'!$B67 = $K$1, 'Data (Master Table)'!F67, "") | E7: =IF('Data (Master Table)'!$B67 = $K$1, 'Data (Master Table)'!G67, "") | F7: =IF('Data (Master Table)'!$B67 = $K$1, 'Data (Master Table)'!H67, "") | G7: =IF('Data (Master Table)'!$B67 = $K$1, 'Data (Master Table)'!I67, "") | H7: =IF('Data (Master Table)'!$B67 = $K$1, 'Data (Master Table)'!J67, "") | ... J7: =IF('Data (Master Table)'!$B67 = $K$1, 'Data (Master Table)'!L67, "")
A8: =IF('Data (Master Table)'!$B68 = $K$1, 'Data (Master Table)'!C68, "") | B8: =IF('Data (Master Table)'!$B68 = $K$1, 'Data (Master Table)'!D68, "") | C8: =IF('Data (Master Table)'!$B68 = $K$1, 'Data (Master Table)'!E68, "") | D8: =IF('Data (Master Table)'!$B68 = $K$1, 'Data (Master Table)'!F68, "") | E8: =IF('Data (Master Table)'!$B68 = $K$1, 'Data (Master Table)'!G68, "") | F8: =IF('Data (Master Table)'!$B68 = $K$1, 'Data (Master Table)'!H68, "") | G8: =IF('Data (Master Table)'!$B68 = $K$1, 'Data (Master Table)'!I68, "") | H8: =IF('Data (Master Table)'!$B68 = $K$1, 'Data (Master Table)'!J68, "") | ... J8: =IF('Data (Master Table)'!$B68 = $K$1, 'Data (Master Table)'!L68, "")
A9: =IF('Data (Master Table)'!$B69 = $K$1, 'Data (Master Table)'!C69, "") | B9: =IF('Data (Master Table)'!$B69 = $K$1, 'Data (Master Table)'!D69, "") | C9: =IF('Data (Master Table)'!$B69 = $K$1, 'Data (Master Table)'!E69, "") | D9: =IF('Data (Master Table)'!$B69 = $K$1, 'Data (Master Table)'!F69, "") | E9: =IF('Data (Master Table)'!$B69 = $K$1, 'Data (Master Table)'!G69, "") | F9: =IF('Data (Master Table)'!$B69 = $K$1, 'Data (Master Table)'!H69, "") | G9: =IF('Data (Master Table)'!$B69 = $K$1, 'Data (Master Table)'!I69, "") | H9: =IF('Data (Master Table)'!$B69 = $K$1, 'Data (Master Table)'!J69, "") | ... J9: =IF('Data (Master Table)'!$B69 = $K$1, 'Data (Master Table)'!L69, "")
A10: =IF('Data (Master Table)'!$B70 = $K$1, 'Data (Master Table)'!C70, "") | B10: =IF('Data (Master Table)'!$B70 = $K$1, 'Data (Master Table)'!D70, "") | C10: =IF('Data (Master Table)'!$B70 = $K$1, 'Data (Master Table)'!E70, "") | D10: =IF('Data (Master Table)'!$B70 = $K$1, 'Data (Master Table)'!F70, "") | E10: =IF('Data (Master Table)'!$B70 = $K$1, 'Data (Master Table)'!G70, "") | F10: =IF('Data (Master Table)'!$B70 = $K$1, 'Data (Master Table)'!H70, "") | G10: =IF('Data (Master Table)'!$B70 = $K$1, 'Data (Master Table)'!I70, "") | H10: =IF('Data (Master Table)'!$B70 = $K$1, 'Data (Master Table)'!J70, "") | ... J10: =IF('Data (Master Table)'!$B70 = $K$1, 'Data (Master Table)'!L70, "")
A11: =IF('Data (Master Table)'!$B71 = $K$1, 'Data (Master Table)'!C71, "") | B11: =IF('Data (Master Table)'!$B71 = $K$1, 'Data (Master Table)'!D71, "") | C11: =IF('Data (Master Table)'!$B71 = $K$1, 'Data (Master Table)'!E71, "") | D11: =IF('Data (Master Table)'!$B71 = $K$1, 'Data (Master Table)'!F71, "") | E11: =IF('Data (Master Table)'!$B71 = $K$1, 'Data (Master Table)'!G71, "") | F11: =IF('Data (Master Table)'!$B71 = $K$1, 'Data (Master Table)'!H71, "") | G11: =IF('Data (Master Table)'!$B71 = $K$1, 'Data (Master Table)'!I71, "") | H11: =IF('Data (Master Table)'!$B71 = $K$1, 'Data (Master Table)'!J71, "") | ... J11: =IF('Data (Master Table)'!$B71 = $K$1, 'Data (Master Table)'!L71, "")
A12: =IF('Data (Master Table)'!$B72 = $K$1, 'Data (Master Table)'!C72, "") | B12: =IF('Data (Master Table)'!$B72 = $K$1, 'Data (Master Table)'!D72, "") | C12: =IF('Data (Master Table)'!$B72 = $K$1, 'Data (Master Table)'!E72, "") | D12: =IF('Data (Master Table)'!$B72 = $K$1, 'Data (Master Table)'!F72, "") | E12: =IF('Data (Master Table)'!$B72 = $K$1, 'Data (Master Table)'!G72, "") | F12: =IF('Data (Master Table)'!$B72 = $K$1, 'Data (Master Table)'!H72, "") | G12: =IF('Data (Master Table)'!$B72 = $K$1, 'Data (Master Table)'!I72, "") | H12: =IF('Data (Master Table)'!$B72 = $K$1, 'Data (Master Table)'!J72, "") | ... J12: =IF('Data (Master Table)'!$B72 = $K$1, 'Data (Master Table)'!L72, "")
A13: =IF('Data (Master Table)'!$B73 = $K$1, 'Data (Master Table)'!C73, "") | B13: =IF('Data (Master Table)'!$B73 = $K$1, 'Data (Master Table)'!D73, "") | C13: =IF('Data (Master Table)'!$B73 = $K$1, 'Data (Master Table)'!E73, "") | D13: =IF('Data (Master Table)'!$B73 = $K$1, 'Data (Master Table)'!F73, "") | E13: =IF('Data (Master Table)'!$B73 = $K$1, 'Data (Master Table)'!G73, "") | F13: =IF('Data (Master Table)'!$B73 = $K$1, 'Data (Master Table)'!H73, "") | G13: =IF('Data (Master Table)'!$B73 = $K$1, 'Data (Master Table)'!I73, "") | H13: =IF('Data (Master Table)'!$B73 = $K$1, 'Data (Master Table)'!J73, "") | ... J13: =IF('Data (Master Table)'!$B73 = $K$1, 'Data (Master Table)'!L73, "")
A14: =IF('Data (Master Table)'!$B74 = $K$1, 'Data (Master Table)'!C74, "") | B14: =IF('Data (Master Table)'!$B74 = $K$1, 'Data (Master Table)'!D74, "") | C14: =IF('Data (Master Table)'!$B74 = $K$1, 'Data (Master Table)'!E74, "") | D14: =IF('Data (Master Table)'!$B74 = $K$1, 'Data (Master Table)'!F74, "") | E14: =IF('Data (Master Table)'!$B74 = $K$1, 'Data (Master Table)'!G74, "") | F14: =IF('Data (Master Table)'!$B74 = $K$1, 'Data (Master Table)'!H74, "") | G14: =IF('Data (Master Table)'!$B74 = $K$1, 'Data (Master Table)'!I74, "") | H14: =IF('Data (Master Table)'!$B74 = $K$1, 'Data (Master Table)'!J74, "") | ... J14: =IF('Data (Master Table)'!$B74 = $K$1, 'Data (Master Table)'!L74, "")
A15: =IF('Data (Master Table)'!$B75 = $K$1, 'Data (Master Table)'!C75, "") | B15: =IF('Data (Master Table)'!$B75 = $K$1, 'Data (Master Table)'!D75, "") | C15: =IF('Data (Master Table)'!$B75 = $K$1, 'Data (Master Table)'!E75, "") | D15: =IF('Data (Master Table)'!$B75 = $K$1, 'Data (Master Table)'!F75, "") | E15: =IF('Data (Master Table)'!$B75 = $K$1, 'Data (Master Table)'!G75, "") | F15: =IF('Data (Master Table)'!$B75 = $K$1, 'Data (Master Table)'!H75, "") | G15: =IF('Data (Master Table)'!$B75 = $K$1, 'Data (Master Table)'!I75, "") | H15: =IF('Data (Master Table)'!$B75 = $K$1, 'Data (Master Table)'!J75, "") | ... J15: =IF('Data (Master Table)'!$B75 = $K$1, 'Data (Master Table)'!L75, "")
A16: =IF('Data (Master Table)'!$B76 = $K$1, 'Data (Master Table)'!C76, "") | B16: =IF('Data (Master Table)'!$B76 = $K$1, 'Data (Master Table)'!D76, "") | C16: =IF('Data (Master Table)'!$B76 = $K$1, 'Data (Master Table)'!E76, "") | D16: =IF('Data (Master Table)'!$B76 = $K$1, 'Data (Master Table)'!F76, "") | E16: =IF('Data (Master Table)'!$B76 = $K$1, 'Data (Master Table)'!G76, "") | F16: =IF('Data (Master Table)'!$B76 = $K$1, 'Data (Master Table)'!H76, "") | G16: =IF('Data (Master Table)'!$B76 = $K$1, 'Data (Master Table)'!I76, "") | H16: =IF('Data (Master Table)'!$B76 = $K$1, 'Data (Master Table)'!J76, "") | ... J16: =IF('Data (Master Table)'!$B76 = $K$1, 'Data (Master Table)'!L76, "")

Sheet Spiritual Focus
A1: ULTIMATE AIM : COMMUNITY TRANSFORMATION SLT Lead Omar Taha | K1: ='Data (Master Table)'!W8 -> Spiritual Focus
A2: ='Data (Master Table)'!C2 -> IS VALID | B2: ='Data (Master Table)'!D2 -> SMART Outcome | C2: ='Data (Master Table)'!E2 -> Benefit | D2: ='Data (Master Table)'!F2 -> Starting Point / Baseline | E2: ='Data (Master Table)'!G2 -> Department | F2: ='Data (Master Table)'!H2 -> Reported to OPEX | G2: ='Data (Master Table)'!I2 -> Responsible Person | H2: ='Data (Master Table)'!J2 -> Risk Level | ... S2: ='Data (Master Table)'!U2 -> Notes
A3: =IF('Data (Master Table)'!$B78 = $K$1, 'Data (Master Table)'!C78, "") -> YES | B3: =IF('Data (Master Table)'!$B78 = $K$1, 'Data (Master Table)'!D78, "") -> Learning & practice | C3: =IF('Data (Master Table)'!$B78 = $K$1, 'Data (Master Table)'!E78, "") -> Deeper community spirituality | D3: =IF('Data (Master Table)'!$B78 = $K$1, 'Data (Master Table)'!F78, "") -> Regular Jumu’ah/Ramadan programmes; limited modular learning beyond madrassa/occasional talks | E3: =IF('Data (Master Table)'!$B78 = $K$1, 'Data (Master Table)'!G78, "") -> Islamic Affairs | F3: =IF('Data (Master Table)'!$B78 = $K$1, 'Data (Master Table)'!H78, "") -> End of March End of June End of Sept | G3: =IF('Data (Master Table)'!$B78 = $K$1, 'Data (Master Table)'!I78, "") -> Omar | H3: =IF('Data (Master Table)'!$B78 = $K$1, 'Data (Master Table)'!J78, "") -> Medium | ... J3: =IF('Data (Master Table)'!$B78 = $K$1, 'Data (Master Table)'!L78, "") -> 46295 | K3: Increase participation in structured spiritual education by 30% by September 2026. | L3: 3 | M3: 1. Modular spiritual education courses introduced beyond Jumu’ah and Ramadan. 2. Family-friendly timings implemented to widen access to learning programmes. | N3: Jan 2026: Pilot modular spiritual education sessions (including Ramadan programmes). Jun 2026: Regular modular courses running with family-friendly timings. Sept 2026: Programme fully embedded with sustained and increased attendance. | O3: Develop and deliver modular spiritual education programmes, building on existing classes and talks; introduce family-friendly timings and expand engagement with youth, children, and reverts. | P3: In Progress | R3: 0.9 | S3: 1. Weekly tafsir started June for all members of family 2. Sisters fortnightly halaqah started. 3. Youth 16-25 circle for men started. 4. Youth monthly q&a started. 5. Youth Rawa tales planned in June 6. Fajr club felt covers brothers circle 7. Guest khateebs Sh Ziyad and Sh Zubayr 8. Completed Ramadan and Dhul Hijjah social media reminders 9. In need of revert, youth sisters and 11-15 brothers 10. Possibly an Isha reminder (more appropriate for Imam)
A4: =IF('Data (Master Table)'!$B82 = $K$1, 'Data (Master Table)'!C82, "") -> YES | B4: =IF('Data (Master Table)'!$B82 = $K$1, 'Data (Master Table)'!D82, "") -> Learning & practice | C4: =IF('Data (Master Table)'!$B82 = $K$1, 'Data (Master Table)'!E82, "") -> Deeper community spirituality | D4: =IF('Data (Master Table)'!$B82 = $K$1, 'Data (Master Table)'!F82, "") -> Limited talks to date | E4: =IF('Data (Master Table)'!$B82 = $K$1, 'Data (Master Table)'!G82, "") -> Islamic Affairs | F4: =IF('Data (Master Table)'!$B82 = $K$1, 'Data (Master Table)'!H82, "") -> End of March End of June End of Sept | G4: =IF('Data (Master Table)'!$B82 = $K$1, 'Data (Master Table)'!I82, "") -> Omar | H4: =IF('Data (Master Table)'!$B82 = $K$1, 'Data (Master Table)'!J82, "") -> Medium | ... J4: =IF('Data (Master Table)'!$B82 = $K$1, 'Data (Master Table)'!L82, "") -> 46295 | K4: Deliver a consistent programme of small and large-scale talks for diverse demographics to increase engagement and spiritual understanding by September 2026. | L4: 4 | M4: 1. Monthly themed talks delivered for key demographics. 2. Guest speakers introduced for selected sessions. 3. Increased attendance and engagement across talk programmes. | N4: Jan 2026: Monthly talk structure established Jun 2026: Guest speakers and varied topics introduced Sept 2026: Programme embedded with strong attendance | O4: Plan and deliver regular talks across different demographics, including khutbahs, short reminders, and guest sessions, to increase engagement and accessibility. | P4: In Progress | R4: 0.6 | S4: 1. Plan for September Ilm Essentials 1 year programme 2. Plan for Tajweed for ladies Sep and for Arabic ladies tajweed 3. Seeking a lead for Arabic and men's tajweed 4. Agreed regular marriage related talks 5. History talk 21st June 6. Planning riba talk with Ustadh Umer Sulaiman 7. Completed Ramadan and Hajj talks 8. Planning Mothers Quran group 9. Aim Khutbah delivery workshop by Sep 10. Planning a sisters q&a (either Omar or Imam) 11. Planning hifdh programme (Imam)
A5: =IF('Data (Master Table)'!$B81 = $K$1, 'Data (Master Table)'!C81, "") -> YES | B5: =IF('Data (Master Table)'!$B81 = $K$1, 'Data (Master Table)'!D81, "") -> Al-Qalam Madrassa expansion | C5: =IF('Data (Master Table)'!$B81 = $K$1, 'Data (Master Table)'!E81, "") -> Education for young people in our community, development fo youth leaders | D5: =IF('Data (Master Table)'!$B81 = $K$1, 'Data (Master Table)'!F81, "") -> Already have an established Madrassa | E5: =IF('Data (Master Table)'!$B81 = $K$1, 'Data (Master Table)'!G81, "") -> Education | F5: =IF('Data (Master Table)'!$B81 = $K$1, 'Data (Master Table)'!H81, "") -> End of March End of June End of Sept | G5: =IF('Data (Master Table)'!$B81 = $K$1, 'Data (Master Table)'!I81, "") -> Omar | H5: =IF('Data (Master Table)'!$B81 = $K$1, 'Data (Master Table)'!J81, "") -> Medium | ... J5: =IF('Data (Master Table)'!$B81 = $K$1, 'Data (Master Table)'!L81, "") -> 46295 | K5: Increase student numbers whilst maintaining educational standards | L5: 1 | M5: 1. New leadership team settled into roles 2. Move to Ravenswood secured by June 2026 | N5: 1. End of March 2. End of June | P5: In Progress | R5: 0.8 | S5: Ravenswood move complete! Curriculum has been proposed, and being finalised. Omar to plan a meeting with teachers on this. Leadership team better place than last year, appears to have worked. Awaiting full report by next month. Awaiting open day and review of numbers in coming month.
A6: =IF('Data (Master Table)'!$B80 = $K$1, 'Data (Master Table)'!C80, "") -> YES | B6: =IF('Data (Master Table)'!$B80 = $K$1, 'Data (Master Table)'!D80, "") -> Community retreats | C6: =IF('Data (Master Table)'!$B80 = $K$1, 'Data (Master Table)'!E80, "") -> Renewal & connection | D6: =IF('Data (Master Table)'!$B80 = $K$1, 'Data (Master Table)'!F80, "") -> Limited spiritual development to date | E6: =IF('Data (Master Table)'!$B80 = $K$1, 'Data (Master Table)'!G80, "") -> Islamic Affairs | F6: =IF('Data (Master Table)'!$B80 = $K$1, 'Data (Master Table)'!H80, "") -> End of March End of June End of Sept | G6: =IF('Data (Master Table)'!$B80 = $K$1, 'Data (Master Table)'!I80, "") -> Omar | H6: =IF('Data (Master Table)'!$B80 = $K$1, 'Data (Master Table)'!J80, "") -> Medium | ... J6: =IF('Data (Master Table)'!$B80 = $K$1, 'Data (Master Table)'!L80, "") -> 46265 | K6: Deliver quarterly spiritual retreats and Qur’an reflection circles to strengthen community connection and spiritual growth by August 2026. | L6: 3 | M6: 1. Retreat structure and programme designed (including Qur’an reflection focus). 2. Logistics in place (venue, childcare, sign-ups). 3. First retreat delivered and model refined for ongoing quarterly delivery. | N6: Jan 2026: Retreat format and programme agreed. Jun 2026: First retreat delivered with logistics in place. Aug 2026: Quarterly retreat model embedded. | O6: Plan and deliver quarterly retreats including Qur’an reflection sessions, ensuring accessibility through childcare and structured sign-up processes. | P6: In Progress | R6: 0.3 | S6: To consider embedding into camp retreat, or considering a youth excurcusion with reminders. Not yet ready for full education retreat given my time committments - potentially one for an incoming Imam
A7: =IF('Data (Master Table)'!$B83 = $K$1, 'Data (Master Table)'!C83, "") -> YES | B7: =IF('Data (Master Table)'!$B83 = $K$1, 'Data (Master Table)'!D83, "") -> Spiritual self- development | C7: =IF('Data (Master Table)'!$B83 = $K$1, 'Data (Master Table)'!E83, "") -> Deeper individual spirituality | D7: =IF('Data (Master Table)'!$B83 = $K$1, 'Data (Master Table)'!F83, "") -> Not formally developed | E7: =IF('Data (Master Table)'!$B83 = $K$1, 'Data (Master Table)'!G83, "") -> Exec | F7: =IF('Data (Master Table)'!$B83 = $K$1, 'Data (Master Table)'!H83, "") -> End of March End of June End of Sept | G7: =IF('Data (Master Table)'!$B83 = $K$1, 'Data (Master Table)'!I83, "") -> Shaffiq | H7: =IF('Data (Master Table)'!$B83 = $K$1, 'Data (Master Table)'!J83, "") -> Medium | ... J7: =IF('Data (Master Table)'!$B83 = $K$1, 'Data (Master Table)'!L83, "") -> 46295 | K7: A system which allows individual community members to begin a tracked, AI driven,journey starting from where they are, built upon the resources available at the masjid. Includes training, courses and volunteering | L7: 2 | M7: 1. Get MosqueApp running 2. Develop and deploy framework for personal self-development | N7: 1. Jan 2. Before Ramadhan | O7: Found possible suitable provider. had second round meetings with him. Next steps: asked him for a one pager explaining his product, a one pager for my Education Lead, detailing Islamic education authenticity, and then we will meet to finalise the financials and how that works, and how to embed the product via ai to our masjid, its services, volunteering etc. Decided to launch via our website and not wait until app is completed. | P7: Delayed | R7: 0.6 | S7: Need Khalyfa guy to produce scholar endorsement and fine checking for educational content before we proceed any further
A8: =IF('Data (Master Table)'!$B84 = $K$1, 'Data (Master Table)'!C84, "") | B8: =IF('Data (Master Table)'!$B84 = $K$1, 'Data (Master Table)'!D84, "") | C8: =IF('Data (Master Table)'!$B84 = $K$1, 'Data (Master Table)'!E84, "") | D8: =IF('Data (Master Table)'!$B84 = $K$1, 'Data (Master Table)'!F84, "") | E8: =IF('Data (Master Table)'!$B84 = $K$1, 'Data (Master Table)'!G84, "") | F8: =IF('Data (Master Table)'!$B84 = $K$1, 'Data (Master Table)'!H84, "") | G8: =IF('Data (Master Table)'!$B84 = $K$1, 'Data (Master Table)'!I84, "") | H8: =IF('Data (Master Table)'!$B84 = $K$1, 'Data (Master Table)'!J84, "") | ... J8: =IF('Data (Master Table)'!$B84 = $K$1, 'Data (Master Table)'!L84, "")
A9: =IF('Data (Master Table)'!$B85 = $K$1, 'Data (Master Table)'!C85, "") | B9: =IF('Data (Master Table)'!$B85 = $K$1, 'Data (Master Table)'!D85, "") | C9: =IF('Data (Master Table)'!$B85 = $K$1, 'Data (Master Table)'!E85, "") | D9: =IF('Data (Master Table)'!$B85 = $K$1, 'Data (Master Table)'!F85, "") | E9: =IF('Data (Master Table)'!$B85 = $K$1, 'Data (Master Table)'!G85, "") | F9: =IF('Data (Master Table)'!$B85 = $K$1, 'Data (Master Table)'!H85, "") | G9: =IF('Data (Master Table)'!$B85 = $K$1, 'Data (Master Table)'!I85, "") | H9: =IF('Data (Master Table)'!$B85 = $K$1, 'Data (Master Table)'!J85, "") | ... J9: =IF('Data (Master Table)'!$B85 = $K$1, 'Data (Master Table)'!L85, "")
A10: =IF('Data (Master Table)'!$B86 = $K$1, 'Data (Master Table)'!C86, "") | B10: =IF('Data (Master Table)'!$B86 = $K$1, 'Data (Master Table)'!D86, "") | C10: =IF('Data (Master Table)'!$B86 = $K$1, 'Data (Master Table)'!E86, "") | D10: =IF('Data (Master Table)'!$B86 = $K$1, 'Data (Master Table)'!F86, "") | E10: =IF('Data (Master Table)'!$B86 = $K$1, 'Data (Master Table)'!G86, "") | F10: =IF('Data (Master Table)'!$B86 = $K$1, 'Data (Master Table)'!H86, "") | G10: =IF('Data (Master Table)'!$B86 = $K$1, 'Data (Master Table)'!I86, "") | H10: =IF('Data (Master Table)'!$B86 = $K$1, 'Data (Master Table)'!J86, "") | ... J10: =IF('Data (Master Table)'!$B86 = $K$1, 'Data (Master Table)'!L86, "")
A11: =IF('Data (Master Table)'!$B87 = $K$1, 'Data (Master Table)'!C87, "") | B11: =IF('Data (Master Table)'!$B87 = $K$1, 'Data (Master Table)'!D87, "") | C11: =IF('Data (Master Table)'!$B87 = $K$1, 'Data (Master Table)'!E87, "") | D11: =IF('Data (Master Table)'!$B87 = $K$1, 'Data (Master Table)'!F87, "") | E11: =IF('Data (Master Table)'!$B87 = $K$1, 'Data (Master Table)'!G87, "") | F11: =IF('Data (Master Table)'!$B87 = $K$1, 'Data (Master Table)'!H87, "") | G11: =IF('Data (Master Table)'!$B87 = $K$1, 'Data (Master Table)'!I87, "") | H11: =IF('Data (Master Table)'!$B87 = $K$1, 'Data (Master Table)'!J87, "") | ... J11: =IF('Data (Master Table)'!$B87 = $K$1, 'Data (Master Table)'!L87, "")
A12: =IF('Data (Master Table)'!$B88 = $K$1, 'Data (Master Table)'!C88, "") | B12: =IF('Data (Master Table)'!$B88 = $K$1, 'Data (Master Table)'!D88, "") | C12: =IF('Data (Master Table)'!$B88 = $K$1, 'Data (Master Table)'!E88, "") | D12: =IF('Data (Master Table)'!$B88 = $K$1, 'Data (Master Table)'!F88, "") | E12: =IF('Data (Master Table)'!$B88 = $K$1, 'Data (Master Table)'!G88, "") | F12: =IF('Data (Master Table)'!$B88 = $K$1, 'Data (Master Table)'!H88, "") | G12: =IF('Data (Master Table)'!$B88 = $K$1, 'Data (Master Table)'!I88, "") | H12: =IF('Data (Master Table)'!$B88 = $K$1, 'Data (Master Table)'!J88, "") | ... J12: =IF('Data (Master Table)'!$B88 = $K$1, 'Data (Master Table)'!L88, "")
A13: =IF('Data (Master Table)'!$B89 = $K$1, 'Data (Master Table)'!C89, "") | B13: =IF('Data (Master Table)'!$B89 = $K$1, 'Data (Master Table)'!D89, "") | C13: =IF('Data (Master Table)'!$B89 = $K$1, 'Data (Master Table)'!E89, "") | D13: =IF('Data (Master Table)'!$B89 = $K$1, 'Data (Master Table)'!F89, "") | E13: =IF('Data (Master Table)'!$B89 = $K$1, 'Data (Master Table)'!G89, "") | F13: =IF('Data (Master Table)'!$B89 = $K$1, 'Data (Master Table)'!H89, "") | G13: =IF('Data (Master Table)'!$B89 = $K$1, 'Data (Master Table)'!I89, "") | H13: =IF('Data (Master Table)'!$B89 = $K$1, 'Data (Master Table)'!J89, "") | ... J13: =IF('Data (Master Table)'!$B89 = $K$1, 'Data (Master Table)'!L89, "")
A14: =IF('Data (Master Table)'!$B90 = $K$1, 'Data (Master Table)'!C90, "") | B14: =IF('Data (Master Table)'!$B90 = $K$1, 'Data (Master Table)'!D90, "") | C14: =IF('Data (Master Table)'!$B90 = $K$1, 'Data (Master Table)'!E90, "") | D14: =IF('Data (Master Table)'!$B90 = $K$1, 'Data (Master Table)'!F90, "") | E14: =IF('Data (Master Table)'!$B90 = $K$1, 'Data (Master Table)'!G90, "") | F14: =IF('Data (Master Table)'!$B90 = $K$1, 'Data (Master Table)'!H90, "") | G14: =IF('Data (Master Table)'!$B90 = $K$1, 'Data (Master Table)'!I90, "") | H14: =IF('Data (Master Table)'!$B90 = $K$1, 'Data (Master Table)'!J90, "") | ... J14: =IF('Data (Master Table)'!$B90 = $K$1, 'Data (Master Table)'!L90, "")

Sheet Data (Master Table)
A2: MASTER KEY | B2: Focus Area | C2: IS VALID | D2: SMART Outcome | E2: Benefit | F2: Starting Point / Baseline | G2: Department | H2: Reported to OPEX | I2: Responsible Person | J2: Risk Level | K2: Risk if Not Achieved | L2: Target Date | M2: Specific Desired Outcome | N2: Milestone Count | O2: Milestone/s | P2: Milestone/s Date | Q2: Actions | R2: Status | S2: Reason for Delay | T2: Complete % | U2: Notes | W2: FOCUS AREA LIST | Y2: PROGRESS LIST | AA2: COMPLETION LIST | AC2: RISK | AE2: IS VALID
A3: FS1 | B3: Financial Stability | C3: YES | D3: Establish diversified, sustainable income streams | E3: Service provision, significant income stream to be invested in Waqf | F3: Donation-dependent operations; limited reserves; no diversified income operational yet. Soft launch of TFS complete | G3: Safa Holdings / Finance | H3: End of March End of June End of Sept | I3: Shaffiq | J3: Medium | K3: High | L3: 46081 | M3: =IF('Financial Stability'!K3<>"",'Financial Stability'!K3,"") -> Deliver a live Funeral Service: Tahreem Funeral Service (operational & marketed) | N3: =IF('Financial Stability'!L3<>"",'Financial Stability'!L3,"") -> 3 | O3: =IF('Financial Stability'!M3<>"",'Financial Stability'!M3,"") -> 1. Cement policies & procedures 2. Hard Launch 3. Full service provision + £ | P3: =IF('Financial Stability'!N3<>"",'Financial Stability'!N3,"") -> 1. Jan - March 2. March 3. Mar - Sept | Q3: =IF('Financial Stability'!O3<>"",'Financial Stability'!O3,"") -> Continuous service improvement, additional fridge set up. Imam and Funeral Director to run roadshow prior to hard launch. Thorough marketing and relationship building- cemeteries, hospitals etc. Add our website link to other masajid and Eternal Gardens website | R3: =IF('Financial Stability'!P3<>"",'Financial Stability'!P3,"") -> Complete | S3: =IF('Financial Stability'!Q3<>"",'Financial Stability'!Q3,"") | T3: =IF('Financial Stability'!R3<>"",'Financial Stability'!R3,"") -> 1 | U3: =IF('Financial Stability'!S3<>"",'Financial Stability'!S3,"") -> The launch included delivering 21 full funerals, tightening policies and procedures, adding fridges, creating leaflets, livening the website, sending emails and WhatsApp messages, building relationships with Shirley, Penge, Purley, MCWAS, Tunbridge Wells and Maidstone (including use of facilities at Maidstone and TW). Send messages to our community, making a popup for the AEC website, setting up Tahreem@group email, adding our details to the Eternal Gardens website, announcing at jumu'ah. Before hard laucnh we have made a net profit of £20k | W3: Financial Stability | Y3: Not Started | AA3: 0 | AC3: High | AE3: YES
A4: FS2 | B4: Financial Stability | C4: YES | D4: Establish diversified, sustainable income streams | E4: Service provision, recurring advertising revenue + partnerships | F4: Donation-dependent operations; limited reserves; no diversified income operational yet. Idea and website ready for Business Directory | G4: Safa Holdings / Finance | H4: End of March End of June End of Sept | I4: Raja | J4: Medium | K4: Medium | L4: 46112 | M4: =IF('Financial Stability'!K4<>"",'Financial Stability'!K4,"") -> Launch Green Pages Business Directory (100+ listings.) Launch through MosqueApp | N4: =IF('Financial Stability'!L4<>"",'Financial Stability'!L4,"") -> 1 | O4: =IF('Financial Stability'!M4<>"",'Financial Stability'!M4,"") -> Created website offering, Raja to launch and do intital pre registration checks | P4: =IF('Financial Stability'!N4<>"",'Financial Stability'!N4,"") -> 46142 | Q4: =IF('Financial Stability'!O4<>"",'Financial Stability'!O4,"") -> Intro offer; outreach to local businesses; simple sign-up | R4: =IF('Financial Stability'!P4<>"",'Financial Stability'!P4,"") -> In Progress | S4: =IF('Financial Stability'!Q4<>"",'Financial Stability'!Q4,"") | T4: =IF('Financial Stability'!R4<>"",'Financial Stability'!R4,"") -> 0.9 | U4: =IF('Financial Stability'!S4<>"",'Financial Stability'!S4,"") -> Raja is on this iA | W4: Youth Succession Planning | Y4: In Progress | AA4: 0.1 | AC4: Medium | AE4: NO
A5: FS3 | B5: Financial Stability | C5: NO | D5: Grow current Waqf capital by £60,000 by Sept 2026 | E5: Perpetual income for AEC | F5: Donation-dependent operations; limited reserves; no diversified income operational yet. Curently contains £75k | G5: Finance | H5: End of March End of June End of Sept | I5: Raja / Kamraan | J5: Low | K5: High | L5: 46203 | M5: =IF('Financial Stability'!K5<>"",'Financial Stability'!K5,"") -> Raise £60k additional funds for waqf investment | O5: =IF('Financial Stability'!M5<>"",'Financial Stability'!M5,"") -> Ramadhan Waqf fundraising round 2 | P5: =IF('Financial Stability'!N5<>"",'Financial Stability'!N5,"") -> Last 10 days of Ramadhan | Q5: =IF('Financial Stability'!O5<>"",'Financial Stability'!O5,"") -> Friday talks, create deck for last 10 days of Ramadhan | R5: =IF('Financial Stability'!P5<>"",'Financial Stability'!P5,"") -> In Progress | S5: =IF('Financial Stability'!Q5<>"",'Financial Stability'!Q5,"") -> The amount we wanted to raise in the last 10 days of Ramadhan was not realised | T5: =IF('Financial Stability'!R5<>"",'Financial Stability'!R5,"") | U5: =IF('Financial Stability'!S5<>"",'Financial Stability'!S5,"") -> Will look to HNW network to achieve this | W5: Wider Community Engagement | Y5: Complete | AA5: 0.2 | AC5: Low
A6: FS4 | B6: Financial Stability | C6: YES | D6: Grow Waqf capital to £200,000 by Sept 2026 | E6: Step-change in waqf investment amount | F6: Donation-dependent operations; limited reserves; no diversified income operational yet. Curently contains £75k (+£60k Ramadhan iA) | G6: Exec | H6: End of March End of June End of Sept | I6: Shaffiq | J6: Medium | K6: High | L6: 46295 | M6: =IF('Financial Stability'!K6<>"",'Financial Stability'!K6,"") -> Increase waqf investment by further £65k | N6: =IF('Financial Stability'!L6<>"",'Financial Stability'!L6,"") -> 1 | O6: =IF('Financial Stability'!M6<>"",'Financial Stability'!M6,"") -> HNW and individual investor approach pack + roadshows | P6: =IF('Financial Stability'!N6<>"",'Financial Stability'!N6,"") -> 46266 | Q6: =IF('Financial Stability'!O6<>"",'Financial Stability'!O6,"") -> Curated deck; Brunei / Malaysian network, donor lunches; targeted HNW outreach | R6: =IF('Financial Stability'!P6<>"",'Financial Stability'!P6,"") -> In Progress | S6: =IF('Financial Stability'!Q6<>"",'Financial Stability'!Q6,"") | T6: =IF('Financial Stability'!R6<>"",'Financial Stability'!R6,"") -> 0.7 | U6: =IF('Financial Stability'!S6<>"",'Financial Stability'!S6,"") | W6: Building Teams & Leadership | Y6: Delayed | AA6: 0.3
A7: FS5 | B7: Financial Stability | C7: YES | D7: Achieve net-positive operating balance by Sept 2026 | E7: Operational transparency + sustainability | F7: Donation-dependent operations; limited reserves; no diversified income operational yet | G7: Finance | H7: End of March End of June End of Sept | I7: Behzat / Raja / Kamraan | J7: Low | K7: Medium | L7: 46295 | M7: =IF('Financial Stability'!K7<>"",'Financial Stability'!K7,"") -> Monthly finance dashboard & cost controls | N7: =IF('Financial Stability'!L7<>"",'Financial Stability'!L7,"") -> 1 | O7: =IF('Financial Stability'!M7<>"",'Financial Stability'!M7,"") -> Ramadhan BAU fundraising Dashboard creation | P7: =IF('Financial Stability'!N7<>"",'Financial Stability'!N7,"") -> 46266 | Q7: =IF('Financial Stability'!O7<>"",'Financial Stability'!O7,"") -> Budget discipline; procurement policy | R7: =IF('Financial Stability'!P7<>"",'Financial Stability'!P7,"") -> In Progress | S7: =IF('Financial Stability'!Q7<>"",'Financial Stability'!Q7,"") | T7: =IF('Financial Stability'!R7<>"",'Financial Stability'!R7,"") -> 0 | U7: =IF('Financial Stability'!S7<>"",'Financial Stability'!S7,"") | W7: Community Activities | AA7: 0.4
A8: FS6 | M8: =IF('Financial Stability'!K8<>"",'Financial Stability'!K8,"") | N8: =IF('Financial Stability'!L8<>"",'Financial Stability'!L8,"") | O8: =IF('Financial Stability'!M8<>"",'Financial Stability'!M8,"") | P8: =IF('Financial Stability'!N8<>"",'Financial Stability'!N8,"") | Q8: =IF('Financial Stability'!O8<>"",'Financial Stability'!O8,"") | R8: =IF('Financial Stability'!P8<>"",'Financial Stability'!P8,"") | S8: =IF('Financial Stability'!Q8<>"",'Financial Stability'!Q8,"") | T8: =IF('Financial Stability'!R8<>"",'Financial Stability'!R8,"") | U8: =IF('Financial Stability'!S8<>"",'Financial Stability'!S8,"") | W8: Spiritual Focus | AA8: 0.5
A9: FS7 | M9: =IF('Financial Stability'!K9<>"",'Financial Stability'!K9,"") | N9: =IF('Financial Stability'!L9<>"",'Financial Stability'!L9,"") | O9: =IF('Financial Stability'!M9<>"",'Financial Stability'!M9,"") | P9: =IF('Financial Stability'!N9<>"",'Financial Stability'!N9,"") | Q9: =IF('Financial Stability'!O9<>"",'Financial Stability'!O9,"") | R9: =IF('Financial Stability'!P9<>"",'Financial Stability'!P9,"") | S9: =IF('Financial Stability'!Q9<>"",'Financial Stability'!Q9,"") | T9: =IF('Financial Stability'!R9<>"",'Financial Stability'!R9,"") | U9: =IF('Financial Stability'!S9<>"",'Financial Stability'!S9,"") | AA9: 0.6
A10: FS8 | M10: =IF('Financial Stability'!K10<>"",'Financial Stability'!K10,"") | N10: =IF('Financial Stability'!L10<>"",'Financial Stability'!L10,"") | O10: =IF('Financial Stability'!M10<>"",'Financial Stability'!M10,"") | P10: =IF('Financial Stability'!N10<>"",'Financial Stability'!N10,"") | Q10: =IF('Financial Stability'!O10<>"",'Financial Stability'!O10,"") | R10: =IF('Financial Stability'!P10<>"",'Financial Stability'!P10,"") | S10: =IF('Financial Stability'!Q10<>"",'Financial Stability'!Q10,"") | T10: =IF('Financial Stability'!R10<>"",'Financial Stability'!R10,"") | U10: =IF('Financial Stability'!S10<>"",'Financial Stability'!S10,"") | AA10: 0.7
A11: FS9 | M11: =IF('Financial Stability'!K11<>"",'Financial Stability'!K11,"") | N11: =IF('Financial Stability'!L11<>"",'Financial Stability'!L11,"") | O11: =IF('Financial Stability'!M11<>"",'Financial Stability'!M11,"") | P11: =IF('Financial Stability'!N11<>"",'Financial Stability'!N11,"") | Q11: =IF('Financial Stability'!O11<>"",'Financial Stability'!O11,"") | R11: =IF('Financial Stability'!P11<>"",'Financial Stability'!P11,"") | S11: =IF('Financial Stability'!Q11<>"",'Financial Stability'!Q11,"") | T11: =IF('Financial Stability'!R11<>"",'Financial Stability'!R11,"") | U11: =IF('Financial Stability'!S11<>"",'Financial Stability'!S11,"") | AA11: 0.8
A12: FS10 | M12: =IF('Financial Stability'!K12<>"",'Financial Stability'!K12,"") | N12: =IF('Financial Stability'!L12<>"",'Financial Stability'!L12,"") | O12: =IF('Financial Stability'!M12<>"",'Financial Stability'!M12,"") | P12: =IF('Financial Stability'!N12<>"",'Financial Stability'!N12,"") | Q12: =IF('Financial Stability'!O12<>"",'Financial Stability'!O12,"") | R12: =IF('Financial Stability'!P12<>"",'Financial Stability'!P12,"") | S12: =IF('Financial Stability'!Q12<>"",'Financial Stability'!Q12,"") | T12: =IF('Financial Stability'!R12<>"",'Financial Stability'!R12,"") | U12: =IF('Financial Stability'!S12<>"",'Financial Stability'!S12,"") | AA12: 0.9
A13: FS11 | M13: =IF('Financial Stability'!K13<>"",'Financial Stability'!K13,"") | N13: =IF('Financial Stability'!L13<>"",'Financial Stability'!L13,"") | O13: =IF('Financial Stability'!M13<>"",'Financial Stability'!M13,"") | P13: =IF('Financial Stability'!N13<>"",'Financial Stability'!N13,"") | Q13: =IF('Financial Stability'!O13<>"",'Financial Stability'!O13,"") | R13: =IF('Financial Stability'!P13<>"",'Financial Stability'!P13,"") | S13: =IF('Financial Stability'!Q13<>"",'Financial Stability'!Q13,"") | T13: =IF('Financial Stability'!R13<>"",'Financial Stability'!R13,"") | U13: =IF('Financial Stability'!S13<>"",'Financial Stability'!S13,"") | AA13: 1
A14: FS12 | M14: =IF('Financial Stability'!K14<>"",'Financial Stability'!K14,"") | N14: =IF('Financial Stability'!L14<>"",'Financial Stability'!L14,"") | O14: =IF('Financial Stability'!M14<>"",'Financial Stability'!M14,"") | P14: =IF('Financial Stability'!N14<>"",'Financial Stability'!N14,"") | Q14: =IF('Financial Stability'!O14<>"",'Financial Stability'!O14,"") | R14: =IF('Financial Stability'!P14<>"",'Financial Stability'!P14,"") | S14: =IF('Financial Stability'!Q14<>"",'Financial Stability'!Q14,"") | T14: =IF('Financial Stability'!R14<>"",'Financial Stability'!R14,"") | U14: =IF('Financial Stability'!S14<>"",'Financial Stability'!S14,"")
A15: FS13 | M15: =IF('Financial Stability'!K15<>"",'Financial Stability'!K15,"") | N15: =IF('Financial Stability'!L15<>"",'Financial Stability'!L15,"") | O15: =IF('Financial Stability'!M15<>"",'Financial Stability'!M15,"") | P15: =IF('Financial Stability'!N15<>"",'Financial Stability'!N15,"") | Q15: =IF('Financial Stability'!O15<>"",'Financial Stability'!O15,"") | R15: =IF('Financial Stability'!P15<>"",'Financial Stability'!P15,"") | S15: =IF('Financial Stability'!Q15<>"",'Financial Stability'!Q15,"") | T15: =IF('Financial Stability'!R15<>"",'Financial Stability'!R15,"") | U15: =IF('Financial Stability'!S15<>"",'Financial Stability'!S15,"")
A16: FS14 | M16: =IF('Financial Stability'!K16<>"",'Financial Stability'!K16,"") | N16: =IF('Financial Stability'!L16<>"",'Financial Stability'!L16,"") | O16: =IF('Financial Stability'!M16<>"",'Financial Stability'!M16,"") | P16: =IF('Financial Stability'!N16<>"",'Financial Stability'!N16,"") | Q16: =IF('Financial Stability'!O16<>"",'Financial Stability'!O16,"") | R16: =IF('Financial Stability'!P16<>"",'Financial Stability'!P16,"") | S16: =IF('Financial Stability'!Q16<>"",'Financial Stability'!Q16,"") | T16: =IF('Financial Stability'!R16<>"",'Financial Stability'!R16,"") | U16: =IF('Financial Stability'!S16<>"",'Financial Stability'!S16,"")
A17: FS15 | M17: =IF('Financial Stability'!K17<>"",'Financial Stability'!K17,"") | N17: =IF('Financial Stability'!L17<>"",'Financial Stability'!L17,"") | O17: =IF('Financial Stability'!M17<>"",'Financial Stability'!M17,"") | P17: =IF('Financial Stability'!N17<>"",'Financial Stability'!N17,"") | Q17: =IF('Financial Stability'!O17<>"",'Financial Stability'!O17,"") | R17: =IF('Financial Stability'!P17<>"",'Financial Stability'!P17,"") | S17: =IF('Financial Stability'!Q17<>"",'Financial Stability'!Q17,"") | T17: =IF('Financial Stability'!R17<>"",'Financial Stability'!R17,"") | U17: =IF('Financial Stability'!S17<>"",'Financial Stability'!S17,"")
A18: YS1 | B18: Youth Succession Planning | C18: YES | D18: Develop youth leadership | E18: Pipeline of young leaders, succession planning | F18: No formal youth leadership structure; involvement is ad‑hoc and reactive | G18: Youth | H18: End of March End of June End of Sept | I18: Afsor | J18: Medium | K18: High | L18: 46068 | M18: =IF('Youth Succession Planning'!K3<>"",'Youth Succession Planning'!K3,"") -> Establish Youth Council (10 members) + Shadow Trustees + Key staff positions proteges allocated | N18: =IF('Youth Succession Planning'!L3<>"",'Youth Succession Planning'!L3,"") -> 1 | O18: =IF('Youth Succession Planning'!M3<>"",'Youth Succession Planning'!M3,"") -> Clear roles; mentor pairing; monthly meetings, Liaise with Madrassa, Scouts, Boxing and Taekwondo functions | P18: =IF('Youth Succession Planning'!N3<>"",'Youth Succession Planning'!N3,"") -> Target end Ramadan for first results | Q18: =IF('Youth Succession Planning'!O3<>"",'Youth Succession Planning'!O3,"") -> Ramadan: Volunteer Request, Omar Youth talks > key to identify youth. Youth Experience event plan for post Ramadan. | R18: =IF('Youth Succession Planning'!P3<>"",'Youth Succession Planning'!P3,"") -> In Progress | S18: =IF('Youth Succession Planning'!Q3<>"",'Youth Succession Planning'!Q3,"") | T18: =IF('Youth Succession Planning'!R3<>"",'Youth Succession Planning'!R3,"") -> 0.8 | U18: =IF('Youth Succession Planning'!S3<>"",'Youth Succession Planning'!S3,"") -> Results Ramadan> Youth activiites - building responsibility for the youth across the mosque. Demonstrated across youth events, running the coffee cart (i.e not just running, but also increasing product range to generate more "revenue" for the mosque), youth volunteers. How does this line with pipelne of young leaders: We have identified young leaders who we would recommend as part of a youth leadership strucutre that can support our growth. So based on we have identnfied caditates and now its about setting the strucutre, we have completed 40%, next 20% is setting structure, next 20% is executing it, and final 20% is ensuring its operating as part of the wider management teams. Q2: setting up youth board in progress.
A19: YS2 | B19: Youth Succession Planning | C19: YES | D19: Increase youth volunteering team by 40% | E19: Higher engagement & continuity | F19: Current team number: X | G19: Youth | H19: End of March End of June End of Sept | I19: Afsor | J19: Low | K19: Medium | L19: 46203 | M19: =IF('Youth Succession Planning'!K4<>"",'Youth Succession Planning'!K4,"") -> Quarterly youth volunteer drives | N19: =IF('Youth Succession Planning'!L4<>"",'Youth Succession Planning'!L4,"") -> 1 | O19: =IF('Youth Succession Planning'!M4<>"",'Youth Succession Planning'!M4,"") -> School/college outreach; buddy system | P19: =IF('Youth Succession Planning'!N4<>"",'Youth Succession Planning'!N4,"") -> Target end Ramadan for first results | Q19: =IF('Youth Succession Planning'!O4<>"",'Youth Succession Planning'!O4,"") -> Ramadan - youth voltuneering kicked off. | R19: =IF('Youth Succession Planning'!P4<>"",'Youth Succession Planning'!P4,"") -> In Progress | S19: =IF('Youth Succession Planning'!Q4<>"",'Youth Succession Planning'!Q4,"") | T19: =IF('Youth Succession Planning'!R4<>"",'Youth Succession Planning'!R4,"") -> 0.6 | U19: =IF('Youth Succession Planning'!S4<>"",'Youth Succession Planning'!S4,"") -> Q1:Results Ramadan: Youth volunteering from our advertising was not as successful but we had youth volunteering more by supporting the young adults i.e. Davids kids were helping coffee stand. We just need a bit more forward planning around youth volunteer requirements leading up to events, lead with young adults .. this will yield better results in future. Q2: We are building a core set of youth who are very engaged. Summer will be an important time to build events which bring our youth together.
A20: YS3 | B20: Youth Succession Planning | C20: YES | D20: Targeted talks to attract youth | E20: Higher engagement & building youth connection to masjid | F20: Ad-hoc talks currently | G20: Youth | H20: End of March End of June End of Sept | I20: Afsor | J20: Medium | K20: Medium | L20: 46112 | M20: =IF('Youth Succession Planning'!K5<>"",'Youth Succession Planning'!K5,"") -> Plan and deliver targeted talks for all youth demographics | N20: =IF('Youth Succession Planning'!L5<>"",'Youth Succession Planning'!L5,"") -> 6 | O20: =IF('Youth Succession Planning'!M5<>"",'Youth Succession Planning'!M5,"") -> 1 every 2 months | P20: =IF('Youth Succession Planning'!N5<>"",'Youth Succession Planning'!N5,"") -> Target end Ramadan for first results | Q20: =IF('Youth Succession Planning'!O5<>"",'Youth Succession Planning'!O5,"") -> Working with Omar to create a better set of talks for youth. Focus is not purley on topic, but more on connecting them to mentors + people they can respect/look up too (people who are not to old). First test of this will be in Ramadan. | R20: =IF('Youth Succession Planning'!P5<>"",'Youth Succession Planning'!P5,"") -> In Progress | S20: =IF('Youth Succession Planning'!Q5<>"",'Youth Succession Planning'!Q5,"") | T20: =IF('Youth Succession Planning'!R5<>"",'Youth Succession Planning'!R5,"") -> 0.6 | U20: =IF('Youth Succession Planning'!S5<>"",'Youth Succession Planning'!S5,"") -> Ramadan Resulst > Continue youth. Omar and Eni doing a great job. Think we need a sisters lead one switch at some point. 60% completion rate once we get consisten cy, have new people joining, 80% once we see engagement from youth outsend youth talks and final 100% swhen we have sister led sessions as well
A21: YS4 | B21: Youth Succession Planning | C21: YES | D21: Bi-monthly events to attract youth | E21: Higher engagement & building youth connection to masjid | F21: Ad-hoc events running currently | G21: Youth | H21: End of March End of June End of Sept | I21: Afsor | J21: High | K21: High | L21: 46112 | M21: =IF('Youth Succession Planning'!K6<>"",'Youth Succession Planning'!K6,"") -> Plan and deliver fortnightly events, social, Islamic, food etc for specific youth demographics | N21: =IF('Youth Succession Planning'!L6<>"",'Youth Succession Planning'!L6,"") -> 24 | O21: =IF('Youth Succession Planning'!M6<>"",'Youth Succession Planning'!M6,"") -> 2 every month | P21: =IF('Youth Succession Planning'!N6<>"",'Youth Succession Planning'!N6,"") -> on-going | Q21: =IF('Youth Succession Planning'!O6<>"",'Youth Succession Planning'!O6,"") -> While this is aspiration. For youth, possible. We will continue with consistency on boys and girls circles. For the YA, we want to build more on providing experiences e.g. hike at seven sisters etc. Build stronger bonds + friendships. This helps them feel more connected to the mosque and the community. | R21: =IF('Youth Succession Planning'!P6<>"",'Youth Succession Planning'!P6,"") -> In Progress | S21: =IF('Youth Succession Planning'!Q6<>"",'Youth Succession Planning'!Q6,"") | T21: =IF('Youth Succession Planning'!R6<>"",'Youth Succession Planning'!R6,"") -> 0.5 | U21: =IF('Youth Succession Planning'!S6<>"",'Youth Succession Planning'!S6,"") -> Q1: Ideas being progress: Experienced based events. Volunteering. DoE - our first volunteer. Building plans. Q2: Summer will be key. Where we want to get more volunteers and more experiences for youth.
A22: YS5 | B22: Youth Succession Planning | C22: YES | D22: Leadership development | E22: Safer, more competent teams | F22: No formal youth leadership structure; involvement is ad‑hoc and reactive | G22: OPEX | H22: End of March End of June End of Sept | I22: Amer | J22: Low | K22: Medium | L22: 46112 | M22: =IF('Youth Succession Planning'!K7<>"",'Youth Succession Planning'!K7,"") -> Training calendar (safeguarding, first aid, comms) | N22: =IF('Youth Succession Planning'!L7<>"",'Youth Succession Planning'!L7,"") -> 1 | O22: =IF('Youth Succession Planning'!M7<>"",'Youth Succession Planning'!M7,"") -> Book trainers; certificates; track completion | P22: =IF('Youth Succession Planning'!N7<>"",'Youth Succession Planning'!N7,"") -> 18.01.26 | Q22: =IF('Youth Succession Planning'!O7<>"",'Youth Succession Planning'!O7,"") -> Begin leadership development programme with Yusra training | R22: =IF('Youth Succession Planning'!P7<>"",'Youth Succession Planning'!P7,"") -> In Progress | S22: =IF('Youth Succession Planning'!Q7<>"",'Youth Succession Planning'!Q7,"") -> Completion of pre-training 1-2-1 sessions with OPEX | T22: =IF('Youth Succession Planning'!R7<>"",'Youth Succession Planning'!R7,"") -> 0.7 | U22: =IF('Youth Succession Planning'!S7<>"",'Youth Succession Planning'!S7,"") -> Youth Lead Afsor Miah is captured within this training programme. Following MOSCARS awards ceremony several youth volunteers were identified for consideration for a youth council or shadow trustee/directors board. Shaffiq has put document tyogether detailing proposed structure. Some of the youth m,embers have also attended Yusar training sessions.
A23: YS6 | B23: Youth Succession Planning | C23: YES | D23: Leadership development | E23: Pipeline of young leaders, succession planning | F23: Scouts provision low | G23: Scouts | H23: End of March End of June End of Sept | I23: Khaleeq | J23: Medium | K23: Medium | L23: 46112 | M23: =IF('Youth Succession Planning'!K8<>"",'Youth Succession Planning'!K8,"") -> Increase number of Scouts places- key issue; staffing | N23: =IF('Youth Succession Planning'!L8<>"",'Youth Succession Planning'!L8,"") -> 1 | O23: =IF('Youth Succession Planning'!M8<>"",'Youth Succession Planning'!M8,"") -> Increase staff numbers | P23: =IF('Youth Succession Planning'!N8<>"",'Youth Succession Planning'!N8,"") -> 31.01.26 | Q23: =IF('Youth Succession Planning'!O8<>"",'Youth Succession Planning'!O8,"") -> Advertising targeted for Q1. Story around impact and outcomes. We will keep on top of this. We will review impact. | R23: =IF('Youth Succession Planning'!P8<>"",'Youth Succession Planning'!P8,"") -> Not Started | S23: =IF('Youth Succession Planning'!Q8<>"",'Youth Succession Planning'!Q8,"") | T23: =IF('Youth Succession Planning'!R8<>"",'Youth Succession Planning'!R8,"") -> 0 | U23: =IF('Youth Succession Planning'!S8<>"",'Youth Succession Planning'!S8,"") -> Risk: Scout leader is leaving. Need to first onboard a new lead Lack of volunteers are we progressing this?
A24: YS7 | M24: =IF('Youth Succession Planning'!K9<>"",'Youth Succession Planning'!K9,"") | N24: =IF('Youth Succession Planning'!L9<>"",'Youth Succession Planning'!L9,"") | O24: =IF('Youth Succession Planning'!M9<>"",'Youth Succession Planning'!M9,"") | P24: =IF('Youth Succession Planning'!N9<>"",'Youth Succession Planning'!N9,"") | Q24: =IF('Youth Succession Planning'!O9<>"",'Youth Succession Planning'!O9,"") | R24: =IF('Youth Succession Planning'!P9<>"",'Youth Succession Planning'!P9,"") | S24: =IF('Youth Succession Planning'!Q9<>"",'Youth Succession Planning'!Q9,"") | T24: =IF('Youth Succession Planning'!R9<>"",'Youth Succession Planning'!R9,"") | U24: =IF('Youth Succession Planning'!S9<>"",'Youth Succession Planning'!S9,"")
A25: YS8 | M25: =IF('Youth Succession Planning'!K10<>"",'Youth Succession Planning'!K10,"") | N25: =IF('Youth Succession Planning'!L10<>"",'Youth Succession Planning'!L10,"") | O25: =IF('Youth Succession Planning'!M10<>"",'Youth Succession Planning'!M10,"") | P25: =IF('Youth Succession Planning'!N10<>"",'Youth Succession Planning'!N10,"") | Q25: =IF('Youth Succession Planning'!O10<>"",'Youth Succession Planning'!O10,"") | R25: =IF('Youth Succession Planning'!P10<>"",'Youth Succession Planning'!P10,"") | S25: =IF('Youth Succession Planning'!Q10<>"",'Youth Succession Planning'!Q10,"") | T25: =IF('Youth Succession Planning'!R10<>"",'Youth Succession Planning'!R10,"") | U25: =IF('Youth Succession Planning'!S10<>"",'Youth Succession Planning'!S10,"")
A26: YS9 | M26: =IF('Youth Succession Planning'!K11<>"",'Youth Succession Planning'!K11,"") | N26: =IF('Youth Succession Planning'!L11<>"",'Youth Succession Planning'!L11,"") | O26: =IF('Youth Succession Planning'!M11<>"",'Youth Succession Planning'!M11,"") | P26: =IF('Youth Succession Planning'!N11<>"",'Youth Succession Planning'!N11,"") | Q26: =IF('Youth Succession Planning'!O11<>"",'Youth Succession Planning'!O11,"") | R26: =IF('Youth Succession Planning'!P11<>"",'Youth Succession Planning'!P11,"") | S26: =IF('Youth Succession Planning'!Q11<>"",'Youth Succession Planning'!Q11,"") | T26: =IF('Youth Succession Planning'!R11<>"",'Youth Succession Planning'!R11,"") | U26: =IF('Youth Succession Planning'!S11<>"",'Youth Succession Planning'!S11,"")
A27: YS10 | M27: =IF('Youth Succession Planning'!K12<>"",'Youth Succession Planning'!K12,"") | N27: =IF('Youth Succession Planning'!L12<>"",'Youth Succession Planning'!L12,"") | O27: =IF('Youth Succession Planning'!M12<>"",'Youth Succession Planning'!M12,"") | P27: =IF('Youth Succession Planning'!N12<>"",'Youth Succession Planning'!N12,"") | Q27: =IF('Youth Succession Planning'!O12<>"",'Youth Succession Planning'!O12,"") | R27: =IF('Youth Succession Planning'!P12<>"",'Youth Succession Planning'!P12,"") | S27: =IF('Youth Succession Planning'!Q12<>"",'Youth Succession Planning'!Q12,"") | T27: =IF('Youth Succession Planning'!R12<>"",'Youth Succession Planning'!R12,"") | U27: =IF('Youth Succession Planning'!S12<>"",'Youth Succession Planning'!S12,"")
A28: YS11 | M28: =IF('Youth Succession Planning'!K13<>"",'Youth Succession Planning'!K13,"") | N28: =IF('Youth Succession Planning'!L13<>"",'Youth Succession Planning'!L13,"") | O28: =IF('Youth Succession Planning'!M13<>"",'Youth Succession Planning'!M13,"") | P28: =IF('Youth Succession Planning'!N13<>"",'Youth Succession Planning'!N13,"") | Q28: =IF('Youth Succession Planning'!O13<>"",'Youth Succession Planning'!O13,"") | R28: =IF('Youth Succession Planning'!P13<>"",'Youth Succession Planning'!P13,"") | S28: =IF('Youth Succession Planning'!Q13<>"",'Youth Succession Planning'!Q13,"") | T28: =IF('Youth Succession Planning'!R13<>"",'Youth Succession Planning'!R13,"") | U28: =IF('Youth Succession Planning'!S13<>"",'Youth Succession Planning'!S13,"")
A29: YS12 | M29: =IF('Youth Succession Planning'!K14<>"",'Youth Succession Planning'!K14,"") | N29: =IF('Youth Succession Planning'!L14<>"",'Youth Succession Planning'!L14,"") | O29: =IF('Youth Succession Planning'!M14<>"",'Youth Succession Planning'!M14,"") | P29: =IF('Youth Succession Planning'!N14<>"",'Youth Succession Planning'!N14,"") | Q29: =IF('Youth Succession Planning'!O14<>"",'Youth Succession Planning'!O14,"") | R29: =IF('Youth Succession Planning'!P14<>"",'Youth Succession Planning'!P14,"") | S29: =IF('Youth Succession Planning'!Q14<>"",'Youth Succession Planning'!Q14,"") | T29: =IF('Youth Succession Planning'!R14<>"",'Youth Succession Planning'!R14,"") | U29: =IF('Youth Succession Planning'!S14<>"",'Youth Succession Planning'!S14,"")
A30: YS13 | M30: =IF('Youth Succession Planning'!K15<>"",'Youth Succession Planning'!K15,"") | N30: =IF('Youth Succession Planning'!L15<>"",'Youth Succession Planning'!L15,"") | O30: =IF('Youth Succession Planning'!M15<>"",'Youth Succession Planning'!M15,"") | P30: =IF('Youth Succession Planning'!N15<>"",'Youth Succession Planning'!N15,"") | Q30: =IF('Youth Succession Planning'!O15<>"",'Youth Succession Planning'!O15,"") | R30: =IF('Youth Succession Planning'!P15<>"",'Youth Succession Planning'!P15,"") | S30: =IF('Youth Succession Planning'!Q15<>"",'Youth Succession Planning'!Q15,"") | T30: =IF('Youth Succession Planning'!R15<>"",'Youth Succession Planning'!R15,"") | U30: =IF('Youth Succession Planning'!S15<>"",'Youth Succession Planning'!S15,"")
A31: YS14 | M31: =IF('Youth Succession Planning'!K16<>"",'Youth Succession Planning'!K16,"") | N31: =IF('Youth Succession Planning'!L16<>"",'Youth Succession Planning'!L16,"") | O31: =IF('Youth Succession Planning'!M16<>"",'Youth Succession Planning'!M16,"") | P31: =IF('Youth Succession Planning'!N16<>"",'Youth Succession Planning'!N16,"") | Q31: =IF('Youth Succession Planning'!O16<>"",'Youth Succession Planning'!O16,"") | R31: =IF('Youth Succession Planning'!P16<>"",'Youth Succession Planning'!P16,"") | S31: =IF('Youth Succession Planning'!Q16<>"",'Youth Succession Planning'!Q16,"") | T31: =IF('Youth Succession Planning'!R16<>"",'Youth Succession Planning'!R16,"") | U31: =IF('Youth Succession Planning'!S16<>"",'Youth Succession Planning'!S16,"")
A32: YS15 | M32: =IF('Youth Succession Planning'!K17<>"",'Youth Succession Planning'!K17,"") | N32: =IF('Youth Succession Planning'!L17<>"",'Youth Succession Planning'!L17,"") | O32: =IF('Youth Succession Planning'!M17<>"",'Youth Succession Planning'!M17,"") | P32: =IF('Youth Succession Planning'!N17<>"",'Youth Succession Planning'!N17,"") | Q32: =IF('Youth Succession Planning'!O17<>"",'Youth Succession Planning'!O17,"") | R32: =IF('Youth Succession Planning'!P17<>"",'Youth Succession Planning'!P17,"") | S32: =IF('Youth Succession Planning'!Q17<>"",'Youth Succession Planning'!Q17,"") | T32: =IF('Youth Succession Planning'!R17<>"",'Youth Succession Planning'!R17,"") | U32: =IF('Youth Succession Planning'!S17<>"",'Youth Succession Planning'!S17,"")
A33: WC1 | B33: Wider Community Engagement | C33: YES | D33: Build partnerships | E33: Shared impact & credibility, improved societal integration | F33: 3–4 informal partnerships; sporadic open days; no structured annual calendar | G33: Community / Politics | H33: End of March End of June End of Sept | I33: Matiur | J33: Medium | K33: High | L33: 46173 | M33: =IF('Wider Community Engagement'!K3<>"",'Wider Community Engagement'!K3,"") -> Sign 5 MOUs with local orgs | N33: =IF('Wider Community Engagement'!L3<>"",'Wider Community Engagement'!L3,"") -> 3 | O33: =IF('Wider Community Engagement'!M3<>"",'Wider Community Engagement'!M3,"") -> 1. Target list (schools, council, charities); template MOU 2. Set up Bromley Citizens UK 3. Recruit more volunteers for Citizens UK | P33: =IF('Wider Community Engagement'!N3<>"",'Wider Community Engagement'!N3,"") -> 1. Apr 2. Sept 3. Feb | Q33: =IF('Wider Community Engagement'!O3<>"",'Wider Community Engagement'!O3,"") -> Further Citizen's UK meeting attended by other community members | R33: =IF('Wider Community Engagement'!P3<>"",'Wider Community Engagement'!P3,"") -> In Progress | S33: =IF('Wider Community Engagement'!Q3<>"",'Wider Community Engagement'!Q3,"") | T33: =IF('Wider Community Engagement'!R3<>"",'Wider Community Engagement'!R3,"") -> 0.4 | U33: =IF('Wider Community Engagement'!S4<>"",'Wider Community Engagement'!S4,"") -> Calendar up and running. Testing during Ramdan. Avais and Meryem to own, keep up to date. Need to make this calendar more avalaible to non muslim community. Coffee Cart super successful, we need to get someone to own this and also this need sto beome a more regular daily service. Q2: Progressing well. Eid event we invited wider community. I am keen to do an Art event, farmers market in August etc
A34: WC2 | B34: Wider Community Engagement | C34: YES | D34: Community events | E34: Improved public perception and relationships, increased local impact | F34: 3–4 informal partnerships; sporadic open days; no structured annual calendar | G34: Community / Politics | H34: End of March End of June End of Sept | I34: Avais | J34: Medium | K34: Medium | L34: 46295 | M34: =IF('Wider Community Engagement'!K4<>"",'Wider Community Engagement'!K4,"") -> Deliver 4 open community events | N34: =IF('Wider Community Engagement'!L4<>"",'Wider Community Engagement'!L4,"") -> 5 | O34: =IF('Wider Community Engagement'!M4<>"",'Wider Community Engagement'!M4,"") -> Plan calendar; steward training; inclusive themes. Include neighbourhood consultation (first build relationships, then ask what are your needs?)and Interfaith iftar | P34: =IF('Wider Community Engagement'!N4<>"",'Wider Community Engagement'!N4,"") -> Feb - Calendar May - Eid Jun - World Cup Sep - Dec - Christmas | Q34: =IF('Wider Community Engagement'!O4<>"",'Wider Community Engagement'!O4,"") -> Online community Calendar is ready for Ramadan! Build an informal way of engaging with the mosque space to make it more accessiable for non muslims. Event invitations to consider non-muslim community. Partnerships - tbc | R34: =IF('Wider Community Engagement'!P4<>"",'Wider Community Engagement'!P4,"") -> In Progress | S34: =IF('Wider Community Engagement'!Q4<>"",'Wider Community Engagement'!Q4,"") | T34: =IF('Wider Community Engagement'!R4<>"",'Wider Community Engagement'!R4,"") -> 0.5 | U34: =IF('Wider Community Engagement'!#REF!<>"",'Wider Community Engagement'!#REF!,"") -> #REF!
A35: WC3 | B35: Wider Community Engagement | C35: YES | D35: Transparency | E35: Evidence for funders & partners | F35: 3–4 informal partnerships; sporadic open days; no structured annual calendar | G35: Community / Politics | H35: End of March End of June End of Sept | I35: Avais | J35: Low | K35: Medium | L35: 46295 | M35: =IF('Wider Community Engagement'!K5<>"",'Wider Community Engagement'!K5,"") -> Publish annual Community Impact Report | N35: =IF('Wider Community Engagement'!L5<>"",'Wider Community Engagement'!L5,"") -> 3 | O35: =IF('Wider Community Engagement'!M5<>"",'Wider Community Engagement'!M5,"") -> Collect metrics; case studies; design & print | P35: =IF('Wider Community Engagement'!N5<>"",'Wider Community Engagement'!N5,"") -> On-going | Q35: =IF('Wider Community Engagement'!O5<>"",'Wider Community Engagement'!O5,"") -> Ensuring data capturing of events is requested before events. Looking to get more youth to take videos/photos during evets | R35: =IF('Wider Community Engagement'!P5<>"",'Wider Community Engagement'!P5,"") -> Complete | S35: =IF('Wider Community Engagement'!Q5<>"",'Wider Community Engagement'!Q5,"") | T35: =IF('Wider Community Engagement'!R5<>"",'Wider Community Engagement'!R5,"") -> 1 | U35: =IF('Wider Community Engagement'!S5<>"",'Wider Community Engagement'!S5,"") -> We are getting data for events every time which is good, succewss is shared throguh leads utd, and we are keeping each other updated. Good progress on this and its linked well to marketing
A36: WC4 | B36: Wider Community Engagement | C36: YES | D36: Non-Muslims understand Islam | E36: Spreading the Deen and benefitting local community. Islamic stereotypes broken | F36: Recruited da'ee group; completing training. Dawah stall equipment and clothing being sourced, branding complete. Awaiting stall permission from Bromley Council | G36: Religious Affairs | H36: End of March End of June End of Sept | I36: Ahmed | J36: Low | K36: Medium | L36: 46053 | M36: =IF('Wider Community Engagement'!K6<>"",'Wider Community Engagement'!K6,"") -> Live, active Da'wah project | N36: =IF('Wider Community Engagement'!L6<>"",'Wider Community Engagement'!L6,"") -> 3 | O36: =IF('Wider Community Engagement'!M6<>"",'Wider Community Engagement'!M6,"") -> 1. Complete purchases of equipment 2. Stall permission granted 3. Volunteer training complete | P36: =IF('Wider Community Engagement'!N6<>"",'Wider Community Engagement'!N6,"") -> 1. Jan end 2. Jan end 3. Jan end | Q36: =IF('Wider Community Engagement'!O6<>"",'Wider Community Engagement'!O6,"") | R36: =IF('Wider Community Engagement'!P6<>"",'Wider Community Engagement'!P6,"") -> In Progress | S36: =IF('Wider Community Engagement'!Q6<>"",'Wider Community Engagement'!Q6,"") | T36: =IF('Wider Community Engagement'!R6<>"",'Wider Community Engagement'!R6,"") -> 0.9 | U36: =IF('Wider Community Engagement'!S6<>"",'Wider Community Engagement'!S6,"")
A37: WC5 | B37: Wider Community Engagement | C37: YES | D37: Engage and connect with local schools and scouts groups | E37: Active daw'ah and increasing Islamic knowledge (including breaking stereotypes) of young local people through immersive experiences | F37: School and scouts visits service already active, through school/scout group contact | G37: Education | H37: End of March End of June End of Sept | I37: Sobia | J37: Low | K37: Medium | L37: 46173 | M37: =IF('Wider Community Engagement'!K7<>"",'Wider Community Engagement'!K7,"") -> Service to become proactive, reaching out to schools /scout groups | N37: =IF('Wider Community Engagement'!L7<>"",'Wider Community Engagement'!L7,"") -> 6 | O37: =IF('Wider Community Engagement'!M7<>"",'Wider Community Engagement'!M7,"") -> 1. Attract and retain further volunteers 2. Begin actively reaching out to schools/scout groups 3. Engage Bromley College 4. Invite them to our wider events 5. Get them to partake in our Ramadhan Challenge and iftars | P37: =IF('Wider Community Engagement'!N7<>"",'Wider Community Engagement'!N7,"") -> 1. Jan Mid 2. May End 3. Feb End 4. Feb Begin 5. Feb end | Q37: =IF('Wider Community Engagement'!O7<>"",'Wider Community Engagement'!O7,"") -> Successfully attracted and retained additional volunteers to support the mosque visits programme. | R37: =IF('Wider Community Engagement'!P7<>"",'Wider Community Engagement'!P7,"") -> In Progress | S37: =IF('Wider Community Engagement'!Q7<>"",'Wider Community Engagement'!Q7,"") | T37: =IF('Wider Community Engagement'!R7<>"",'Wider Community Engagement'!R7,"") -> 0.5 | U37: =IF('Wider Community Engagement'!S7<>"",'Wider Community Engagement'!S7,"")
A38: WC6 | B38: Wider Community Engagement | C38: YES | D38: Deepen relationships and benefit from connections to other faiths | E38: Learn from them, teach them about Islam, break stereotypes, aid geo/political dialogues/situations | F38: Already esablished long term Interfaith relationships | G38: Education | H38: End of March End of June End of Sept | I38: Sofi | J38: Medium | K38: High | L38: 46280 | M38: =IF('Wider Community Engagement'!K8<>"",'Wider Community Engagement'!K8,"") -> Participate in regular Interfaith meetings and continue to educate about Islam, lessons learned from our shared prophets and highlight the advantages of being a people of peace who pray, fast and are ready to help others | N38: =IF('Wider Community Engagement'!L8<>"",'Wider Community Engagement'!L8,"") -> 3 | O38: =IF('Wider Community Engagement'!M8<>"",'Wider Community Engagement'!M8,"") -> 1. Get more of our community involved 2. Strengthen relationships with focus on Justice 3. Benefit from learning about how other faiths function,e.g. financial set up of Christians, power dynamics from Jews. 4.Plan Islamophobia and anti-semitism workshops | P38: =IF('Wider Community Engagement'!N8<>"",'Wider Community Engagement'!N8,"") -> 1. Feb end 2. Apr end 3. Sep end | Q38: =IF('Wider Community Engagement'!O8<>"",'Wider Community Engagement'!O8,"") -> 1. Work in progress re drawing more of our community . Issues are due to advertising events late, this is partly due to the sensitive nature of the topics and have been hesitant to advertise. 2 | R38: =IF('Wider Community Engagement'!P8<>"",'Wider Community Engagement'!P8,"") -> In Progress | S38: =IF('Wider Community Engagement'!Q8<>"",'Wider Community Engagement'!Q8,"") | T38: =IF('Wider Community Engagement'!R8<>"",'Wider Community Engagement'!R8,"") -> 0.5 | U38: =IF('Wider Community Engagement'!S8<>"",'Wider Community Engagement'!S8,"")
A39: WC7 | B39: Wider Community Engagement | C39: YES | D39: Connect with, market, and advertise well with wider community | E39: Improved community cohesion | F39: Have an existing but out of date and non searchable database. A sharepoint version now exists in SharePoint | G39: Community / Politics | H39: End of March End of June End of Sept | I39: Matiur | J39: Medium | K39: Medium | L39: 46234 | M39: =IF('Wider Community Engagement'!K9<>"",'Wider Community Engagement'!K9,"") -> Build useful, searchable, regularly updated database of community contacts | N39: =IF('Wider Community Engagement'!L9<>"",'Wider Community Engagement'!L9,"") -> 1 | O39: =IF('Wider Community Engagement'!M9<>"",'Wider Community Engagement'!M9,"") | P39: =IF('Wider Community Engagement'!N9<>"",'Wider Community Engagement'!N9,"") | Q39: =IF('Wider Community Engagement'!O9<>"",'Wider Community Engagement'!O9,"") | R39: =IF('Wider Community Engagement'!P9<>"",'Wider Community Engagement'!P9,"") -> In Progress | S39: =IF('Wider Community Engagement'!Q9<>"",'Wider Community Engagement'!Q9,"") | T39: =IF('Wider Community Engagement'!R9<>"",'Wider Community Engagement'!R9,"") -> 0.1 | U39: =IF('Wider Community Engagement'!S9<>"",'Wider Community Engagement'!S9,"") -> To be reviewed after Eid. Interfaith iftar invitations was not well executed with many key stakeholders missed
A40: WC8 | M40: =IF('Wider Community Engagement'!K10<>"",'Wider Community Engagement'!K10,"") | N40: =IF('Wider Community Engagement'!L10<>"",'Wider Community Engagement'!L10,"") | O40: =IF('Wider Community Engagement'!M10<>"",'Wider Community Engagement'!M10,"") | P40: =IF('Wider Community Engagement'!N10<>"",'Wider Community Engagement'!N10,"") | Q40: =IF('Wider Community Engagement'!O10<>"",'Wider Community Engagement'!O10,"") -> Work in progress: | R40: =IF('Wider Community Engagement'!P10<>"",'Wider Community Engagement'!P10,"") | S40: =IF('Wider Community Engagement'!Q10<>"",'Wider Community Engagement'!Q10,"") | T40: =IF('Wider Community Engagement'!R10<>"",'Wider Community Engagement'!R10,"") | U40: =IF('Wider Community Engagement'!S10<>"",'Wider Community Engagement'!S10,"")
A41: WC9 | M41: =IF('Wider Community Engagement'!K11<>"",'Wider Community Engagement'!K11,"") | N41: =IF('Wider Community Engagement'!L11<>"",'Wider Community Engagement'!L11,"") | O41: =IF('Wider Community Engagement'!M11<>"",'Wider Community Engagement'!M11,"") | P41: =IF('Wider Community Engagement'!N11<>"",'Wider Community Engagement'!N11,"") | Q41: =IF('Wider Community Engagement'!O11<>"",'Wider Community Engagement'!O11,"") | R41: =IF('Wider Community Engagement'!P11<>"",'Wider Community Engagement'!P11,"") | S41: =IF('Wider Community Engagement'!Q11<>"",'Wider Community Engagement'!Q11,"") | T41: =IF('Wider Community Engagement'!R11<>"",'Wider Community Engagement'!R11,"") | U41: =IF('Wider Community Engagement'!S11<>"",'Wider Community Engagement'!S11,"")
A42: WC10 | M42: =IF('Wider Community Engagement'!K12<>"",'Wider Community Engagement'!K12,"") | N42: =IF('Wider Community Engagement'!L12<>"",'Wider Community Engagement'!L12,"") | O42: =IF('Wider Community Engagement'!M12<>"",'Wider Community Engagement'!M12,"") | P42: =IF('Wider Community Engagement'!N12<>"",'Wider Community Engagement'!N12,"") | Q42: =IF('Wider Community Engagement'!O12<>"",'Wider Community Engagement'!O12,"") | R42: =IF('Wider Community Engagement'!P12<>"",'Wider Community Engagement'!P12,"") | S42: =IF('Wider Community Engagement'!Q12<>"",'Wider Community Engagement'!Q12,"") | T42: =IF('Wider Community Engagement'!R12<>"",'Wider Community Engagement'!R12,"") | U42: =IF('Wider Community Engagement'!S12<>"",'Wider Community Engagement'!S12,"")
A43: WC11 | M43: =IF('Wider Community Engagement'!K13<>"",'Wider Community Engagement'!K13,"") | N43: =IF('Wider Community Engagement'!L13<>"",'Wider Community Engagement'!L13,"") | O43: =IF('Wider Community Engagement'!M13<>"",'Wider Community Engagement'!M13,"") | P43: =IF('Wider Community Engagement'!N13<>"",'Wider Community Engagement'!N13,"") | Q43: =IF('Wider Community Engagement'!O13<>"",'Wider Community Engagement'!O13,"") | R43: =IF('Wider Community Engagement'!P13<>"",'Wider Community Engagement'!P13,"") | S43: =IF('Wider Community Engagement'!Q13<>"",'Wider Community Engagement'!Q13,"") | T43: =IF('Wider Community Engagement'!R13<>"",'Wider Community Engagement'!R13,"") | U43: =IF('Wider Community Engagement'!S13<>"",'Wider Community Engagement'!S13,"")
A44: WC12 | M44: =IF('Wider Community Engagement'!K14<>"",'Wider Community Engagement'!K14,"") | N44: =IF('Wider Community Engagement'!L14<>"",'Wider Community Engagement'!L14,"") | O44: =IF('Wider Community Engagement'!M14<>"",'Wider Community Engagement'!M14,"") | P44: =IF('Wider Community Engagement'!N14<>"",'Wider Community Engagement'!N14,"") | Q44: =IF('Wider Community Engagement'!O14<>"",'Wider Community Engagement'!O14,"") | R44: =IF('Wider Community Engagement'!P14<>"",'Wider Community Engagement'!P14,"") | S44: =IF('Wider Community Engagement'!Q14<>"",'Wider Community Engagement'!Q14,"") | T44: =IF('Wider Community Engagement'!R14<>"",'Wider Community Engagement'!R14,"") | U44: =IF('Wider Community Engagement'!S14<>"",'Wider Community Engagement'!S14,"")
A45: WC13 | M45: =IF('Wider Community Engagement'!K15<>"",'Wider Community Engagement'!K15,"") | N45: =IF('Wider Community Engagement'!L15<>"",'Wider Community Engagement'!L15,"") | O45: =IF('Wider Community Engagement'!M15<>"",'Wider Community Engagement'!M15,"") | P45: =IF('Wider Community Engagement'!N15<>"",'Wider Community Engagement'!N15,"") | Q45: =IF('Wider Community Engagement'!O15<>"",'Wider Community Engagement'!O15,"") | R45: =IF('Wider Community Engagement'!P15<>"",'Wider Community Engagement'!P15,"") | S45: =IF('Wider Community Engagement'!Q15<>"",'Wider Community Engagement'!Q15,"") | T45: =IF('Wider Community Engagement'!R15<>"",'Wider Community Engagement'!R15,"") | U45: =IF('Wider Community Engagement'!S15<>"",'Wider Community Engagement'!S15,"")
A46: WC14 | M46: =IF('Wider Community Engagement'!K16<>"",'Wider Community Engagement'!K16,"") | N46: =IF('Wider Community Engagement'!L16<>"",'Wider Community Engagement'!L16,"") | O46: =IF('Wider Community Engagement'!M16<>"",'Wider Community Engagement'!M16,"") | P46: =IF('Wider Community Engagement'!N16<>"",'Wider Community Engagement'!N16,"") | Q46: =IF('Wider Community Engagement'!O16<>"",'Wider Community Engagement'!O16,"") | R46: =IF('Wider Community Engagement'!P16<>"",'Wider Community Engagement'!P16,"") | S46: =IF('Wider Community Engagement'!Q16<>"",'Wider Community Engagement'!Q16,"") | T46: =IF('Wider Community Engagement'!R16<>"",'Wider Community Engagement'!R16,"") | U46: =IF('Wider Community Engagement'!S16<>"",'Wider Community Engagement'!S16,"")
A47: WC15 | M47: =IF('Wider Community Engagement'!K17<>"",'Wider Community Engagement'!K17,"") | N47: =IF('Wider Community Engagement'!L17<>"",'Wider Community Engagement'!L17,"") | O47: =IF('Wider Community Engagement'!M17<>"",'Wider Community Engagement'!M17,"") | P47: =IF('Wider Community Engagement'!N17<>"",'Wider Community Engagement'!N17,"") | Q47: =IF('Wider Community Engagement'!O17<>"",'Wider Community Engagement'!O17,"") | R47: =IF('Wider Community Engagement'!P17<>"",'Wider Community Engagement'!P17,"") | S47: =IF('Wider Community Engagement'!Q17<>"",'Wider Community Engagement'!Q17,"") | T47: =IF('Wider Community Engagement'!R17<>"",'Wider Community Engagement'!R17,"") | U47: =IF('Wider Community Engagement'!S17<>"",'Wider Community Engagement'!S17,"")
A48: BT1 | B48: Building Teams & Leadership | C48: YES | D48: Competence & compliance | E48: Risk reduction; improved leadership | F48: Partial ad-hoc training coverage | G48: OPEX | H48: End of March End of June End of Sept | I48: Amer | J48: Medium | K48: High | L48: 46203 | M48: =IF('Building Teams & Leadership'!K3<>"",'Building Teams & Leadership'!K3,"") -> Train all leads in leadership, governance & safeguarding | N48: =IF('Building Teams & Leadership'!L3<>"",'Building Teams & Leadership'!L3,"") -> 1 | O48: =IF('Building Teams & Leadership'!M3<>"",'Building Teams & Leadership'!M3,"") -> Book courses; track completion | P48: =IF('Building Teams & Leadership'!N3<>"",'Building Teams & Leadership'!N3,"") -> Yusra training starting 18/01/26 | Q48: =IF('Building Teams & Leadership'!O3<>"",'Building Teams & Leadership'!O3,"") -> Leasdership development programme 8 half day sessions over 6-12 months | R48: =IF('Building Teams & Leadership'!P3<>"",'Building Teams & Leadership'!P3,"") -> In Progress | S48: =IF('Building Teams & Leadership'!Q3<>"",'Building Teams & Leadership'!Q3,"") | T48: =IF('Building Teams & Leadership'!R3<>"",'Building Teams & Leadership'!R3,"") -> 0.6 | U48: =IF('Building Teams & Leadership'!S3<>"",'Building Teams & Leadership'!S3,"") -> To reconvene after Ramadan. Traing resumed Fri 1st May. However poor attendance (6 delegetes) Agreed with trainer Shahid to consider hybrid delivery of next session to encourage more attendees. Online Zoom training delivered Sat 20th June successfully with 2 attendees including most Leads and some team members. Good feedback and training well received. Will speak to Shahid at Yusra training to see how this can be delivered for the remaining sessions. Recent online scheduled session July 18th postponed as trainer's wife unwell. To re-organise.
A49: BT2 | B49: Building Teams & Leadership | C49: YES | D49: Onboarding excellence | E49: Faster integration; safety | F49: Onboarding is informal | G49: OPEX | H49: End of March End of June End of Sept | I49: Amer | J49: Low | K49: Medium | L49: 46142 | M49: =IF('Building Teams & Leadership'!K4<>"",'Building Teams & Leadership'!K4,"") -> Structured induction pack and build a process to align volunteers to roles | N49: =IF('Building Teams & Leadership'!L4<>"",'Building Teams & Leadership'!L4,"") -> 5 | O49: =IF('Building Teams & Leadership'!M4<>"",'Building Teams & Leadership'!M4,"") -> Checklist; DBS; H&S; first aid; handbook | P49: =IF('Building Teams & Leadership'!N4<>"",'Building Teams & Leadership'!N4,"") -> Will need to liase with Ali to organise DBS, 1st Aid and staff handbook | Q49: =IF('Building Teams & Leadership'!O4<>"",'Building Teams & Leadership'!O4,"") -> No communication from Ali regarding staff handbook | R49: =IF('Building Teams & Leadership'!P4<>"",'Building Teams & Leadership'!P4,"") -> In Progress | S49: =IF('Building Teams & Leadership'!Q4<>"",'Building Teams & Leadership'!Q4,"") -> Ali has already DBS several leads. | T49: =IF('Building Teams & Leadership'!R4<>"",'Building Teams & Leadership'!R4,"") -> 0.3 | U49: =IF('Building Teams & Leadership'!S4<>"",'Building Teams & Leadership'!S4,"") -> Faridah has notified me of her stepping down from AEC duties including OPEX and Leads Utd from 30th March. Conversation with Shaffiq regarding Perkbox. Have messaged Br Behzat with proposal and is being considered. After further discussion, Perkbox has been parked as not enough interest generated for this platform. Flick still to be considered for recording of volunteer training and documentation. Spoken to Ali rearding taking over the helm of Leads Utd. Ali has now led a couple of meetings asking for monthly updates from the leads. Amer will coninue leading OPEX onboarding volunteers and organising training.
A50: BT3 | B50: Building Teams & Leadership | C50: YES | D50: Volunteer attraction and retention | E50: Staff retention & morale | F50: Volunteers praised by Leaders, Volunteer yearly event | G50: OPEX | H50: End of March End of June End of Sept | I50: Amer | J50: Medium | K50: High | L50: 46053 | M50: =IF('Building Teams & Leadership'!K5<>"",'Building Teams & Leadership'!K5,"") -> Volunteer recognition & retention programme. considering Perkbox and other reward schemes. | N50: =IF('Building Teams & Leadership'!L5<>"",'Building Teams & Leadership'!L5,"") -> 3 | O50: =IF('Building Teams & Leadership'!M5<>"",'Building Teams & Leadership'!M5,"") -> Badges/PerkBox Dinner/awards; Yusra training | P50: =IF('Building Teams & Leadership'!N5<>"",'Building Teams & Leadership'!N5,"") -> 1.Training starting 18.01.26 2. volunteer dinner to be arranged post ramadan 01.04.26 3. Badges/lanyards 30.03.26 | Q50: =IF('Building Teams & Leadership'!O5<>"",'Building Teams & Leadership'!O5,"") -> Amer to arrange sponsors and speakers for post Ramadan volunteer dinner as per last year. Following a thank you dinner at AEC arranged by Shaffiq and Shazli, I have separated the Leads award ceremony into the 'MOscars' to be held in the first week in April or first week of June. Families of leads to also be invited to acknowledge their support in the process. | R50: =IF('Building Teams & Leadership'!P5<>"",'Building Teams & Leadership'!P5,"") -> In Progress | S50: =IF('Building Teams & Leadership'!Q5<>"",'Building Teams & Leadership'!Q5,"") -> We did see some new voliunteers sign up at Ramadan but these were drated in the 'Ramadan group' headed by Br Tauffique and Br Shazli who are notably not part of Leads Utd and contunues to be a bone of contention. | T50: =IF('Building Teams & Leadership'!R5<>"",'Building Teams & Leadership'!R5,"") -> 0.8 | U50: =IF('Building Teams & Leadership'!S5<>"",'Building Teams & Leadership'!S5,"") -> sponsors to include Abrahams, Cuppa Chai, Langthorne Pharmacy, Garden Square Denta, Kayi Crossfit. MOSCARS Lead Volunteer awards ceremony delivered successfully. Some excellent feedback from this especially with encoragement for youth memebers. Consideration for these youth members to form a youth council or shadow directors committee. Afsor has stepped back from youth activitie for now due to personal reasons. Will need to organise youth board meeting.
A51: BT4 | B51: Building Teams & Leadership | C51: YES | D51: Improved performance in key areas | E51: Make important functions work better, prevent burnout | F51: Digital, Marketing and Outreach teams limited human resources | G51: OPEX | H51: End of March End of June End of Sept | I51: Amer | J51: High | K51: High | L51: 46203 | M51: =IF('Building Teams & Leadership'!K6<>"",'Building Teams & Leadership'!K6,"") -> Increase volunteers in Digital, Marketing and Outreach Teams | N51: =IF('Building Teams & Leadership'!L6<>"",'Building Teams & Leadership'!L6,"") -> 3 | O51: =IF('Building Teams & Leadership'!M6<>"",'Building Teams & Leadership'!M6,"") -> Role profiles; mentoring; appraisal process | P51: =IF('Building Teams & Leadership'!N6<>"",'Building Teams & Leadership'!N6,"") -> Volunteer drive during Ramadan | Q51: =IF('Building Teams & Leadership'!O6<>"",'Building Teams & Leadership'!O6,"") -> Request Imam to advertise volunteer rercuitment during Ramadan | R51: =IF('Building Teams & Leadership'!P6<>"",'Building Teams & Leadership'!P6,"") -> In Progress | S51: =IF('Building Teams & Leadership'!Q6<>"",'Building Teams & Leadership'!Q6,"") -> Imam has his own ideasabout volunteer training. He has run some Zoom online training session pre-Ramadan. | T51: =IF('Building Teams & Leadership'!R6<>"",'Building Teams & Leadership'!R6,"") -> 0.5 | U51: =IF('Building Teams & Leadership'!S6<>"",'Building Teams & Leadership'!S6,"") -> Imam Ossama had mentioned volunteers for Ramadan at Jummah Khutbah . After the departure of Imam Ossama we have not as yet led a volunteer drive but individiual gropups are reaching out to theoir own networks to recruit eg dawah project Ahmed Rawi. Still need top recruit further for SEND Tech team, and Scouts following imminent departure of Saira who is currently Lead.
A52: BT5 | M52: =IF('Building Teams & Leadership'!K7<>"",'Building Teams & Leadership'!K7,"") | N52: =IF('Building Teams & Leadership'!L7<>"",'Building Teams & Leadership'!L7,"") | O52: =IF('Building Teams & Leadership'!M7<>"",'Building Teams & Leadership'!M7,"") | P52: =IF('Building Teams & Leadership'!N7<>"",'Building Teams & Leadership'!N7,"") | Q52: =IF('Building Teams & Leadership'!O7<>"",'Building Teams & Leadership'!O7,"") | R52: =IF('Building Teams & Leadership'!P7<>"",'Building Teams & Leadership'!P7,"") | S52: =IF('Building Teams & Leadership'!Q7<>"",'Building Teams & Leadership'!Q7,"") | T52: =IF('Building Teams & Leadership'!R7<>"",'Building Teams & Leadership'!R7,"") | U52: =IF('Building Teams & Leadership'!S7<>"",'Building Teams & Leadership'!S7,"")
A53: BT6 | M53: =IF('Building Teams & Leadership'!K8<>"",'Building Teams & Leadership'!K8,"") | N53: =IF('Building Teams & Leadership'!L8<>"",'Building Teams & Leadership'!L8,"") | O53: =IF('Building Teams & Leadership'!M8<>"",'Building Teams & Leadership'!M8,"") | P53: =IF('Building Teams & Leadership'!N8<>"",'Building Teams & Leadership'!N8,"") | Q53: =IF('Building Teams & Leadership'!O8<>"",'Building Teams & Leadership'!O8,"") | R53: =IF('Building Teams & Leadership'!P8<>"",'Building Teams & Leadership'!P8,"") | S53: =IF('Building Teams & Leadership'!Q8<>"",'Building Teams & Leadership'!Q8,"") | T53: =IF('Building Teams & Leadership'!R8<>"",'Building Teams & Leadership'!R8,"") | U53: =IF('Building Teams & Leadership'!S8<>"",'Building Teams & Leadership'!S8,"")
A54: BT7 | M54: =IF('Building Teams & Leadership'!K9<>"",'Building Teams & Leadership'!K9,"") | N54: =IF('Building Teams & Leadership'!L9<>"",'Building Teams & Leadership'!L9,"") | O54: =IF('Building Teams & Leadership'!M9<>"",'Building Teams & Leadership'!M9,"") | P54: =IF('Building Teams & Leadership'!N9<>"",'Building Teams & Leadership'!N9,"") | Q54: =IF('Building Teams & Leadership'!O9<>"",'Building Teams & Leadership'!O9,"") | R54: =IF('Building Teams & Leadership'!P9<>"",'Building Teams & Leadership'!P9,"") | S54: =IF('Building Teams & Leadership'!Q9<>"",'Building Teams & Leadership'!Q9,"") | T54: =IF('Building Teams & Leadership'!R9<>"",'Building Teams & Leadership'!R9,"") | U54: =IF('Building Teams & Leadership'!S9<>"",'Building Teams & Leadership'!S9,"")
A55: BT8 | M55: =IF('Building Teams & Leadership'!K10<>"",'Building Teams & Leadership'!K10,"") | N55: =IF('Building Teams & Leadership'!L10<>"",'Building Teams & Leadership'!L10,"") | O55: =IF('Building Teams & Leadership'!M10<>"",'Building Teams & Leadership'!M10,"") | P55: =IF('Building Teams & Leadership'!N10<>"",'Building Teams & Leadership'!N10,"") | Q55: =IF('Building Teams & Leadership'!O10<>"",'Building Teams & Leadership'!O10,"") | R55: =IF('Building Teams & Leadership'!P10<>"",'Building Teams & Leadership'!P10,"") | S55: =IF('Building Teams & Leadership'!Q10<>"",'Building Teams & Leadership'!Q10,"") | T55: =IF('Building Teams & Leadership'!R10<>"",'Building Teams & Leadership'!R10,"") | U55: =IF('Building Teams & Leadership'!S10<>"",'Building Teams & Leadership'!S10,"")
A56: BT9 | M56: =IF('Building Teams & Leadership'!K11<>"",'Building Teams & Leadership'!K11,"") | N56: =IF('Building Teams & Leadership'!L11<>"",'Building Teams & Leadership'!L11,"") | O56: =IF('Building Teams & Leadership'!M11<>"",'Building Teams & Leadership'!M11,"") | P56: =IF('Building Teams & Leadership'!N11<>"",'Building Teams & Leadership'!N11,"") | Q56: =IF('Building Teams & Leadership'!O11<>"",'Building Teams & Leadership'!O11,"") | R56: =IF('Building Teams & Leadership'!P11<>"",'Building Teams & Leadership'!P11,"") | S56: =IF('Building Teams & Leadership'!Q11<>"",'Building Teams & Leadership'!Q11,"") | T56: =IF('Building Teams & Leadership'!R11<>"",'Building Teams & Leadership'!R11,"") | U56: =IF('Building Teams & Leadership'!S11<>"",'Building Teams & Leadership'!S11,"")
A57: BT10 | M57: =IF('Building Teams & Leadership'!K12<>"",'Building Teams & Leadership'!K12,"") | N57: =IF('Building Teams & Leadership'!L12<>"",'Building Teams & Leadership'!L12,"") | O57: =IF('Building Teams & Leadership'!M12<>"",'Building Teams & Leadership'!M12,"") | P57: =IF('Building Teams & Leadership'!N12<>"",'Building Teams & Leadership'!N12,"") | Q57: =IF('Building Teams & Leadership'!O12<>"",'Building Teams & Leadership'!O12,"") | R57: =IF('Building Teams & Leadership'!P12<>"",'Building Teams & Leadership'!P12,"") | S57: =IF('Building Teams & Leadership'!Q12<>"",'Building Teams & Leadership'!Q12,"") | T57: =IF('Building Teams & Leadership'!R12<>"",'Building Teams & Leadership'!R12,"") | U57: =IF('Building Teams & Leadership'!S12<>"",'Building Teams & Leadership'!S12,"")
A58: BT11 | M58: =IF('Building Teams & Leadership'!K13<>"",'Building Teams & Leadership'!K13,"") | N58: =IF('Building Teams & Leadership'!L13<>"",'Building Teams & Leadership'!L13,"") | O58: =IF('Building Teams & Leadership'!M13<>"",'Building Teams & Leadership'!M13,"") | P58: =IF('Building Teams & Leadership'!N13<>"",'Building Teams & Leadership'!N13,"") | Q58: =IF('Building Teams & Leadership'!O13<>"",'Building Teams & Leadership'!O13,"") | R58: =IF('Building Teams & Leadership'!P13<>"",'Building Teams & Leadership'!P13,"") | S58: =IF('Building Teams & Leadership'!Q13<>"",'Building Teams & Leadership'!Q13,"") | T58: =IF('Building Teams & Leadership'!R13<>"",'Building Teams & Leadership'!R13,"") | U58: =IF('Building Teams & Leadership'!S13<>"",'Building Teams & Leadership'!S13,"")
A59: BT12 | M59: =IF('Building Teams & Leadership'!K14<>"",'Building Teams & Leadership'!K14,"") | N59: =IF('Building Teams & Leadership'!L14<>"",'Building Teams & Leadership'!L14,"") | O59: =IF('Building Teams & Leadership'!M14<>"",'Building Teams & Leadership'!M14,"") | P59: =IF('Building Teams & Leadership'!N14<>"",'Building Teams & Leadership'!N14,"") | Q59: =IF('Building Teams & Leadership'!O14<>"",'Building Teams & Leadership'!O14,"") | R59: =IF('Building Teams & Leadership'!P14<>"",'Building Teams & Leadership'!P14,"") | S59: =IF('Building Teams & Leadership'!Q14<>"",'Building Teams & Leadership'!Q14,"") | T59: =IF('Building Teams & Leadership'!R14<>"",'Building Teams & Leadership'!R14,"") | U59: =IF('Building Teams & Leadership'!S14<>"",'Building Teams & Leadership'!S14,"")
A60: BT13 | M60: =IF('Building Teams & Leadership'!K15<>"",'Building Teams & Leadership'!K15,"") | N60: =IF('Building Teams & Leadership'!L15<>"",'Building Teams & Leadership'!L15,"") | O60: =IF('Building Teams & Leadership'!M15<>"",'Building Teams & Leadership'!M15,"") | P60: =IF('Building Teams & Leadership'!N15<>"",'Building Teams & Leadership'!N15,"") | Q60: =IF('Building Teams & Leadership'!O15<>"",'Building Teams & Leadership'!O15,"") | R60: =IF('Building Teams & Leadership'!P15<>"",'Building Teams & Leadership'!P15,"") | S60: =IF('Building Teams & Leadership'!Q15<>"",'Building Teams & Leadership'!Q15,"") | T60: =IF('Building Teams & Leadership'!R15<>"",'Building Teams & Leadership'!R15,"") | U60: =IF('Building Teams & Leadership'!S15<>"",'Building Teams & Leadership'!S15,"")
A61: BT14 | M61: =IF('Building Teams & Leadership'!K16<>"",'Building Teams & Leadership'!K16,"") | N61: =IF('Building Teams & Leadership'!L16<>"",'Building Teams & Leadership'!L16,"") | O61: =IF('Building Teams & Leadership'!M16<>"",'Building Teams & Leadership'!M16,"") | P61: =IF('Building Teams & Leadership'!N16<>"",'Building Teams & Leadership'!N16,"") | Q61: =IF('Building Teams & Leadership'!O16<>"",'Building Teams & Leadership'!O16,"") | R61: =IF('Building Teams & Leadership'!P16<>"",'Building Teams & Leadership'!P16,"") | S61: =IF('Building Teams & Leadership'!Q16<>"",'Building Teams & Leadership'!Q16,"") | T61: =IF('Building Teams & Leadership'!R16<>"",'Building Teams & Leadership'!R16,"") | U61: =IF('Building Teams & Leadership'!S16<>"",'Building Teams & Leadership'!S16,"")
A62: BT15 | M62: =IF('Building Teams & Leadership'!K17<>"",'Building Teams & Leadership'!K17,"") | N62: =IF('Building Teams & Leadership'!L17<>"",'Building Teams & Leadership'!L17,"") | O62: =IF('Building Teams & Leadership'!M17<>"",'Building Teams & Leadership'!M17,"") | P62: =IF('Building Teams & Leadership'!N17<>"",'Building Teams & Leadership'!N17,"") | Q62: =IF('Building Teams & Leadership'!O17<>"",'Building Teams & Leadership'!O17,"") | R62: =IF('Building Teams & Leadership'!P17<>"",'Building Teams & Leadership'!P17,"") | S62: =IF('Building Teams & Leadership'!Q17<>"",'Building Teams & Leadership'!Q17,"") | T62: =IF('Building Teams & Leadership'!R17<>"",'Building Teams & Leadership'!R17,"") | U62: =IF('Building Teams & Leadership'!S17<>"",'Building Teams & Leadership'!S17,"")
A63: CA1 | B63: Community Activities | C63: YES | D63: Vibrant Events Calendar | E63: Cohesion & visibility | F63: Approx. 6 activities per year; decentralised planning; limited follow-up/feedback loops | G63: Events | H63: End of March End of June End of Sept | I63: Avais | J63: Medium | K63: Medium | L63: 46295 | M63: =IF('Community Activities'!K3<>"",'Community Activities'!K3,"") -> Deliver 10 high-impact events. Quarterly themes; partnerships; family focus | N63: =IF('Community Activities'!L3<>"",'Community Activities'!L3,"") -> 6 | O63: =IF('Community Activities'!M3<>"",'Community Activities'!M3,"") -> Big ticket events: Community and Neighbour Consultations, Eids,Volunteer thank you, Mosque Fayre, family BBQ, talks. Communicate these through calendar, newsletters and Annual Report | P63: =IF('Community Activities'!N3<>"",'Community Activities'!N3,"") | Q63: =IF('Community Activities'!O3<>"",'Community Activities'!O3,"") | R63: =IF('Community Activities'!P3<>"",'Community Activities'!P3,"") -> In Progress | S63: =IF('Community Activities'!Q3<>"",'Community Activities'!Q3,"") | T63: =IF('Community Activities'!R3<>"",'Community Activities'!R3,"") -> 0.7 | U63: =IF('Community Activities'!S3<>"",'Community Activities'!S3,"") -> Events wise, structure, lot of good things. Big community events we need to now plan post ramadan.
A64: CA2 | B64: Community Activities | C64: YES | D64: Attendance growth | E64: Broader engagement | F64: Approx. 6 activities per year; decentralised planning; limited follow-up/feedback loops | G64: Marketing | H64: End of March End of June End of Sept | I64: Ameera | J64: Medium | K64: Medium | L64: 46295 | M64: =IF('Community Activities'!K4<>"",'Community Activities'!K4,"") -> Strengthen visibility and engagement of community activities via social media and WhatsApp, contributing to at least a 25% increase in event attendance vs 2025 baseline | N64: =IF('Community Activities'!L4<>"",'Community Activities'!L4,"") -> 3 | O64: =IF('Community Activities'!M4<>"",'Community Activities'!M4,"") -> 1. Coordinated social media & WhatsApp promotion for all major community events. 2. Published and regularly updated community events calendar (online and/or on-site). 3. Systematic post-event feedback and attendance tracking after major events. | P64: =IF('Community Activities'!N4<>"",'Community Activities'!N4,"") -> Jan 2026: Initial coordinated promotion in place + draft calendar created. Feb 2026: Online calendar live and used for Ramadan communications. Jun 2026: Regular promotion embedded + feedback piloted. Sept 2026: Approach fully embedded with systematic feedback and attendance tracking. | Q64: =IF('Community Activities'!O4<>"",'Community Activities'!O4,"") -> Work with the Events Team to coordinate promotion of major community activities via social media and WhatsApp; work with the Digital Team to maintain an up-to-date online events calendar; and support the rollout of simple post-event feedback and attendance tracking. | R64: =IF('Community Activities'!P4<>"",'Community Activities'!P4,"") -> In Progress | S64: =IF('Community Activities'!Q4<>"",'Community Activities'!Q4,"") | T64: =IF('Community Activities'!R4<>"",'Community Activities'!R4,"") -> 0.7 | U64: =IF('Community Activities'!S4<>"",'Community Activities'!S4,"") -> Ramadan programme successfully delivered with very strong attendance and engagement; mosque consistently full across key events. Coordinated promotion via WhatsApp and social media, supported by live events calendar. Positive feedback and compliments received from the community
A65: CA3 | B65: Community Activities | C65: YES | D65: Events well advertised and attended | E65: Increased event attendance,staff booking system | F65: No calendar currently available | G65: Tech | H65: End of March End of June End of Sept | I65: Khaleeq | J65: High | K65: High | L65: 46173 | M65: =IF('Community Activities'!K5<>"",'Community Activities'!K5,"") -> Clear electronic calendar of events for staff and community to see/access | N65: =IF('Community Activities'!L5<>"",'Community Activities'!L5,"") -> 3 | O65: =IF('Community Activities'!M5<>"",'Community Activities'!M5,"") -> 1. Set up calendars 2. Integrate 3. Share | P65: =IF('Community Activities'!N5<>"",'Community Activities'!N5,"") -> 1. Jan 2.Jan 3. Feb | Q65: =IF('Community Activities'!O5<>"",'Community Activities'!O5,"") | R65: =IF('Community Activities'!P5<>"",'Community Activities'!P5,"") -> In Progress | S65: =IF('Community Activities'!Q5<>"",'Community Activities'!Q5,"") | T65: =IF('Community Activities'!R5<>"",'Community Activities'!R5,"") -> 0.7 | U65: =IF('Community Activities'!S5<>"",'Community Activities'!S5,"")
A66: CA4 | M66: =IF('Community Activities'!K6<>"",'Community Activities'!K6,"") | N66: =IF('Community Activities'!L6<>"",'Community Activities'!L6,"") | O66: =IF('Community Activities'!M6<>"",'Community Activities'!M6,"") | P66: =IF('Community Activities'!N6<>"",'Community Activities'!N6,"") | Q66: =IF('Community Activities'!O6<>"",'Community Activities'!O6,"") | R66: =IF('Community Activities'!P6<>"",'Community Activities'!P6,"") | S66: =IF('Community Activities'!Q6<>"",'Community Activities'!Q6,"") | T66: =IF('Community Activities'!R6<>"",'Community Activities'!R6,"") | U66: =IF('Community Activities'!S6<>"",'Community Activities'!S6,"")
A67: CA5 | M67: =IF('Community Activities'!K7<>"",'Community Activities'!K7,"") | N67: =IF('Community Activities'!L7<>"",'Community Activities'!L7,"") | O67: =IF('Community Activities'!M7<>"",'Community Activities'!M7,"") | P67: =IF('Community Activities'!N7<>"",'Community Activities'!N7,"") | Q67: =IF('Community Activities'!O7<>"",'Community Activities'!O7,"") | R67: =IF('Community Activities'!P7<>"",'Community Activities'!P7,"") | S67: =IF('Community Activities'!Q7<>"",'Community Activities'!Q7,"") | T67: =IF('Community Activities'!R7<>"",'Community Activities'!R7,"") | U67: =IF('Community Activities'!S7<>"",'Community Activities'!S7,"")
A68: CA6 | M68: =IF('Community Activities'!K8<>"",'Community Activities'!K8,"") | N68: =IF('Community Activities'!L8<>"",'Community Activities'!L8,"") | O68: =IF('Community Activities'!M8<>"",'Community Activities'!M8,"") | P68: =IF('Community Activities'!N8<>"",'Community Activities'!N8,"") | Q68: =IF('Community Activities'!O8<>"",'Community Activities'!O8,"") | R68: =IF('Community Activities'!P8<>"",'Community Activities'!P8,"") | S68: =IF('Community Activities'!Q8<>"",'Community Activities'!Q8,"") | T68: =IF('Community Activities'!R8<>"",'Community Activities'!R8,"") | U68: =IF('Community Activities'!S8<>"",'Community Activities'!S8,"")
A69: CA7 | M69: =IF('Community Activities'!K9<>"",'Community Activities'!K9,"") | N69: =IF('Community Activities'!L9<>"",'Community Activities'!L9,"") | O69: =IF('Community Activities'!M9<>"",'Community Activities'!M9,"") | P69: =IF('Community Activities'!N9<>"",'Community Activities'!N9,"") | Q69: =IF('Community Activities'!O9<>"",'Community Activities'!O9,"") | R69: =IF('Community Activities'!P9<>"",'Community Activities'!P9,"") | S69: =IF('Community Activities'!Q9<>"",'Community Activities'!Q9,"") | T69: =IF('Community Activities'!R9<>"",'Community Activities'!R9,"") | U69: =IF('Community Activities'!S9<>"",'Community Activities'!S9,"")
A70: CA8 | M70: =IF('Community Activities'!K10<>"",'Community Activities'!K10,"") | N70: =IF('Community Activities'!L10<>"",'Community Activities'!L10,"") | O70: =IF('Community Activities'!M10<>"",'Community Activities'!M10,"") | P70: =IF('Community Activities'!N10<>"",'Community Activities'!N10,"") | Q70: =IF('Community Activities'!O10<>"",'Community Activities'!O10,"") | R70: =IF('Community Activities'!P10<>"",'Community Activities'!P10,"") | S70: =IF('Community Activities'!Q10<>"",'Community Activities'!Q10,"") | T70: =IF('Community Activities'!R10<>"",'Community Activities'!R10,"") | U70: =IF('Community Activities'!S10<>"",'Community Activities'!S10,"")
A71: CA9 | M71: =IF('Community Activities'!K11<>"",'Community Activities'!K11,"") | N71: =IF('Community Activities'!L11<>"",'Community Activities'!L11,"") | O71: =IF('Community Activities'!M11<>"",'Community Activities'!M11,"") | P71: =IF('Community Activities'!N11<>"",'Community Activities'!N11,"") | Q71: =IF('Community Activities'!O11<>"",'Community Activities'!O11,"") | R71: =IF('Community Activities'!P11<>"",'Community Activities'!P11,"") | S71: =IF('Community Activities'!Q11<>"",'Community Activities'!Q11,"") | T71: =IF('Community Activities'!R11<>"",'Community Activities'!R11,"") | U71: =IF('Community Activities'!S11<>"",'Community Activities'!S11,"")
A72: CA10 | M72: =IF('Community Activities'!K12<>"",'Community Activities'!K12,"") | N72: =IF('Community Activities'!L12<>"",'Community Activities'!L12,"") | O72: =IF('Community Activities'!M12<>"",'Community Activities'!M12,"") | P72: =IF('Community Activities'!N12<>"",'Community Activities'!N12,"") | Q72: =IF('Community Activities'!O12<>"",'Community Activities'!O12,"") | R72: =IF('Community Activities'!P12<>"",'Community Activities'!P12,"") | S72: =IF('Community Activities'!Q12<>"",'Community Activities'!Q12,"") | T72: =IF('Community Activities'!R12<>"",'Community Activities'!R12,"") | U72: =IF('Community Activities'!S12<>"",'Community Activities'!S12,"")
A73: CA11 | M73: =IF('Community Activities'!K13<>"",'Community Activities'!K13,"") | N73: =IF('Community Activities'!L13<>"",'Community Activities'!L13,"") | O73: =IF('Community Activities'!M13<>"",'Community Activities'!M13,"") | P73: =IF('Community Activities'!N13<>"",'Community Activities'!N13,"") | Q73: =IF('Community Activities'!O13<>"",'Community Activities'!O13,"") | R73: =IF('Community Activities'!P13<>"",'Community Activities'!P13,"") | S73: =IF('Community Activities'!Q13<>"",'Community Activities'!Q13,"") | T73: =IF('Community Activities'!R13<>"",'Community Activities'!R13,"") | U73: =IF('Community Activities'!S13<>"",'Community Activities'!S13,"")
A74: CA12 | M74: =IF('Community Activities'!K14<>"",'Community Activities'!K14,"") | N74: =IF('Community Activities'!L14<>"",'Community Activities'!L14,"") | O74: =IF('Community Activities'!M14<>"",'Community Activities'!M14,"") | P74: =IF('Community Activities'!N14<>"",'Community Activities'!N14,"") | Q74: =IF('Community Activities'!O14<>"",'Community Activities'!O14,"") | R74: =IF('Community Activities'!P14<>"",'Community Activities'!P14,"") | S74: =IF('Community Activities'!Q14<>"",'Community Activities'!Q14,"") | T74: =IF('Community Activities'!R14<>"",'Community Activities'!R14,"") | U74: =IF('Community Activities'!S14<>"",'Community Activities'!S14,"")
A75: CA13 | M75: =IF('Community Activities'!K15<>"",'Community Activities'!K15,"") | N75: =IF('Community Activities'!L15<>"",'Community Activities'!L15,"") | O75: =IF('Community Activities'!M15<>"",'Community Activities'!M15,"") | P75: =IF('Community Activities'!N15<>"",'Community Activities'!N15,"") | Q75: =IF('Community Activities'!O15<>"",'Community Activities'!O15,"") | R75: =IF('Community Activities'!P15<>"",'Community Activities'!P15,"") | S75: =IF('Community Activities'!Q15<>"",'Community Activities'!Q15,"") | T75: =IF('Community Activities'!R15<>"",'Community Activities'!R15,"") | U75: =IF('Community Activities'!S15<>"",'Community Activities'!S15,"")
A76: CA14 | M76: =IF('Community Activities'!K16<>"",'Community Activities'!K16,"") | N76: =IF('Community Activities'!L16<>"",'Community Activities'!L16,"") | O76: =IF('Community Activities'!M16<>"",'Community Activities'!M16,"") | P76: =IF('Community Activities'!N16<>"",'Community Activities'!N16,"") | Q76: =IF('Community Activities'!O16<>"",'Community Activities'!O16,"") | R76: =IF('Community Activities'!P16<>"",'Community Activities'!P16,"") | S76: =IF('Community Activities'!Q16<>"",'Community Activities'!Q16,"") | T76: =IF('Community Activities'!R16<>"",'Community Activities'!R16,"") | U76: =IF('Community Activities'!S16<>"",'Community Activities'!S16,"")
A77: CA15 | M77: =IF('Community Activities'!K17<>"",'Community Activities'!K17,"") | N77: =IF('Community Activities'!L17<>"",'Community Activities'!L17,"") | O77: =IF('Community Activities'!M17<>"",'Community Activities'!M17,"") | P77: =IF('Community Activities'!N17<>"",'Community Activities'!N17,"") | Q77: =IF('Community Activities'!O17<>"",'Community Activities'!O17,"") | R77: =IF('Community Activities'!P17<>"",'Community Activities'!P17,"") | S77: =IF('Community Activities'!Q17<>"",'Community Activities'!Q17,"") | T77: =IF('Community Activities'!R17<>"",'Community Activities'!R17,"") | U77: =IF('Community Activities'!S17<>"",'Community Activities'!S17,"")
A78: SF1 | B78: Spiritual Focus | C78: YES | D78: Learning & practice | E78: Deeper community spirituality | F78: Regular Jumu’ah/Ramadan programmes; limited modular learning beyond madrassa/occasional talks | G78: Islamic Affairs | H78: End of March End of June End of Sept | I78: Omar | J78: Medium | K78: Medium | L78: 46295 | M78: =IF('Spiritual Focus'!K3<>"",'Spiritual Focus'!K3,"") -> Increase participation in structured spiritual education by 30% by September 2026. | N78: =IF('Spiritual Focus'!L3<>"",'Spiritual Focus'!L3,"") -> 3 | O78: =IF('Spiritual Focus'!M3<>"",'Spiritual Focus'!M3,"") -> 1. Modular spiritual education courses introduced beyond Jumu’ah and Ramadan. 2. Family-friendly timings implemented to widen access to learning programmes. | P78: =IF('Spiritual Focus'!N3<>"",'Spiritual Focus'!N3,"") -> Jan 2026: Pilot modular spiritual education sessions (including Ramadan programmes). Jun 2026: Regular modular courses running with family-friendly timings. Sept 2026: Programme fully embedded with sustained and increased attendance. | Q78: =IF('Spiritual Focus'!O3<>"",'Spiritual Focus'!O3,"") -> Develop and deliver modular spiritual education programmes, building on existing classes and talks; introduce family-friendly timings and expand engagement with youth, children, and reverts. | R78: =IF('Spiritual Focus'!P3<>"",'Spiritual Focus'!P3,"") -> In Progress | S78: =IF('Spiritual Focus'!Q3<>"",'Spiritual Focus'!Q3,"") | T78: =IF('Spiritual Focus'!R3<>"",'Spiritual Focus'!R3,"") -> 0.9 | U78: =IF('Spiritual Focus'!S3<>"",'Spiritual Focus'!S3,"") -> 1. Weekly tafsir started June for all members of family 2. Sisters fortnightly halaqah started. 3. Youth 16-25 circle for men started. 4. Youth monthly q&a started. 5. Youth Rawa tales planned in June 6. Fajr club felt covers brothers circle 7. Guest khateebs Sh Ziyad and Sh Zubayr 8. Completed Ramadan and Dhul Hijjah social media reminders 9. In need of revert, youth sisters and 11-15 brothers 10. Possibly an Isha reminder (more appropriate for Imam)
A79: SF2 | B79: Spiritual Focus | C79: YES | D79: Regular themed lectures | E79: Accessible Islamic education | F79: Limited spiritual development to date | G79: Education | H79: End of March End of June End of Sept | I79: Omar | J79: Medium | K79: Medium | L79: 46142 | M79: =IF('Spiritual Focus'!#REF!<>"",'Spiritual Focus'!#REF!,"") -> #REF! | N79: =IF('Spiritual Focus'!#REF!<>"",'Spiritual Focus'!#REF!,"") -> #REF! | O79: =IF('Spiritual Focus'!#REF!<>"",'Spiritual Focus'!#REF!,"") -> #REF! | P79: =IF('Spiritual Focus'!#REF!<>"",'Spiritual Focus'!#REF!,"") -> #REF! | Q79: =IF('Spiritual Focus'!#REF!<>"",'Spiritual Focus'!#REF!,"") -> #REF! | R79: =IF('Spiritual Focus'!#REF!<>"",'Spiritual Focus'!#REF!,"") -> #REF! | S79: =IF('Spiritual Focus'!#REF!<>"",'Spiritual Focus'!#REF!,"") -> #REF! | T79: =IF('Spiritual Focus'!#REF!<>"",'Spiritual Focus'!#REF!,"") -> #REF! | U79: =IF('Spiritual Focus'!#REF!<>"",'Spiritual Focus'!#REF!,"") -> #REF!
A80: SF3 | B80: Spiritual Focus | C80: YES | D80: Community retreats | E80: Renewal & connection | F80: Limited spiritual development to date | G80: Islamic Affairs | H80: End of March End of June End of Sept | I80: Omar | J80: Medium | K80: Medium | L80: 46265 | M80: =IF('Spiritual Focus'!K6<>"",'Spiritual Focus'!K6,"") -> Deliver quarterly spiritual retreats and Qur’an reflection circles to strengthen community connection and spiritual growth by August 2026. | N80: =IF('Spiritual Focus'!L6<>"",'Spiritual Focus'!L6,"") -> 3 | O80: =IF('Spiritual Focus'!M6<>"",'Spiritual Focus'!M6,"") -> 1. Retreat structure and programme designed (including Qur’an reflection focus). 2. Logistics in place (venue, childcare, sign-ups). 3. First retreat delivered and model refined for ongoing quarterly delivery. | P80: =IF('Spiritual Focus'!N6<>"",'Spiritual Focus'!N6,"") -> Jan 2026: Retreat format and programme agreed. Jun 2026: First retreat delivered with logistics in place. Aug 2026: Quarterly retreat model embedded. | Q80: =IF('Spiritual Focus'!O6<>"",'Spiritual Focus'!O6,"") -> Plan and deliver quarterly retreats including Qur’an reflection sessions, ensuring accessibility through childcare and structured sign-up processes. | R80: =IF('Spiritual Focus'!P6<>"",'Spiritual Focus'!P6,"") -> In Progress | S80: =IF('Spiritual Focus'!Q6<>"",'Spiritual Focus'!Q6,"") | T80: =IF('Spiritual Focus'!R6<>"",'Spiritual Focus'!R6,"") -> 0.3 | U80: =IF('Spiritual Focus'!S6<>"",'Spiritual Focus'!S6,"") -> To consider embedding into camp retreat, or considering a youth excurcusion with reminders. Not yet ready for full education retreat given my time committments - potentially one for an incoming Imam
A81: SF4 | B81: Spiritual Focus | C81: YES | D81: Al-Qalam Madrassa expansion | E81: Education for young people in our community, development fo youth leaders | F81: Already have an established Madrassa | G81: Education | H81: End of March End of June End of Sept | I81: Omar | J81: Medium | K81: Medium | L81: 46295 | M81: =IF('Spiritual Focus'!K5<>"",'Spiritual Focus'!K5,"") -> Increase student numbers whilst maintaining educational standards | N81: =IF('Spiritual Focus'!L5<>"",'Spiritual Focus'!L5,"") -> 1 | O81: =IF('Spiritual Focus'!M5<>"",'Spiritual Focus'!M5,"") -> 1. New leadership team settled into roles 2. Move to Ravenswood secured by June 2026 | P81: =IF('Spiritual Focus'!N5<>"",'Spiritual Focus'!N5,"") -> 1. End of March 2. End of June | Q81: =IF('Spiritual Focus'!O5<>"",'Spiritual Focus'!O5,"") | R81: =IF('Spiritual Focus'!P5<>"",'Spiritual Focus'!P5,"") -> In Progress | S81: =IF('Spiritual Focus'!Q5<>"",'Spiritual Focus'!Q5,"") | T81: =IF('Spiritual Focus'!R5<>"",'Spiritual Focus'!R5,"") -> 0.8 | U81: =IF('Spiritual Focus'!S5<>"",'Spiritual Focus'!S5,"") -> Ravenswood move complete! Curriculum has been proposed, and being finalised. Omar to plan a meeting with teachers on this. Leadership team better place than last year, appears to have worked. Awaiting full report by next month. Awaiting open day and review of numbers in coming month.
A82: SF5 | B82: Spiritual Focus | C82: YES | D82: Learning & practice | E82: Deeper community spirituality | F82: Limited talks to date | G82: Islamic Affairs | H82: End of March End of June End of Sept | I82: Omar | J82: Medium | K82: Medium | L82: 46295 | M82: =IF('Spiritual Focus'!K4<>"",'Spiritual Focus'!K4,"") -> Deliver a consistent programme of small and large-scale talks for diverse demographics to increase engagement and spiritual understanding by September 2026. | N82: =IF('Spiritual Focus'!L4<>"",'Spiritual Focus'!L4,"") -> 4 | O82: =IF('Spiritual Focus'!M4<>"",'Spiritual Focus'!M4,"") -> 1. Monthly themed talks delivered for key demographics. 2. Guest speakers introduced for selected sessions. 3. Increased attendance and engagement across talk programmes. | P82: =IF('Spiritual Focus'!N4<>"",'Spiritual Focus'!N4,"") -> Jan 2026: Monthly talk structure established Jun 2026: Guest speakers and varied topics introduced Sept 2026: Programme embedded with strong attendance | Q82: =IF('Spiritual Focus'!O4<>"",'Spiritual Focus'!O4,"") -> Plan and deliver regular talks across different demographics, including khutbahs, short reminders, and guest sessions, to increase engagement and accessibility. | R82: =IF('Spiritual Focus'!P4<>"",'Spiritual Focus'!P4,"") -> In Progress | S82: =IF('Spiritual Focus'!Q4<>"",'Spiritual Focus'!Q4,"") | T82: =IF('Spiritual Focus'!R4<>"",'Spiritual Focus'!R4,"") -> 0.6 | U82: =IF('Spiritual Focus'!S4<>"",'Spiritual Focus'!S4,"") -> 1. Plan for September Ilm Essentials 1 year programme 2. Plan for Tajweed for ladies Sep and for Arabic ladies tajweed 3. Seeking a lead for Arabic and men's tajweed 4. Agreed regular marriage related talks 5. History talk 21st June 6. Planning riba talk with Ustadh Umer Sulaiman 7. Completed Ramadan and Hajj talks 8. Planning Mothers Quran group 9. Aim Khutbah delivery workshop by Sep 10. Planning a sisters q&a (either Omar or Imam) 11. Planning hifdh programme (Imam)
A83: SF7 | B83: Spiritual Focus | C83: YES | D83: Spiritual self- development | E83: Deeper individual spirituality | F83: Not formally developed | G83: Exec | H83: End of March End of June End of Sept | I83: Shaffiq | J83: Medium | K83: Medium | L83: 46295 | M83: =IF('Spiritual Focus'!K7<>"",'Spiritual Focus'!K7,"") -> A system which allows individual community members to begin a tracked, AI driven,journey starting from where they are, built upon the resources available at the masjid. Includes training, courses and volunteering | N83: =IF('Spiritual Focus'!L7<>"",'Spiritual Focus'!L7,"") -> 2 | O83: =IF('Spiritual Focus'!M7<>"",'Spiritual Focus'!M7,"") -> 1. Get MosqueApp running 2. Develop and deploy framework for personal self-development | P83: =IF('Spiritual Focus'!N7<>"",'Spiritual Focus'!N7,"") -> 1. Jan 2. Before Ramadhan | Q83: =IF('Spiritual Focus'!O7<>"",'Spiritual Focus'!O7,"") -> Found possible suitable provider. had second round meetings with him. Next steps: asked him for a one pager explaining his product, a one pager for my Education Lead, detailing Islamic education authenticity, and then we will meet to finalise the financials and how that works, and how to embed the product via ai to our masjid, its services, volunteering etc. Decided to launch via our website and not wait until app is completed. | R83: =IF('Spiritual Focus'!P7<>"",'Spiritual Focus'!P7,"") -> Delayed | S83: =IF('Spiritual Focus'!Q7<>"",'Spiritual Focus'!Q7,"") | T83: =IF('Spiritual Focus'!R7<>"",'Spiritual Focus'!R7,"") -> 0.6 | U83: =IF('Spiritual Focus'!S7<>"",'Spiritual Focus'!S7,"") -> Need Khalyfa guy to produce scholar endorsement and fine checking for educational content before we proceed any further
A84: SF8 | M84: =IF('Spiritual Focus'!K8<>"",'Spiritual Focus'!K8,"") | N84: =IF('Spiritual Focus'!L8<>"",'Spiritual Focus'!L8,"") | O84: =IF('Spiritual Focus'!M8<>"",'Spiritual Focus'!M8,"") | P84: =IF('Spiritual Focus'!N8<>"",'Spiritual Focus'!N8,"") | Q84: =IF('Spiritual Focus'!O8<>"",'Spiritual Focus'!O8,"") | R84: =IF('Spiritual Focus'!P8<>"",'Spiritual Focus'!P8,"") | S84: =IF('Spiritual Focus'!Q8<>"",'Spiritual Focus'!Q8,"") | T84: =IF('Spiritual Focus'!R8<>"",'Spiritual Focus'!R8,"") | U84: =IF('Spiritual Focus'!S8<>"",'Spiritual Focus'!S8,"")
A85: SF9 | M85: =IF('Spiritual Focus'!K9<>"",'Spiritual Focus'!K9,"") | N85: =IF('Spiritual Focus'!L9<>"",'Spiritual Focus'!L9,"") | O85: =IF('Spiritual Focus'!M9<>"",'Spiritual Focus'!M9,"") | P85: =IF('Spiritual Focus'!N9<>"",'Spiritual Focus'!N9,"") | Q85: =IF('Spiritual Focus'!O9<>"",'Spiritual Focus'!O9,"") | R85: =IF('Spiritual Focus'!P9<>"",'Spiritual Focus'!P9,"") | S85: =IF('Spiritual Focus'!Q9<>"",'Spiritual Focus'!Q9,"") | T85: =IF('Spiritual Focus'!R9<>"",'Spiritual Focus'!R9,"") | U85: =IF('Spiritual Focus'!S9<>"",'Spiritual Focus'!S9,"")
A86: SF10 | M86: =IF('Spiritual Focus'!K10<>"",'Spiritual Focus'!K10,"") | N86: =IF('Spiritual Focus'!L10<>"",'Spiritual Focus'!L10,"") | O86: =IF('Spiritual Focus'!M10<>"",'Spiritual Focus'!M10,"") | P86: =IF('Spiritual Focus'!N10<>"",'Spiritual Focus'!N10,"") | Q86: =IF('Spiritual Focus'!O10<>"",'Spiritual Focus'!O10,"") | R86: =IF('Spiritual Focus'!P10<>"",'Spiritual Focus'!P10,"") | S86: =IF('Spiritual Focus'!Q10<>"",'Spiritual Focus'!Q10,"") | T86: =IF('Spiritual Focus'!R10<>"",'Spiritual Focus'!R10,"") | U86: =IF('Spiritual Focus'!S10<>"",'Spiritual Focus'!S10,"")
A87: SF11 | M87: =IF('Spiritual Focus'!K11<>"",'Spiritual Focus'!K11,"") | N87: =IF('Spiritual Focus'!L11<>"",'Spiritual Focus'!L11,"") | O87: =IF('Spiritual Focus'!M11<>"",'Spiritual Focus'!M11,"") | P87: =IF('Spiritual Focus'!N11<>"",'Spiritual Focus'!N11,"") | Q87: =IF('Spiritual Focus'!O11<>"",'Spiritual Focus'!O11,"") | R87: =IF('Spiritual Focus'!P11<>"",'Spiritual Focus'!P11,"") | S87: =IF('Spiritual Focus'!Q11<>"",'Spiritual Focus'!Q11,"") | T87: =IF('Spiritual Focus'!R11<>"",'Spiritual Focus'!R11,"") | U87: =IF('Spiritual Focus'!S11<>"",'Spiritual Focus'!S11,"")
A88: SF12 | M88: =IF('Spiritual Focus'!K12<>"",'Spiritual Focus'!K12,"") | N88: =IF('Spiritual Focus'!L12<>"",'Spiritual Focus'!L12,"") | O88: =IF('Spiritual Focus'!M12<>"",'Spiritual Focus'!M12,"") | P88: =IF('Spiritual Focus'!N12<>"",'Spiritual Focus'!N12,"") | Q88: =IF('Spiritual Focus'!O12<>"",'Spiritual Focus'!O12,"") | R88: =IF('Spiritual Focus'!P12<>"",'Spiritual Focus'!P12,"") | S88: =IF('Spiritual Focus'!Q12<>"",'Spiritual Focus'!Q12,"") | T88: =IF('Spiritual Focus'!R12<>"",'Spiritual Focus'!R12,"") | U88: =IF('Spiritual Focus'!S12<>"",'Spiritual Focus'!S12,"")
A89: SF13 | M89: =IF('Spiritual Focus'!K13<>"",'Spiritual Focus'!K13,"") | N89: =IF('Spiritual Focus'!L13<>"",'Spiritual Focus'!L13,"") | O89: =IF('Spiritual Focus'!M13<>"",'Spiritual Focus'!M13,"") | P89: =IF('Spiritual Focus'!N13<>"",'Spiritual Focus'!N13,"") | Q89: =IF('Spiritual Focus'!O13<>"",'Spiritual Focus'!O13,"") | R89: =IF('Spiritual Focus'!P13<>"",'Spiritual Focus'!P13,"") | S89: =IF('Spiritual Focus'!Q13<>"",'Spiritual Focus'!Q13,"") | T89: =IF('Spiritual Focus'!R13<>"",'Spiritual Focus'!R13,"") | U89: =IF('Spiritual Focus'!S13<>"",'Spiritual Focus'!S13,"")
A90: SF14 | M90: =IF('Spiritual Focus'!K14<>"",'Spiritual Focus'!K14,"") | N90: =IF('Spiritual Focus'!L14<>"",'Spiritual Focus'!L14,"") | O90: =IF('Spiritual Focus'!M14<>"",'Spiritual Focus'!M14,"") | P90: =IF('Spiritual Focus'!N14<>"",'Spiritual Focus'!N14,"") | Q90: =IF('Spiritual Focus'!O14<>"",'Spiritual Focus'!O14,"") | R90: =IF('Spiritual Focus'!P14<>"",'Spiritual Focus'!P14,"") | S90: =IF('Spiritual Focus'!Q14<>"",'Spiritual Focus'!Q14,"") | T90: =IF('Spiritual Focus'!R14<>"",'Spiritual Focus'!R14,"") | U90: =IF('Spiritual Focus'!S14<>"",'Spiritual Focus'!S14,"")
A91: SF15 | M91: =IF('Spiritual Focus'!K15<>"",'Spiritual Focus'!K15,"") | N91: =IF('Spiritual Focus'!L15<>"",'Spiritual Focus'!L15,"") | O91: =IF('Spiritual Focus'!M15<>"",'Spiritual Focus'!M15,"") | P91: =IF('Spiritual Focus'!N15<>"",'Spiritual Focus'!N15,"") | Q91: =IF('Spiritual Focus'!O15<>"",'Spiritual Focus'!O15,"") | R91: =IF('Spiritual Focus'!P15<>"",'Spiritual Focus'!P15,"") | S91: =IF('Spiritual Focus'!Q15<>"",'Spiritual Focus'!Q15,"") | T91: =IF('Spiritual Focus'!R15<>"",'Spiritual Focus'!R15,"") | U91: =IF('Spiritual Focus'!S15<>"",'Spiritual Focus'!S15,"")

Sheet BDP-DR

Sheet OPEX Review Log
A1: Focus Area | B1: Stream | C1: Review Date | D1: Reviewed By | E1: Key Discussion Points / Decisions | F1: Actions Agreed | G1: Next Steps / Deadlines | H1: Person Responsible | I1: Date Closed | J1: OPEX Sign-Off
